Workbook

Sheet Dashboard
A1: Shaar Binyamin Gym — Cash-First Owner Dashboard
A2: Focus: what actually comes into the bank, what actually leaves, ending cash and debt. EBITDA, depreciation and DSCR remain in the detail tabs but are intentionally demoted here.
A4: Cash position & key levers
A5: Cash after build + VAT refund | B5: ='Startup & Funding'!B22 -> 160869.73 | C5: Cash reserve target | D5: =Inputs!B80 -> 150000 | E5: Opening debt | F5: =Inputs!B9+Inputs!B10 -> 1140000
A6: Lowest post-opening cash — current base | B6: =IFERROR(__xludf.DUMMYFUNCTION("MIN(FILTER('Owner Pay'!Z21:Z83,'Owner Pay'!C21:C83>0))"),126843.9333898304) -> 126843.93 | C6: Debt-free operating month — current base | D6: ='Owner Pay'!B9 -> 42 | E6: Normal monthly debt payment after grace | F6: =Financing!D10 -> 20881.221
A7: Year 1 modeled cash collected | B7: ='5-Year Summary'!B7 -> 998544 | C7: Year 1 net cash generated | D7: ='5-Year Summary'!B12 -> -10869.73 | E7: Year 1 ending bank cash | F7: ='5-Year Summary'!B14 -> 150000
A8: Year 5 ending bank cash | B8: ='5-Year Summary'!F14 -> 1802390.8 | C8: Year 5 debt remaining | D8: ='5-Year Summary'!F15 -> 0 | E8: Year 5 cash above reserve | F8: =MAX(0,'5-Year Summary'!F14-Inputs!B80) -> 1652390.8
A9: Owner payroll after debt-free | B9: ='Owner Pay'!B12 -> 24000 | C9: Current base owner-pay policy | D9: Debt-Max | E9: Alternative owner-pay scenarios | F9: See Salary Scenarios tab
A11: 5-Year Cash In / Cash Out
A12: Operating year | B12: Cash in — modeled collections | C12: Operating cash out | D12: Debt paid | E12: Tax paid | F12: Owner payroll | G12: Total cash out | H12: Net cash generated | I12: Ending bank cash | J12: Debt remaining | K12: End members
A13: Year 1 | B13: ='5-Year Summary'!B7 -> 998544 | C13: =B13-'5-Year Summary'!B9 -> 927747.25 | D13: ='5-Year Summary'!B10 -> 81666.476 | E13: ='5-Year Summary'!B11 -> 0 | F13: ='5-Year Summary'!B20 -> 0 | G13: =SUM(C13:F13) -> 1009413.7 | H13: =B13-G13 -> -10869.73 | I13: ='5-Year Summary'!B14 -> 150000 | J13: ='5-Year Summary'!B15 -> 1068862.7 | K13: ='5-Year Summary'!B6 -> 450
A14: Year 2 | B14: ='5-Year Summary'!C7 -> 1500294 | C14: =B14-'5-Year Summary'!C9 -> 1008537.5 | D14: ='5-Year Summary'!C10 -> 424218.24 | E14: ='5-Year Summary'!C11 -> 67538.255 | F14: ='5-Year Summary'!C20 -> 0 | G14: =SUM(C14:F14) -> 1500294 | H14: =B14-G14 -> 0 | I14: ='5-Year Summary'!C14 -> 150000 | J14: ='5-Year Summary'!C15 -> 679457.94 | K14: ='5-Year Summary'!C6 -> 600
A15: Year 3 | B15: ='5-Year Summary'!D7 -> 1864899 | C15: =B15-'5-Year Summary'!D9 -> 1067245.1 | D15: ='5-Year Summary'!D10 -> 636626.7 | E15: ='5-Year Summary'!D11 -> 161027.21 | F15: ='5-Year Summary'!D20 -> 0 | G15: =SUM(C15:F15) -> 1864899 | H15: =B15-G15 -> 0 | I15: ='5-Year Summary'!D14 -> 150000 | J15: ='5-Year Summary'!D15 -> 58610.857 | K15: ='5-Year Summary'!D6 -> 725
A16: Year 4 | B16: ='5-Year Summary'!E7 -> 2127147 | C16: =B16-'5-Year Summary'!E9 -> 1109471.5 | D16: ='5-Year Summary'!E10 -> 58610.857 | E16: ='5-Year Summary'!E11 -> 215261.49 | F16: ='5-Year Summary'!E20 -> 0 | G16: =SUM(C16:F16) -> 1383343.8 | H16: =B16-G16 -> 743803.18 | I16: ='5-Year Summary'!E14 -> 893803.18 | J16: ='5-Year Summary'!E15 -> 0 | K16: ='5-Year Summary'!E6 -> 800
A17: Year 5 | B17: ='5-Year Summary'!F7 -> 2291498 | C17: =B17-'5-Year Summary'!F9 -> 1135934.8 | D17: ='5-Year Summary'!F10 -> 0 | E17: ='5-Year Summary'!F11 -> 246975.66 | F17: ='5-Year Summary'!F20 -> 0 | G17: =SUM(C17:F17) -> 1382910.4 | H17: =B17-G17 -> 908587.57 | I17: ='5-Year Summary'!F14 -> 1802390.8 | J17: ='5-Year Summary'!F15 -> 0 | K17: ='5-Year Summary'!F6 -> 850
A18: Cash in is gross modeled collections. Operating cash out is the day-to-day gym cash cost, card fees and net VAT effect; debt, corporate tax and owner payroll are shown separately. This table is designed to reconcile cash in minus cash out to net cash generated.
A20: Owner-pay choices — cash impact
A21: Current base | B21: Debt-Max — no owner salary until debt-free; ₪10k gross each after. | C21: Debt-free op month | D21: ='Salary Scenarios'!B13 -> 42 | E21: Lowest post-opening cash | F21: ='Salary Scenarios'!B27 -> 126843.93
A22: Early Balanced | B22: ₪5k gross each from operating month 7; ₪10k each after debt-free. | C22: Debt-free op month | D22: ='Salary Scenarios'!E13 -> 47 | E22: Lowest post-opening cash | F22: ='Salary Scenarios'!E27 -> 89793.066
A23: Debt sweep rule | B23: Keep the ₪150k reserve target; every 6 months from operating month 12, use excess cash for a lump-sum debt payment.
A24: Distributions | B24: No automatic distributions. Cash stays in the company unless the owners decide otherwise after debt and reserve needs are considered.
A45: Readiness checklist before signing / opening
A46: Item | B46: Status | C46: Why it matters
A47: Bank confirms early-prepayment rules / fees | B47: OPEN | C47: Critical to debt-first plan; model assumes extra payments can be made.
A48: Final insurance quote for rebuilt gym | B48: OPEN | C48: Current ₪600/month may not carry over after rebuild.
A49: Lease assignment, term & rent escalation | B49: OPEN | C49: Major fixed-cost and exit-risk item.
A50: Contractor budget + 3-month closure timeline | B50: OPEN | C50: Directly affects runway and VAT-refund timing.
A51: Retention / presale plan for 317 members | B51: OPEN | C51: Reopening-member assumption is a major early risk.
A52: Moatza agreement terms in writing | B52: OPEN | C52: Currently modeled as an assumption, not signed revenue.
A53: Eurotec quote / final machine list / Smith machine | B53: OPEN | C53: Locks capex and avoids equipment-scope surprises.
A54: Studio instructor payroll vs invoicing status | B54: OPEN | C54: Changes VAT and employer-cost treatment.
A55: Accountant sign-off on salary / dividend policy | B55: OPEN | C55: Personal tax and National Insurance are outside this company model.
A56: Maintenance / equipment-refresh reserve policy | B56: OPEN | C56: Prevents mature-year cash from overstating distributable money.

Sheet Inputs
A1: Shaar Binyamin Gym - Core Inputs
A2: Simple operating assumptions for the 5-year model. Blue cells are editable; yellow cells are the few assumptions worth revisiting.
A4: Financing, VAT & tax
A5: Input | B5: Value | C5: Unit | D5: Treatment | E5: Source | F5: Status
A6: VAT rate | B6: 0.18 | C6: % | D6: Gross prices/invoices normalized to ex-VAT for P&L. | E6: User / source docs | F6: Given
A7: Partner 1 ownership | B7: 0.5 | C7: % | D7: Assumed 50/50 equity. | E7: User | F7: Assumption
A8: Partner 2 ownership | B8: =1-B7 -> 0.5 | C8: % | D8: Formula = 100% - Partner 1. | E8: Formula | F8: Formula
A9: Loan A - interest free | B9: 240000 | C9: NIS | D9: 0%; no interest/no payments during grace; 60 payments after grace. | E9: User | F9: Given
A10: Loan B - Prime | B10: 900000 | C10: NIS | D10: Prime-linked; no interest/no payments during grace; 60 amortizing payments after grace. | E10: User | F10: Given
A11: BOI policy rate | B11: 0.0325 | C11: % | D11: Effective 03/09/2026. | E11: Bank of Israel 01/09/2026 | F11: Current
A12: Prime spread | B12: 0.015 | C12: % | D12: Prime = BOI rate + 1.5%. | E12: Israeli Prime convention | F12: Current
A13: Current Prime rate | B13: =B11+B12 -> 0.0475 | C13: % | D13: Formula. | E13: Formula | F13: Formula
A15: Grace months from funding | B15: 12 | C15: months | D15: Build months consume part of grace. | E15: User + Claude timeline | F15: Important
A16: Repayment term after grace | B16: 60 | C16: months | D16: 5 years after grace. | E16: User | F16: Given
A17: Corporate tax rate | B17: 0.23 | C17: % | D17: Simplified monthly accrual with tax-loss carryforward. | E17: gym_dump.md | F17: Model
A18: Monthly depreciation | B18: 6813 | C18: NIS / month | D18: Tax deduction only; non-cash. | E18: gym_dump.md | F18: Model
A19: Operating cost inflation | B19: 0 | C19: % / year | D19: 0% base to match Claude current settings. | E19: Model choice | F19: Assumption
A20: Membership price inflation | B20: 0 | C20: % / year | D20: 0% base to match Claude current settings. | E20: Model choice | F20: Assumption
A22: Current business / reopening assumptions
A23: Input | B23: Value | C23: Unit | D23: Treatment | E23: Source | F23: Status
A24: Current active paying members | B24: 317 | C24: members | D24: Verified Aug 2026. | E24: gym_dump.md | F24: Verified
A25: Planning capacity | B25: 850 | C25: members | D25: Base planning cap for the forecast. | E25: User update | F25: Target
A26: Current blended fee actually collected | B26: 206 | C26: NIS gross / month | D26: Reality check only. | E26: gym_dump.md | F26: Verified
A27: Closure period | B27: 3 | C27: months | D27: Full renovation closure. | E27: gym_dump.md | F27: Assumption
A28: Retention at reopening | B28: 0.75 | C28: % of current | D28: 75% gives ~238; consistent with user's ~250. | E28: gym_dump.md | F28: Assumption
A29: Average monthly increase to Year-1 target | B29: =(B70-ROUND(B24*B28,0))/11 -> 19.272727 | C29: members / month | D29: Calculated from reopening members to the Year-1 target. | E29: Model | F29: Formula
A30: Year 1 end member goal (linked below) | B30: =B70 -> 450 | C30: members | D30: Edit the target in the Membership growth targets section below. | E30: Formula | F30: Formula
A33: Closure-period fixed cash cost | B33: 22000 | C33: NIS gross / month | D33: Approx. 20,018 ex-VAT. | E33: gym_dump.md | F33: Model
A34: Closure-period economic cost | B34: 20018 | C34: NIS ex VAT / month | D34: Use in P&L/cash model; source dump selected monthly build cost. | E34: gym_dump.md | F34: Model
A36: Membership products & other revenue
A37: Input | B37: Value | C37: Unit | D37: Treatment | E37: Source | F37: Status
A38: Full access - gym + classes | B38: 230 | C38: NIS gross / month | D38: Main product; classes have direct revenue role. | E38: User + consultant | F38: Given
A39: Single service - gym OR classes | B39: 200 | C39: NIS gross / month | D39: Lower tier. | E39: User | F39: Assumption
A40: Soldier / student program | B40: 150 | C40: NIS gross / month | D40: Discount tier. | E40: User + consultant | F40: Given
A41: Full-access mix | B41: 0.85 | C41: % members | D41: Most members at full price. | E41: User direction | F41: Assumption
A42: Single-service mix | B42: 0.1 | C42: % members | D42: Editable. | E42: Model assumption | F42: Assumption
A43: Soldier mix | B43: 0.05 | C43: % members | D43: Low percentage. | E43: User direction | F43: Assumption
A44: Blended membership fee | B44: =B38*B41+B39*B42+B40*B43 -> 223 | C44: NIS gross / month | D44: Weighted formula. | E44: Formula | F44: Formula
A45: Existing partnerships gross | B45: 8160 | C45: NIS / month | D45: Prefit + Mob tie-ins. | E45: gym_dump.md | F45: Verified
A46: Existing store/day passes gross | B46: 1580 | C46: NIS / month | D46: Current actual. | E46: gym_dump.md | F46: Verified
A47: Base other income gross | B47: 6500 | C47: NIS / month | D47: Claude/consultant base; below current 9,740. | E47: gym_dump.md | F47: Conservative
A48: Upside other income gross | B48: =B45+B46 -> 9740 | C48: NIS / month | D48: Current partnerships + store/day passes. | E48: Formula | F48: Formula
A49: Card/payment processing | B49: 0.01 | C49: % gross billings | D49: ~1% based on Jump actuals. | E49: Jump / gym_dump.md | F49: Actual-derived
A50: Moatza deal included? | B50: 0 | C50: 0=OFF / 1=ON | D50: Base OFF. | E50: gym_dump.md | F50: Hypothetical
A52: Moatza optional deal
A53: Input | B53: Value | C53: Unit | D53: Treatment | E53: Source | F53: Status
A54: Moatza members | B54: 300 | C54: members | D54: If ON, fixed block can displace organic at capacity. | E54: gym_dump.md | F54: Hypothetical
A55: Moatza fee | B55: 190 | C55: NIS gross / month | D55: Below organic blend. | E55: gym_dump.md | F55: Hypothetical
A56: Moatza start - operating month | B56: 8 | C56: month | D56: Base OFF. | E56: gym_dump.md | F56: Hypothetical
A57: Capacity cap | B57: =B25 -> 850 | C57: members | D57: Links current capacity. | E57: Formula | F57: Formula
A59: Startup liquidity assumptions
A60: Input | B60: Value | C60: Unit | D60: Treatment | E60: Source | F60: Status
A61: Run-in reserve | B61: 75000 | C61: NIS | D61: Working-capital reserve, not VATable invoice in base. | E61: Consultant + audit | F61: Important
A62: Optional extra presale marketing | B62: 0 | C62: NIS ex VAT | D62: Not added until defined campaign exists. | E62: User | F62: Optional
A63: Build VAT refund lag | B63: 2 | C63: timeline month | D63: Critical liquidity assumption. | E63: gym_dump.md | F63: Important
A64: Operating VAT lag | B64: 1 | C64: month | D64: Note only; base cash uses ex-VAT economics to avoid double count. | E64: gym_dump.md | F64: Model
A65: Minimum retained monthly cash before owner pay | B65: 10000 | C65: NIS / month | D65: Prudence test. | E65: Model assumption | F65: Assumption
A66: Employer load on owner salary | B66: 0.2 | C66: % of gross salary | D66: Used for affordability. | E66: Existing staff assumption | F66: Assumption
A68: Membership growth targets — organic vs total incl. Moatza
A69: Organic member target | B69: Value | C69: Total target incl. Moatza | D69: Unit | E69: Treatment | F69: Source | G69: Status
A70: Year 1 organic end member target | B70: 450 | C70: =MIN($B$25,B70+IF(AND($B$50=1,$B$56<=12),$B$54,0)) -> 450 | D70: members | E70: Organic target; total target adds Moatza members when active by year-end. | F70: User target | G70: Input
A71: Year 2 organic end member target | B71: 600 | C71: =MIN($B$25,B71+IF(AND($B$50=1,$B$56<=24),$B$54,0)) -> 600 | D71: members | E71: Organic target; total target adds Moatza members when active by year-end. | F71: Planning target | G71: Input
A72: Year 3 organic end member target | B72: 725 | C72: =MIN($B$25,B72+IF(AND($B$50=1,$B$56<=36),$B$54,0)) -> 725 | D72: members | E72: Organic target; total target adds Moatza members when active by year-end. | F72: Planning target | G72: Input
A73: Year 4 organic end member target | B73: 800 | C73: =MIN($B$25,B73+IF(AND($B$50=1,$B$56<=48),$B$54,0)) -> 800 | D73: members | E73: Organic target; total target adds Moatza members when active by year-end. | F73: Planning target | G73: Input
A74: Year 5 organic end member target | B74: 850 | C74: =MIN($B$25,B74+IF(AND($B$50=1,$B$56<=60),$B$54,0)) -> 850 | D74: members | E74: Organic target; total target adds Moatza members when active by year-end. | F74: Planning target | G74: Input
A77: Debt payoff & owner compensation policy
A78: Input | B78: Value | C78: Unit | D78: Treatment | E78: Source | F78: Status
A79: Accelerated debt payoff included? | B79: 1 | C79: 0=OFF / 1=ON | D79: When ON, debt is paid down through scheduled payments plus periodic lump-sum sweeps of excess cash. | E79: Partner policy | F79: Important
A80: Debt-sweep cash reserve target | B80: 150000 | C80: NIS | D80: Cash kept in the company before any extra debt payment or owner distribution. | E80: Model policy | F80: Important
A81: Excess cash used at each sweep | B81: 1 | C81: % | D81: At each scheduled sweep date, cash above the reserve floor is used first for Loan B (Prime), then Loan A (0%). | E81: Partner policy | F81: Important
A82: Extra debt sweeps not before timeline month | B82: =B15 -> 12 | C82: timeline month | D82: No voluntary extra prepayment during the free grace period. | E82: Formula | F82: Formula
A83: Debt repayment priority | B83: Loan B (Prime) → Loan A (0%) | C83: order | D83: Interest-bearing debt is eliminated first, then the 0% loan for full debt freedom. | E83: Partner policy | F83: Given
A84: Owner salaries enabled after debt? | B84: 0 | C84: 0=OFF / 1=ON | D84: Salary begins only after total business debt reaches zero. | E84: Partner policy | F84: Important
A85: Partner 1 (Gershon) equal owner salary after debt | B85: 10000 | C85: NIS / month | D85: Both partners are modeled equally and both work in the business; Hodaya remains staff. | E85: Partner policy | F85: Input
A86: Partner 2 (Yishai) equal owner salary after debt | B86: 10000 | C86: NIS / month | D86: Equal to Partner 1; ownership and modeled owner salary are 50/50. | E86: Partner policy | F86: Input
A87: Salary start rule | B87: Month after all debt is repaid | C87: rule | D87: Prevents salary from competing with the debt-paydown goal. | E87: Partner policy | F87: Given
A88: Owner salary growth | B88: 0 | C88: % / year | D88: 0% base; editable for later years. | E88: Model choice | F88: Assumption
A89: Distribution policy | B89: No automatic distributions | C89: policy | D89: Model shows cash available above the reserve once debt-free, but does not automatically pay it out. | E89: Partner policy | F89: Given
A90: Debt sweep frequency | B90: 6 | C90: operating months | D90: Cash is reviewed twice a year; any excess above reserve is paid as one lump-sum prepayment. | E90: Partner policy | F90: Important
A91: First debt sweep operating month | B91: 12 | C91: operating month | D91: First lump-sum review is at the end of operating Year 1, then every 6 months. | E91: Partner policy | F91: Important

Sheet Operating Costs
A1: Rebuild Monthly Operating Cost - Transparent VAT Build
A2: Monthly operating plan using morning human coverage, automated evenings/weekends, outsourced cleaning and scheduled studio classes.
A4: Category | B4: Line item | C4: Gross cash / mo | D4: VATable? | E4: VAT cash | F4: Ex-VAT cost | G4: Model note | H4: Source | I4: Confidence
A5: Fixed | B5: Rent | C5: 20000 | D5: Y | E5: =IF(D5="Y",C5-C5/(1+Inputs!$B$6),0) -> 3050.8475 | F5: =C5-E5 -> 16949.153 | G5: Incl VAT; user confirmed | H5: gym_dump.md | I5: Base
A6: Fixed | B6: Arnona | C6: 4500 | D6: N | E6: =IF(D6="Y",C6-C6/(1+Inputs!$B$6),0) -> 0 | F6: =C6-E6 -> 4500 | G6: Claude operating model | H6: gym_dump.md | I6: Base
A7: Fixed | B7: Electricity | C7: 4000 | D7: Y | E7: =IF(D7="Y",C7-C7/(1+Inputs!$B$6),0) -> 610.16949 | F7: =C7-E7 -> 3389.8305 | G7: Claude operating model | H7: gym_dump.md | I7: Base
A8: Fixed | B8: Water | C8: 1500 | D8: Y | E8: =IF(D8="Y",C8-C8/(1+Inputs!$B$6),0) -> 228.81356 | F8: =C8-E8 -> 1271.1864 | G8: Claude operating model | H8: gym_dump.md | I8: Base
A9: Fixed | B9: Cleaning - outsourced | C9: 3500 | D9: Y | E9: =IF(D9="Y",C9-C9/(1+Inputs!$B$6),0) -> 533.89831 | F9: =C9-E9 -> 2966.1017 | G9: Outsourced cleaning allowance | H9: gym_dump.md | I9: Base
A10: Fixed | B10: Accounting | C10: 1800 | D10: Y | E10: =IF(D10="Y",C10-C10/(1+Inputs!$B$6),0) -> 274.57627 | F10: =C10-E10 -> 1525.4237 | G10: Monthly accounting allowance | H10: gym_dump.md | I10: Base
A11: Fixed | B11: Software / CRM / access | C11: 1500 | D11: Y | E11: =IF(D11="Y",C11-C11/(1+Inputs!$B$6),0) -> 228.81356 | F11: =C11-E11 -> 1271.1864 | G11: Automated access stack | H11: gym_dump.md | I11: Base
A12: Fixed | B12: Phone + mobile + comms | C12: 1059 | D12: Y | E12: =IF(D12="Y",C12-C12/(1+Inputs!$B$6),0) -> 161.54237 | F12: =C12-E12 -> 897.45763 | G12: Claude operating model | H12: gym_dump.md | I12: Base
A13: Fixed | B13: Maintenance | C13: 1000 | D13: Y | E13: =IF(D13="Y",C13-C13/(1+Inputs!$B$6),0) -> 152.54237 | F13: =C13-E13 -> 847.45763 | G13: Allowance | H13: gym_dump.md | I13: Base
A14: Fixed | B14: Insurance | C14: 600 | D14: N | E14: =IF(D14="Y",C14-C14/(1+Inputs!$B$6),0) -> 0 | F14: =C14-E14 -> 600 | G14: Current actual; re-quote rebuilt facility | H14: gym_dump.md | I14: Base
A15: Fixed | B15: Office / signage / sundries | C15: 250 | D15: Y | E15: =IF(D15="Y",C15-C15/(1+Inputs!$B$6),0) -> 38.135593 | F15: =C15-E15 -> 211.86441 | G15: Allowance | H15: gym_dump.md | I15: Base
A16: Fixed | B16: Management fee | C16: 2300 | D16: Y | E16: =IF(D16="Y",C16-C16/(1+Inputs!$B$6),0) -> 350.84746 | F16: =C16-E16 -> 1949.1525 | G16: Confirmed real | H16: gym_dump.md | I16: Base
... A19: Marketing | B19: Ongoing marketing | C19: 2000 | D19: Y | E19: =IF(D19="Y",C19-C19/(1+Inputs!$B$6),0) -> 305.08475 | F19: =C19-E19 -> 1694.9153 | G19: Recurring | H19: gym_dump.md | I19: Base
A21: Monthly totals
A22: Metric | B22: Gross | C22: Ex-VAT | D22: Comment
A23: Core monthly operating cost | B23: =SUM(C5:C19) -> 69849 | C23: =SUM(F5:F19) -> 63913.729 | D23: Before variable card processing
A24: Card processing at ₪100k gross billings | B24: 1000 | C24: =B24/(1+Inputs!$B$6) -> 847.45763 | D24: 1% example
A25: Total at ₪100k gross billings | B25: =B23+B24 -> 70849 | C25: =C23+C24 -> 64761.186 | D25: Illustrative run-rate
A26: Annual core operating cost | B26: =B23*12 -> 838188 | C26: =C23*12 -> 766964.75 | D26: Before variable card processing
A30: Open items
A31: Insurance | B31: ₪600 is the current actual; obtain a fresh quote for the rebuilt facility.
A32: Studio VAT | B32: Studio instruction is treated conservatively as non-VAT until contractor status is confirmed.
A33: Automation | B33: Base model assumes automated entry and no permanent evening/weekend front desk.
A34: Owner salary | B34: Owner salaries are excluded here and tested separately on the Owner Pay tab.

Sheet Startup & Funding
A1: Startup Investment, VAT & Working Capital
A2: The ₪75k run-in amount is treated as working-capital reserve rather than a separate VATable capital invoice.
A4: Startup item | B4: Ex-VAT amount | C4: VATable? | D4: VAT | E4: Gross cash | F4: Base treatment | G4: Source | H4: Note
A5: Business plan | B5: 9000 | C5: Y | D5: =IF(C5="Y",B5*Inputs!$B$6,0) -> 1620 | E5: =B5+D5 -> 10620 | F5: Upfront | G5: Consultant
A6: Plans & consultants | B6: 90000 | C6: Y | D6: =IF(C6="Y",B6*Inputs!$B$6,0) -> 16200 | E6: =B6+D6 -> 106200 | F6: Upfront | G6: Consultant
A7: Build / renovation | B7: 200000 | C7: Y | D7: =IF(C7="Y",B7*Inputs!$B$6,0) -> 36000 | E7: =B7+D7 -> 236000 | F7: Upfront | G7: Consultant
A8: Operational equipment | B8: 146000 | C8: Y | D8: =IF(C8="Y",B8*Inputs!$B$6,0) -> 26280 | E8: =B8+D8 -> 172280 | F8: Upfront | G8: Consultant
A9: Professional gym equipment | B9: 399076.27 | C9: Y | D9: =IF(C9="Y",B9*Inputs!$B$6,0) -> 71833.729 | E9: =B9+D9 -> 470910 | F9: Upfront | G9: Eurotec quote | H9: Exact quote
A10: Run-in reserve | B10: 75000 | C10: N | D10: =IF(C10="Y",B10*Inputs!$B$6,0) -> 0 | E10: =B10+D10 -> 75000 | F10: Working-capital reserve | G10: Consultant | H10: Not VATable invoice in base
A11: Optional extra presale marketing | B11: =Inputs!$B$62 -> 0 | C11: Y | D11: =IF(C11="Y",B11*Inputs!$B$6,0) -> 0 | E11: =B11+D11 -> 0 | F11: Only if activated | G11: Inputs | H11: Base zero
A13: Base normalized funding bridge
A14: Metric | B14: Amount
A15: Total startup budget ex VAT incl reserve | B15: =SUM(B5:B11) -> 919076.27
A16: Reclaimable startup VAT | B16: =SUM(D5:D11) -> 151933.73
A17: Gross cash allocated incl reserve | B17: =SUM(E5:E11) -> 1071010
A18: Total financing | B18: =Inputs!$B$9+Inputs!$B$10 -> 1140000
A19: Cash headroom at funding | B19: =B18-B17 -> 68990.001
A20: 3-month closure economic cost exVAT | B20: =Inputs!$B$27*Inputs!$B$34 -> 60054
A21: Build VAT refund | B21: =B16 -> 151933.73
A22: Approx cash after closure + refund | B22: =B19-B20+B21 -> 160869.73

Sheet Financing
A1: Loan Schedule
A2: 12 months from funding with no payment and no interest; the 3-month renovation period uses part of that grace.
A4: Metric | B4: Loan A | C4: Loan B | D4: Total
A5: Principal | B5: =Inputs!$B$9 -> 240000 | C5: =Inputs!$B$10 -> 900000 | D5: =SUM(B5:C5) -> 1140000
A6: Annual rate | B6: 0 | C6: =Inputs!$B$13 -> 0.0475
A7: Grace months | B7: =Inputs!$B$15 -> 12 | C7: =Inputs!$B$15 -> 12
A8: Balance after grace | B8: =B5 -> 240000 | C8: =C5 -> 900000
A9: Repayment months | B9: 60 | C9: 60
A10: Monthly payment after grace | B10: =B8/B9 -> 4000 | C10: =C8*(C6/12)/(1-(1+C6/12)^(-C9)) -> 16881.221 | D10: =SUM(B10:C10) -> 20881.221
A11: Total debt service after grace | D11: =D10 -> 20881.221
A12: Payment starts timeline month | D12: =Inputs!$B$15 -> 12
A13: Approx operating month payment starts | D13: =MAX(1,Inputs!$B$15-Inputs!$B$27+1) -> 10
A15: 63-Month funding timeline loan schedule
A16: Timeline Mo | B16: A Opening | C16: A Interest | D16: A Payment | E16: A Closing | F16: B Opening | G16: B Interest | H16: B Payment | I16: B Closing | J16: Total Payment
A17: 0 | B17: =$B$5 -> 240000 | C17: 0 | D17: 0 | E17: =$B$5 -> 240000 | F17: =$C$5 -> 900000 | G17: 0 | H17: 0 | I17: =$C$5 -> 900000 | J17: 0
A18: =A17+1 -> 1 | B18: =E17 -> 240000 | C18: =0 -> 0 | D18: =IF(A18<Inputs!$B$15,0,MIN($B$10,B18)) -> 0 | E18: =MAX(0,B18-D18) -> 240000 | F18: =I17 -> 900000 | G18: =IF(A18<Inputs!$B$15,0,F18*$C$6/12) -> 0 | H18: =IF(A18<Inputs!$B$15,0,MIN($C$10,F18+G18)) -> 0 | I18: =MAX(0,F18+G18-H18) -> 900000 | J18: =D18+H18 -> 0
A19: =A18+1 -> 2 | B19: =E18 -> 240000 | C19: =0 -> 0 | D19: =IF(A19<Inputs!$B$15,0,MIN($B$10,B19)) -> 0 | E19: =MAX(0,B19-D19) -> 240000 | F19: =I18 -> 900000 | G19: =IF(A19<Inputs!$B$15,0,F19*$C$6/12) -> 0 | H19: =IF(A19<Inputs!$B$15,0,MIN($C$10,F19+G19)) -> 0 | I19: =MAX(0,F19+G19-H19) -> 900000 | J19: =D19+H19 -> 0
A20: =A19+1 -> 3 | B20: =E19 -> 240000 | C20: =0 -> 0 | D20: =IF(A20<Inputs!$B$15,0,MIN($B$10,B20)) -> 0 | E20: =MAX(0,B20-D20) -> 240000 | F20: =I19 -> 900000 | G20: =IF(A20<Inputs!$B$15,0,F20*$C$6/12) -> 0 | H20: =IF(A20<Inputs!$B$15,0,MIN($C$10,F20+G20)) -> 0 | I20: =MAX(0,F20+G20-H20) -> 900000 | J20: =D20+H20 -> 0
A21: =A20+1 -> 4 | B21: =E20 -> 240000 | C21: =0 -> 0 | D21: =IF(A21<Inputs!$B$15,0,MIN($B$10,B21)) -> 0 | E21: =MAX(0,B21-D21) -> 240000 | F21: =I20 -> 900000 | G21: =IF(A21<Inputs!$B$15,0,F21*$C$6/12) -> 0 | H21: =IF(A21<Inputs!$B$15,0,MIN($C$10,F21+G21)) -> 0 | I21: =MAX(0,F21+G21-H21) -> 900000 | J21: =D21+H21 -> 0
A22: =A21+1 -> 5 | B22: =E21 -> 240000 | C22: =0 -> 0 | D22: =IF(A22<Inputs!$B$15,0,MIN($B$10,B22)) -> 0 | E22: =MAX(0,B22-D22) -> 240000 | F22: =I21 -> 900000 | G22: =IF(A22<Inputs!$B$15,0,F22*$C$6/12) -> 0 | H22: =IF(A22<Inputs!$B$15,0,MIN($C$10,F22+G22)) -> 0 | I22: =MAX(0,F22+G22-H22) -> 900000 | J22: =D22+H22 -> 0
A23: =A22+1 -> 6 | B23: =E22 -> 240000 | C23: =0 -> 0 | D23: =IF(A23<Inputs!$B$15,0,MIN($B$10,B23)) -> 0 | E23: =MAX(0,B23-D23) -> 240000 | F23: =I22 -> 900000 | G23: =IF(A23<Inputs!$B$15,0,F23*$C$6/12) -> 0 | H23: =IF(A23<Inputs!$B$15,0,MIN($C$10,F23+G23)) -> 0 | I23: =MAX(0,F23+G23-H23) -> 900000 | J23: =D23+H23 -> 0
A24: =A23+1 -> 7 | B24: =E23 -> 240000 | C24: =0 -> 0 | D24: =IF(A24<Inputs!$B$15,0,MIN($B$10,B24)) -> 0 | E24: =MAX(0,B24-D24) -> 240000 | F24: =I23 -> 900000 | G24: =IF(A24<Inputs!$B$15,0,F24*$C$6/12) -> 0 | H24: =IF(A24<Inputs!$B$15,0,MIN($C$10,F24+G24)) -> 0 | I24: =MAX(0,F24+G24-H24) -> 900000 | J24: =D24+H24 -> 0
A25: =A24+1 -> 8 | B25: =E24 -> 240000 | C25: =0 -> 0 | D25: =IF(A25<Inputs!$B$15,0,MIN($B$10,B25)) -> 0 | E25: =MAX(0,B25-D25) -> 240000 | F25: =I24 -> 900000 | G25: =IF(A25<Inputs!$B$15,0,F25*$C$6/12) -> 0 | H25: =IF(A25<Inputs!$B$15,0,MIN($C$10,F25+G25)) -> 0 | I25: =MAX(0,F25+G25-H25) -> 900000 | J25: =D25+H25 -> 0
A26: =A25+1 -> 9 | B26: =E25 -> 240000 | C26: =0 -> 0 | D26: =IF(A26<Inputs!$B$15,0,MIN($B$10,B26)) -> 0 | E26: =MAX(0,B26-D26) -> 240000 | F26: =I25 -> 900000 | G26: =IF(A26<Inputs!$B$15,0,F26*$C$6/12) -> 0 | H26: =IF(A26<Inputs!$B$15,0,MIN($C$10,F26+G26)) -> 0 | I26: =MAX(0,F26+G26-H26) -> 900000 | J26: =D26+H26 -> 0
A27: =A26+1 -> 10 | B27: =E26 -> 240000 | C27: =0 -> 0 | D27: =IF(A27<Inputs!$B$15,0,MIN($B$10,B27)) -> 0 | E27: =MAX(0,B27-D27) -> 240000 | F27: =I26 -> 900000 | G27: =IF(A27<Inputs!$B$15,0,F27*$C$6/12) -> 0 | H27: =IF(A27<Inputs!$B$15,0,MIN($C$10,F27+G27)) -> 0 | I27: =MAX(0,F27+G27-H27) -> 900000 | J27: =D27+H27 -> 0
A28: =A27+1 -> 11 | B28: =E27 -> 240000 | C28: =0 -> 0 | D28: =IF(A28<Inputs!$B$15,0,MIN($B$10,B28)) -> 0 | E28: =MAX(0,B28-D28) -> 240000 | F28: =I27 -> 900000 | G28: =IF(A28<Inputs!$B$15,0,F28*$C$6/12) -> 0 | H28: =IF(A28<Inputs!$B$15,0,MIN($C$10,F28+G28)) -> 0 | I28: =MAX(0,F28+G28-H28) -> 900000 | J28: =D28+H28 -> 0
A29: =A28+1 -> 12 | B29: =E28 -> 240000 | C29: =0 -> 0 | D29: =IF(A29<Inputs!$B$15,0,MIN($B$10,B29)) -> 4000 | E29: =MAX(0,B29-D29) -> 236000 | F29: =I28 -> 900000 | G29: =IF(A29<Inputs!$B$15,0,F29*$C$6/12) -> 3562.5 | H29: =IF(A29<Inputs!$B$15,0,MIN($C$10,F29+G29)) -> 16881.221 | I29: =MAX(0,F29+G29-H29) -> 886681.28 | J29: =D29+H29 -> 20881.221
... A79: =A78+1 -> 62 | B79: =E78 -> 40000 | C79: =0 -> 0 | D79: =IF(A79<Inputs!$B$15,0,MIN($B$10,B79)) -> 4000 | E79: =MAX(0,B79-D79) -> 36000 | F79: =I78 -> 165194.48 | G79: =IF(A79<Inputs!$B$15,0,F79*$C$6/12) -> 653.8948 | H79: =IF(A79<Inputs!$B$15,0,MIN($C$10,F79+G79)) -> 16881.221 | I79: =MAX(0,F79+G79-H79) -> 148967.15 | J79: =D79+H79 -> 20881.221

Sheet Monthly Base
A1: 63-Month Base Cash Model - 3 Build Months + 60 Operating Months
A2: Membership follows the editable Year 1-5 targets on Inputs. Monthly values interpolate automatically between targets, while pricing, costs, financing, VAT and owner-pay assumptions flow through the full model.
A4: Timeline Mo | B4: Phase | C4: Operating Mo | D4: Organic Members | E4: Organic Billed | F4: Moatza Members | G4: Total Members | H4: Blended Organic Fee | I4: Membership Gross | J4: Other Gross | K4: Total Gross Billings | L4: Net Revenue ex VAT | M4: Card Fees ex VAT | N4: Core Opex ex VAT | O4: EBITDA | P4: Debt Service | Q4: Loan B Interest | R4: Depreciation | S4: Taxable Before Loss | T4: Tax Loss CF Begin | U4: Taxable After Loss | V4: Corp Tax | W4: Tax Loss CF End | X4: Pre-Owner Cash | Y4: Startup VAT Refund | Z4: Cash Balance | AA4: Debt Balance | AB4: Op BE Members | AC4: Post-Debt BE Members | AD4: Notes
A5: 0 | B5: =IF(A5<Inputs!$B$27,"BUILD","OPEN") -> BUILD | C5: =IF(B5="OPEN",A5-Inputs!$B$27+1,0) -> 0 | D5: =IF(C5=0,0,MIN(Inputs!$B$25,IF(C5=1,ROUND(Inputs!$B$24*Inputs!$B$28,0),IF(C5<=12,ROUND(ROUND(Inputs!$B$24*Inputs!$B$28,0)+(Inputs!$B$70-ROUND(Inputs!$B$24*Inputs!$B$28,0))*(C5-1)/11,0),IF(C5<=24,ROUND(Inputs!$B$70+(Inputs!$B$71-Inputs!$B$70)*(C5-12)/12,0),IF(C5<=36,ROUND(Inputs!$B$71+(Inputs!$B$72-Inputs!$B$71)*(C5-24)/12,0),IF(C5<=48,ROUND(Inputs!$B$72+(Inputs!$B$73-Inputs!$B$72)*(C5-36)/12,0),ROUND(Inputs!$B$73+(Inputs!$B$74-Inputs!$B$73)*MIN(C5-48,12)/12,0)))))))) -> 0 | E5: =IF(C5=0,0,IF(Inputs!$B$50=1,MIN(D5,MAX(0,Inputs!$B$57-Inputs!$B$54)),MIN(D5,Inputs!$B$57))) -> 0 | F5: =IF(AND(C5>=Inputs!$B$56,Inputs!$B$50=1),Inputs!$B$54,0) -> 0 | G5: =E5+F5 -> 0 | H5: =Inputs!$B$44*(1+Inputs!$B$20)^MAX(0,ROUNDUP(C5/12,0)-1) -> 223 | I5: =IF(C5=0,0,E5*H5+F5*Inputs!$B$55) -> 0 | J5: =IF(C5=0,0,Inputs!$B$47) -> 0 | K5: =I5+J5 -> 0 | L5: =K5/(1+Inputs!$B$6) -> 0 | M5: =(K5*Inputs!$B$49)/(1+Inputs!$B$6) -> 0 | N5: =IF(C5=0,Inputs!$B$34,'Operating Costs'!$C$23*(1+Inputs!$B$19)^MAX(0,ROUNDUP(C5/12,0)-1)) -> 20018 | O5: =L5-M5-N5 -> -20018 | P5: =Financing!J17 -> 0 | Q5: =Financing!G17 -> 0 | R5: =IF(C5=0,0,Inputs!$B$18) -> 0 | S5: =O5-R5-Q5 -> -20018 | T5: 0 | U5: =MAX(0,S5-T5) -> 0 | V5: =U5*Inputs!$B$17 -> 0 | W5: =MAX(0,T5-MAX(0,S5))+MAX(0,-S5) -> 20018 | X5: =O5-P5-V5 -> -20018 | Y5: =IF(A5=Inputs!$B$63,'Startup & Funding'!$B$16,0) -> 0 | Z5: ='Startup & Funding'!$B$19+X5+Y5 -> 48972.001 | AA5: =Financing!E17+Financing!I17 -> 1140000 | AB5: =('Operating Costs'!$C$23-(Inputs!$B$47*(1-Inputs!$B$49)/(1+Inputs!$B$6)))/(Inputs!$B$44*(1-Inputs!$B$49)/(1+Inputs!$B$6)) -> 312.46637 | AC5: =('Operating Costs'!$C$23+Financing!$D$10-(Inputs!$B$47*(1-Inputs!$B$49)/(1+Inputs!$B$6)))/(Inputs!$B$44*(1-Inputs!$B$49)/(1+Inputs!$B$6)) -> 424.07501 | AD5: Funding month 0
A6: =A5+1 -> 1 | B6: =IF(A6<Inputs!$B$27,"BUILD","OPEN") -> BUILD | C6: =IF(B6="OPEN",A6-Inputs!$B$27+1,0) -> 0 | D6: =IF(C6=0,0,MIN(Inputs!$B$25,IF(C6=1,ROUND(Inputs!$B$24*Inputs!$B$28,0),IF(C6<=12,ROUND(ROUND(Inputs!$B$24*Inputs!$B$28,0)+(Inputs!$B$70-ROUND(Inputs!$B$24*Inputs!$B$28,0))*(C6-1)/11,0),IF(C6<=24,ROUND(Inputs!$B$70+(Inputs!$B$71-Inputs!$B$70)*(C6-12)/12,0),IF(C6<=36,ROUND(Inputs!$B$71+(Inputs!$B$72-Inputs!$B$71)*(C6-24)/12,0),IF(C6<=48,ROUND(Inputs!$B$72+(Inputs!$B$73-Inputs!$B$72)*(C6-36)/12,0),ROUND(Inputs!$B$73+(Inputs!$B$74-Inputs!$B$73)*MIN(C6-48,12)/12,0)))))))) -> 0 | E6: =IF(C6=0,0,IF(Inputs!$B$50=1,MIN(D6,MAX(0,Inputs!$B$57-Inputs!$B$54)),MIN(D6,Inputs!$B$57))) -> 0 | F6: =IF(AND(C6>=Inputs!$B$56,Inputs!$B$50=1),Inputs!$B$54,0) -> 0 | G6: =E6+F6 -> 0 | H6: =Inputs!$B$44*(1+Inputs!$B$20)^MAX(0,ROUNDUP(C6/12,0)-1) -> 223 | I6: =IF(C6=0,0,E6*H6+F6*Inputs!$B$55) -> 0 | J6: =IF(C6=0,0,Inputs!$B$47) -> 0 | K6: =I6+J6 -> 0 | L6: =K6/(1+Inputs!$B$6) -> 0 | M6: =(K6*Inputs!$B$49)/(1+Inputs!$B$6) -> 0 | N6: =IF(C6=0,Inputs!$B$34,'Operating Costs'!$C$23*(1+Inputs!$B$19)^MAX(0,ROUNDUP(C6/12,0)-1)) -> 20018 | O6: =L6-M6-N6 -> -20018 | P6: {=INDEX(Financing!$J$17:$J$79,A6+1)} -> 0 | Q6: {=INDEX(Financing!$G$17:$G$79,A6+1)} -> 0 | R6: =IF(C6=0,0,Inputs!$B$18) -> 0 | S6: =O6-R6-Q6 -> -20018 | T6: =W5 -> 20018 | U6: =MAX(0,S6-T6) -> 0 | V6: =U6*Inputs!$B$17 -> 0 | W6: =MAX(0,T6-MAX(0,S6))+MAX(0,-S6) -> 40036 | X6: =O6-P6-V6 -> -20018 | Y6: =IF(A6=Inputs!$B$63,'Startup & Funding'!$B$16,0) -> 0 | Z6: =Z5+X6+Y6 -> 28954.001 | AA6: {=INDEX(Financing!$E$17:$E$79,A6+1)+INDEX(Financing!$I$17:$I$79,A6+1)} -> 1140000 | AB6: =AB5 -> 312.46637 | AC6: =AC5 -> 424.07501 | AD6: =IF(C6=1,"REOPEN",IF(A6=Inputs!$B$15,"DEBT START",IF(AND(C6>0,MOD(C6,12)=0),"YEAR END","")))
A7: =A6+1 -> 2 | B7: =IF(A7<Inputs!$B$27,"BUILD","OPEN") -> BUILD | C7: =IF(B7="OPEN",A7-Inputs!$B$27+1,0) -> 0 | D7: =IF(C7=0,0,MIN(Inputs!$B$25,IF(C7=1,ROUND(Inputs!$B$24*Inputs!$B$28,0),IF(C7<=12,ROUND(ROUND(Inputs!$B$24*Inputs!$B$28,0)+(Inputs!$B$70-ROUND(Inputs!$B$24*Inputs!$B$28,0))*(C7-1)/11,0),IF(C7<=24,ROUND(Inputs!$B$70+(Inputs!$B$71-Inputs!$B$70)*(C7-12)/12,0),IF(C7<=36,ROUND(Inputs!$B$71+(Inputs!$B$72-Inputs!$B$71)*(C7-24)/12,0),IF(C7<=48,ROUND(Inputs!$B$72+(Inputs!$B$73-Inputs!$B$72)*(C7-36)/12,0),ROUND(Inputs!$B$73+(Inputs!$B$74-Inputs!$B$73)*MIN(C7-48,12)/12,0)))))))) -> 0 | E7: =IF(C7=0,0,IF(Inputs!$B$50=1,MIN(D7,MAX(0,Inputs!$B$57-Inputs!$B$54)),MIN(D7,Inputs!$B$57))) -> 0 | F7: =IF(AND(C7>=Inputs!$B$56,Inputs!$B$50=1),Inputs!$B$54,0) -> 0 | G7: =E7+F7 -> 0 | H7: =Inputs!$B$44*(1+Inputs!$B$20)^MAX(0,ROUNDUP(C7/12,0)-1) -> 223 | I7: =IF(C7=0,0,E7*H7+F7*Inputs!$B$55) -> 0 | J7: =IF(C7=0,0,Inputs!$B$47) -> 0 | K7: =I7+J7 -> 0 | L7: =K7/(1+Inputs!$B$6) -> 0 | M7: =(K7*Inputs!$B$49)/(1+Inputs!$B$6) -> 0 | N7: =IF(C7=0,Inputs!$B$34,'Operating Costs'!$C$23*(1+Inputs!$B$19)^MAX(0,ROUNDUP(C7/12,0)-1)) -> 20018 | O7: =L7-M7-N7 -> -20018 | P7: {=INDEX(Financing!$J$17:$J$79,A7+1)} -> 0 | Q7: {=INDEX(Financing!$G$17:$G$79,A7+1)} -> 0 | R7: =IF(C7=0,0,Inputs!$B$18) -> 0 | S7: =O7-R7-Q7 -> -20018 | T7: =W6 -> 40036 | U7: =MAX(0,S7-T7) -> 0 | V7: =U7*Inputs!$B$17 -> 0 | W7: =MAX(0,T7-MAX(0,S7))+MAX(0,-S7) -> 60054 | X7: =O7-P7-V7 -> -20018 | Y7: =IF(A7=Inputs!$B$63,'Startup & Funding'!$B$16,0) -> 151933.73 | Z7: =Z6+X7+Y7 -> 160869.73 | AA7: {=INDEX(Financing!$E$17:$E$79,A7+1)+INDEX(Financing!$I$17:$I$79,A7+1)} -> 1140000 | AB7: =AB6 -> 312.46637 | AC7: =AC6 -> 424.07501 | AD7: =IF(C7=1,"REOPEN",IF(A7=Inputs!$B$15,"DEBT START",IF(AND(C7>0,MOD(C7,12)=0),"YEAR END","")))
A8: =A7+1 -> 3 | B8: =IF(A8<Inputs!$B$27,"BUILD","OPEN") -> OPEN | C8: =IF(B8="OPEN",A8-Inputs!$B$27+1,0) -> 1 | D8: =IF(C8=0,0,MIN(Inputs!$B$25,IF(C8=1,ROUND(Inputs!$B$24*Inputs!$B$28,0),IF(C8<=12,ROUND(ROUND(Inputs!$B$24*Inputs!$B$28,0)+(Inputs!$B$70-ROUND(Inputs!$B$24*Inputs!$B$28,0))*(C8-1)/11,0),IF(C8<=24,ROUND(Inputs!$B$70+(Inputs!$B$71-Inputs!$B$70)*(C8-12)/12,0),IF(C8<=36,ROUND(Inputs!$B$71+(Inputs!$B$72-Inputs!$B$71)*(C8-24)/12,0),IF(C8<=48,ROUND(Inputs!$B$72+(Inputs!$B$73-Inputs!$B$72)*(C8-36)/12,0),ROUND(Inputs!$B$73+(Inputs!$B$74-Inputs!$B$73)*MIN(C8-48,12)/12,0)))))))) -> 238 | E8: =IF(C8=0,0,IF(Inputs!$B$50=1,MIN(D8,MAX(0,Inputs!$B$57-Inputs!$B$54)),MIN(D8,Inputs!$B$57))) -> 238 | F8: =IF(AND(C8>=Inputs!$B$56,Inputs!$B$50=1),Inputs!$B$54,0) -> 0 | G8: =E8+F8 -> 238 | H8: =Inputs!$B$44*(1+Inputs!$B$20)^MAX(0,ROUNDUP(C8/12,0)-1) -> 223 | I8: =IF(C8=0,0,E8*H8+F8*Inputs!$B$55) -> 53074 | J8: =IF(C8=0,0,Inputs!$B$47) -> 6500 | K8: =I8+J8 -> 59574 | L8: =K8/(1+Inputs!$B$6) -> 50486.441 | M8: =(K8*Inputs!$B$49)/(1+Inputs!$B$6) -> 504.86441 | N8: =IF(C8=0,Inputs!$B$34,'Operating Costs'!$C$23*(1+Inputs!$B$19)^MAX(0,ROUNDUP(C8/12,0)-1)) -> 63913.729 | O8: =L8-M8-N8 -> -13932.153 | P8: {=INDEX(Financing!$J$17:$J$79,A8+1)} -> 0 | Q8: {=INDEX(Financing!$G$17:$G$79,A8+1)} -> 0 | R8: =IF(C8=0,0,Inputs!$B$18) -> 6813 | S8: =O8-R8-Q8 -> -20745.153 | T8: =W7 -> 60054 | U8: =MAX(0,S8-T8) -> 0 | V8: =U8*Inputs!$B$17 -> 0 | W8: =MAX(0,T8-MAX(0,S8))+MAX(0,-S8) -> 80799.153 | X8: =O8-P8-V8 -> -13932.153 | Y8: =IF(A8=Inputs!$B$63,'Startup & Funding'!$B$16,0) -> 0 | Z8: =Z7+X8+Y8 -> 146937.58 | AA8: {=INDEX(Financing!$E$17:$E$79,A8+1)+INDEX(Financing!$I$17:$I$79,A8+1)} -> 1140000 | AB8: =AB7 -> 312.46637 | AC8: =AC7 -> 424.07501 | AD8: =IF(C8=1,"REOPEN",IF(A8=Inputs!$B$15,"DEBT START",IF(AND(C8>0,MOD(C8,12)=0),"YEAR END",""))) -> REOPEN
A9: =A8+1 -> 4 | B9: =IF(A9<Inputs!$B$27,"BUILD","OPEN") -> OPEN | C9: =IF(B9="OPEN",A9-Inputs!$B$27+1,0) -> 2 | D9: =IF(C9=0,0,MIN(Inputs!$B$25,IF(C9=1,ROUND(Inputs!$B$24*Inputs!$B$28,0),IF(C9<=12,ROUND(ROUND(Inputs!$B$24*Inputs!$B$28,0)+(Inputs!$B$70-ROUND(Inputs!$B$24*Inputs!$B$28,0))*(C9-1)/11,0),IF(C9<=24,ROUND(Inputs!$B$70+(Inputs!$B$71-Inputs!$B$70)*(C9-12)/12,0),IF(C9<=36,ROUND(Inputs!$B$71+(Inputs!$B$72-Inputs!$B$71)*(C9-24)/12,0),IF(C9<=48,ROUND(Inputs!$B$72+(Inputs!$B$73-Inputs!$B$72)*(C9-36)/12,0),ROUND(Inputs!$B$73+(Inputs!$B$74-Inputs!$B$73)*MIN(C9-48,12)/12,0)))))))) -> 257 | E9: =IF(C9=0,0,IF(Inputs!$B$50=1,MIN(D9,MAX(0,Inputs!$B$57-Inputs!$B$54)),MIN(D9,Inputs!$B$57))) -> 257 | F9: =IF(AND(C9>=Inputs!$B$56,Inputs!$B$50=1),Inputs!$B$54,0) -> 0 | G9: =E9+F9 -> 257 | H9: =Inputs!$B$44*(1+Inputs!$B$20)^MAX(0,ROUNDUP(C9/12,0)-1) -> 223 | I9: =IF(C9=0,0,E9*H9+F9*Inputs!$B$55) -> 57311 | J9: =IF(C9=0,0,Inputs!$B$47) -> 6500 | K9: =I9+J9 -> 63811 | L9: =K9/(1+Inputs!$B$6) -> 54077.119 | M9: =(K9*Inputs!$B$49)/(1+Inputs!$B$6) -> 540.77119 | N9: =IF(C9=0,Inputs!$B$34,'Operating Costs'!$C$23*(1+Inputs!$B$19)^MAX(0,ROUNDUP(C9/12,0)-1)) -> 63913.729 | O9: =L9-M9-N9 -> -10377.381 | P9: {=INDEX(Financing!$J$17:$J$79,A9+1)} -> 0 | Q9: {=INDEX(Financing!$G$17:$G$79,A9+1)} -> 0 | R9: =IF(C9=0,0,Inputs!$B$18) -> 6813 | S9: =O9-R9-Q9 -> -17190.381 | T9: =W8 -> 80799.153 | U9: =MAX(0,S9-T9) -> 0 | V9: =U9*Inputs!$B$17 -> 0 | W9: =MAX(0,T9-MAX(0,S9))+MAX(0,-S9) -> 97989.534 | X9: =O9-P9-V9 -> -10377.381 | Y9: =IF(A9=Inputs!$B$63,'Startup & Funding'!$B$16,0) -> 0 | Z9: =Z8+X9+Y9 -> 136560.2 | AA9: {=INDEX(Financing!$E$17:$E$79,A9+1)+INDEX(Financing!$I$17:$I$79,A9+1)} -> 1140000 | AB9: =AB8 -> 312.46637 | AC9: =AC8 -> 424.07501 | AD9: =IF(C9=1,"REOPEN",IF(A9=Inputs!$B$15,"DEBT START",IF(AND(C9>0,MOD(C9,12)=0),"YEAR END","")))
A10: =A9+1 -> 5 | B10: =IF(A10<Inputs!$B$27,"BUILD","OPEN") -> OPEN | C10: =IF(B10="OPEN",A10-Inputs!$B$27+1,0) -> 3 | D10: =IF(C10=0,0,MIN(Inputs!$B$25,IF(C10=1,ROUND(Inputs!$B$24*Inputs!$B$28,0),IF(C10<=12,ROUND(ROUND(Inputs!$B$24*Inputs!$B$28,0)+(Inputs!$B$70-ROUND(Inputs!$B$24*Inputs!$B$28,0))*(C10-1)/11,0),IF(C10<=24,ROUND(Inputs!$B$70+(Inputs!$B$71-Inputs!$B$70)*(C10-12)/12,0),IF(C10<=36,ROUND(Inputs!$B$71+(Inputs!$B$72-Inputs!$B$71)*(C10-24)/12,0),IF(C10<=48,ROUND(Inputs!$B$72+(Inputs!$B$73-Inputs!$B$72)*(C10-36)/12,0),ROUND(Inputs!$B$73+(Inputs!$B$74-Inputs!$B$73)*MIN(C10-48,12)/12,0)))))))) -> 277 | E10: =IF(C10=0,0,IF(Inputs!$B$50=1,MIN(D10,MAX(0,Inputs!$B$57-Inputs!$B$54)),MIN(D10,Inputs!$B$57))) -> 277 | F10: =IF(AND(C10>=Inputs!$B$56,Inputs!$B$50=1),Inputs!$B$54,0) -> 0 | G10: =E10+F10 -> 277 | H10: =Inputs!$B$44*(1+Inputs!$B$20)^MAX(0,ROUNDUP(C10/12,0)-1) -> 223 | I10: =IF(C10=0,0,E10*H10+F10*Inputs!$B$55) -> 61771 | J10: =IF(C10=0,0,Inputs!$B$47) -> 6500 | K10: =I10+J10 -> 68271 | L10: =K10/(1+Inputs!$B$6) -> 57856.78 | M10: =(K10*Inputs!$B$49)/(1+Inputs!$B$6) -> 578.5678 | N10: =IF(C10=0,Inputs!$B$34,'Operating Costs'!$C$23*(1+Inputs!$B$19)^MAX(0,ROUNDUP(C10/12,0)-1)) -> 63913.729 | O10: =L10-M10-N10 -> -6635.5169 | P10: {=INDEX(Financing!$J$17:$J$79,A10+1)} -> 0 | Q10: {=INDEX(Financing!$G$17:$G$79,A10+1)} -> 0 | R10: =IF(C10=0,0,Inputs!$B$18) -> 6813 | S10: =O10-R10-Q10 -> -13448.517 | T10: =W9 -> 97989.534 | U10: =MAX(0,S10-T10) -> 0 | V10: =U10*Inputs!$B$17 -> 0 | W10: =MAX(0,T10-MAX(0,S10))+MAX(0,-S10) -> 111438.05 | X10: =O10-P10-V10 -> -6635.5169 | Y10: =IF(A10=Inputs!$B$63,'Startup & Funding'!$B$16,0) -> 0 | Z10: =Z9+X10+Y10 -> 129924.68 | AA10: {=INDEX(Financing!$E$17:$E$79,A10+1)+INDEX(Financing!$I$17:$I$79,A10+1)} -> 1140000 | AB10: =AB9 -> 312.46637 | AC10: =AC9 -> 424.07501 | AD10: =IF(C10=1,"REOPEN",IF(A10=Inputs!$B$15,"DEBT START",IF(AND(C10>0,MOD(C10,12)=0),"YEAR END","")))
A11: =A10+1 -> 6 | B11: =IF(A11<Inputs!$B$27,"BUILD","OPEN") -> OPEN | C11: =IF(B11="OPEN",A11-Inputs!$B$27+1,0) -> 4 | D11: =IF(C11=0,0,MIN(Inputs!$B$25,IF(C11=1,ROUND(Inputs!$B$24*Inputs!$B$28,0),IF(C11<=12,ROUND(ROUND(Inputs!$B$24*Inputs!$B$28,0)+(Inputs!$B$70-ROUND(Inputs!$B$24*Inputs!$B$28,0))*(C11-1)/11,0),IF(C11<=24,ROUND(Inputs!$B$70+(Inputs!$B$71-Inputs!$B$70)*(C11-12)/12,0),IF(C11<=36,ROUND(Inputs!$B$71+(Inputs!$B$72-Inputs!$B$71)*(C11-24)/12,0),IF(C11<=48,ROUND(Inputs!$B$72+(Inputs!$B$73-Inputs!$B$72)*(C11-36)/12,0),ROUND(Inputs!$B$73+(Inputs!$B$74-Inputs!$B$73)*MIN(C11-48,12)/12,0)))))))) -> 296 | E11: =IF(C11=0,0,IF(Inputs!$B$50=1,MIN(D11,MAX(0,Inputs!$B$57-Inputs!$B$54)),MIN(D11,Inputs!$B$57))) -> 296 | F11: =IF(AND(C11>=Inputs!$B$56,Inputs!$B$50=1),Inputs!$B$54,0) -> 0 | G11: =E11+F11 -> 296 | H11: =Inputs!$B$44*(1+Inputs!$B$20)^MAX(0,ROUNDUP(C11/12,0)-1) -> 223 | I11: =IF(C11=0,0,E11*H11+F11*Inputs!$B$55) -> 66008 | J11: =IF(C11=0,0,Inputs!$B$47) -> 6500 | K11: =I11+J11 -> 72508 | L11: =K11/(1+Inputs!$B$6) -> 61447.458 | M11: =(K11*Inputs!$B$49)/(1+Inputs!$B$6) -> 614.47458 | N11: =IF(C11=0,Inputs!$B$34,'Operating Costs'!$C$23*(1+Inputs!$B$19)^MAX(0,ROUNDUP(C11/12,0)-1)) -> 63913.729 | O11: =L11-M11-N11 -> -3080.7458 | P11: {=INDEX(Financing!$J$17:$J$79,A11+1)} -> 0 | Q11: {=INDEX(Financing!$G$17:$G$79,A11+1)} -> 0 | R11: =IF(C11=0,0,Inputs!$B$18) -> 6813 | S11: =O11-R11-Q11 -> -9893.7458 | T11: =W10 -> 111438.05 | U11: =MAX(0,S11-T11) -> 0 | V11: =U11*Inputs!$B$17 -> 0 | W11: =MAX(0,T11-MAX(0,S11))+MAX(0,-S11) -> 121331.8 | X11: =O11-P11-V11 -> -3080.7458 | Y11: =IF(A11=Inputs!$B$63,'Startup & Funding'!$B$16,0) -> 0 | Z11: =Z10+X11+Y11 -> 126843.93 | AA11: {=INDEX(Financing!$E$17:$E$79,A11+1)+INDEX(Financing!$I$17:$I$79,A11+1)} -> 1140000 | AB11: =AB10 -> 312.46637 | AC11: =AC10 -> 424.07501 | AD11: =IF(C11=1,"REOPEN",IF(A11=Inputs!$B$15,"DEBT START",IF(AND(C11>0,MOD(C11,12)=0),"YEAR END","")))
A12: =A11+1 -> 7 | B12: =IF(A12<Inputs!$B$27,"BUILD","OPEN") -> OPEN | C12: =IF(B12="OPEN",A12-Inputs!$B$27+1,0) -> 5 | D12: =IF(C12=0,0,MIN(Inputs!$B$25,IF(C12=1,ROUND(Inputs!$B$24*Inputs!$B$28,0),IF(C12<=12,ROUND(ROUND(Inputs!$B$24*Inputs!$B$28,0)+(Inputs!$B$70-ROUND(Inputs!$B$24*Inputs!$B$28,0))*(C12-1)/11,0),IF(C12<=24,ROUND(Inputs!$B$70+(Inputs!$B$71-Inputs!$B$70)*(C12-12)/12,0),IF(C12<=36,ROUND(Inputs!$B$71+(Inputs!$B$72-Inputs!$B$71)*(C12-24)/12,0),IF(C12<=48,ROUND(Inputs!$B$72+(Inputs!$B$73-Inputs!$B$72)*(C12-36)/12,0),ROUND(Inputs!$B$73+(Inputs!$B$74-Inputs!$B$73)*MIN(C12-48,12)/12,0)))))))) -> 315 | E12: =IF(C12=0,0,IF(Inputs!$B$50=1,MIN(D12,MAX(0,Inputs!$B$57-Inputs!$B$54)),MIN(D12,Inputs!$B$57))) -> 315 | F12: =IF(AND(C12>=Inputs!$B$56,Inputs!$B$50=1),Inputs!$B$54,0) -> 0 | G12: =E12+F12 -> 315 | H12: =Inputs!$B$44*(1+Inputs!$B$20)^MAX(0,ROUNDUP(C12/12,0)-1) -> 223 | I12: =IF(C12=0,0,E12*H12+F12*Inputs!$B$55) -> 70245 | J12: =IF(C12=0,0,Inputs!$B$47) -> 6500 | K12: =I12+J12 -> 76745 | L12: =K12/(1+Inputs!$B$6) -> 65038.136 | M12: =(K12*Inputs!$B$49)/(1+Inputs!$B$6) -> 650.38136 | N12: =IF(C12=0,Inputs!$B$34,'Operating Costs'!$C$23*(1+Inputs!$B$19)^MAX(0,ROUNDUP(C12/12,0)-1)) -> 63913.729 | O12: =L12-M12-N12 -> 474.02542 | P12: {=INDEX(Financing!$J$17:$J$79,A12+1)} -> 0 | Q12: {=INDEX(Financing!$G$17:$G$79,A12+1)} -> 0 | R12: =IF(C12=0,0,Inputs!$B$18) -> 6813 | S12: =O12-R12-Q12 -> -6338.9746 | T12: =W11 -> 121331.8 | U12: =MAX(0,S12-T12) -> 0 | V12: =U12*Inputs!$B$17 -> 0 | W12: =MAX(0,T12-MAX(0,S12))+MAX(0,-S12) -> 127670.77 | X12: =O12-P12-V12 -> 474.02542 | Y12: =IF(A12=Inputs!$B$63,'Startup & Funding'!$B$16,0) -> 0 | Z12: =Z11+X12+Y12 -> 127317.96 | AA12: {=INDEX(Financing!$E$17:$E$79,A12+1)+INDEX(Financing!$I$17:$I$79,A12+1)} -> 1140000 | AB12: =AB11 -> 312.46637 | AC12: =AC11 -> 424.07501 | AD12: =IF(C12=1,"REOPEN",IF(A12=Inputs!$B$15,"DEBT START",IF(AND(C12>0,MOD(C12,12)=0),"YEAR END","")))
A13: =A12+1 -> 8 | B13: =IF(A13<Inputs!$B$27,"BUILD","OPEN") -> OPEN | C13: =IF(B13="OPEN",A13-Inputs!$B$27+1,0) -> 6 | D13: =IF(C13=0,0,MIN(Inputs!$B$25,IF(C13=1,ROUND(Inputs!$B$24*Inputs!$B$28,0),IF(C13<=12,ROUND(ROUND(Inputs!$B$24*Inputs!$B$28,0)+(Inputs!$B$70-ROUND(Inputs!$B$24*Inputs!$B$28,0))*(C13-1)/11,0),IF(C13<=24,ROUND(Inputs!$B$70+(Inputs!$B$71-Inputs!$B$70)*(C13-12)/12,0),IF(C13<=36,ROUND(Inputs!$B$71+(Inputs!$B$72-Inputs!$B$71)*(C13-24)/12,0),IF(C13<=48,ROUND(Inputs!$B$72+(Inputs!$B$73-Inputs!$B$72)*(C13-36)/12,0),ROUND(Inputs!$B$73+(Inputs!$B$74-Inputs!$B$73)*MIN(C13-48,12)/12,0)))))))) -> 334 | E13: =IF(C13=0,0,IF(Inputs!$B$50=1,MIN(D13,MAX(0,Inputs!$B$57-Inputs!$B$54)),MIN(D13,Inputs!$B$57))) -> 334 | F13: =IF(AND(C13>=Inputs!$B$56,Inputs!$B$50=1),Inputs!$B$54,0) -> 0 | G13: =E13+F13 -> 334 | H13: =Inputs!$B$44*(1+Inputs!$B$20)^MAX(0,ROUNDUP(C13/12,0)-1) -> 223 | I13: =IF(C13=0,0,E13*H13+F13*Inputs!$B$55) -> 74482 | J13: =IF(C13=0,0,Inputs!$B$47) -> 6500 | K13: =I13+J13 -> 80982 | L13: =K13/(1+Inputs!$B$6) -> 68628.814 | M13: =(K13*Inputs!$B$49)/(1+Inputs!$B$6) -> 686.28814 | N13: =IF(C13=0,Inputs!$B$34,'Operating Costs'!$C$23*(1+Inputs!$B$19)^MAX(0,ROUNDUP(C13/12,0)-1)) -> 63913.729 | O13: =L13-M13-N13 -> 4028.7966 | P13: {=INDEX(Financing!$J$17:$J$79,A13+1)} -> 0 | Q13: {=INDEX(Financing!$G$17:$G$79,A13+1)} -> 0 | R13: =IF(C13=0,0,Inputs!$B$18) -> 6813 | S13: =O13-R13-Q13 -> -2784.2034 | T13: =W12 -> 127670.77 | U13: =MAX(0,S13-T13) -> 0 | V13: =U13*Inputs!$B$17 -> 0 | W13: =MAX(0,T13-MAX(0,S13))+MAX(0,-S13) -> 130454.97 | X13: =O13-P13-V13 -> 4028.7966 | Y13: =IF(A13=Inputs!$B$63,'Startup & Funding'!$B$16,0) -> 0 | Z13: =Z12+X13+Y13 -> 131346.76 | AA13: {=INDEX(Financing!$E$17:$E$79,A13+1)+INDEX(Financing!$I$17:$I$79,A13+1)} -> 1140000 | AB13: =AB12 -> 312.46637 | AC13: =AC12 -> 424.07501 | AD13: =IF(C13=1,"REOPEN",IF(A13=Inputs!$B$15,"DEBT START",IF(AND(C13>0,MOD(C13,12)=0),"YEAR END","")))
A14: =A13+1 -> 9 | B14: =IF(A14<Inputs!$B$27,"BUILD","OPEN") -> OPEN | C14: =IF(B14="OPEN",A14-Inputs!$B$27+1,0) -> 7 | D14: =IF(C14=0,0,MIN(Inputs!$B$25,IF(C14=1,ROUND(Inputs!$B$24*Inputs!$B$28,0),IF(C14<=12,ROUND(ROUND(Inputs!$B$24*Inputs!$B$28,0)+(Inputs!$B$70-ROUND(Inputs!$B$24*Inputs!$B$28,0))*(C14-1)/11,0),IF(C14<=24,ROUND(Inputs!$B$70+(Inputs!$B$71-Inputs!$B$70)*(C14-12)/12,0),IF(C14<=36,ROUND(Inputs!$B$71+(Inputs!$B$72-Inputs!$B$71)*(C14-24)/12,0),IF(C14<=48,ROUND(Inputs!$B$72+(Inputs!$B$73-Inputs!$B$72)*(C14-36)/12,0),ROUND(Inputs!$B$73+(Inputs!$B$74-Inputs!$B$73)*MIN(C14-48,12)/12,0)))))))) -> 354 | E14: =IF(C14=0,0,IF(Inputs!$B$50=1,MIN(D14,MAX(0,Inputs!$B$57-Inputs!$B$54)),MIN(D14,Inputs!$B$57))) -> 354 | F14: =IF(AND(C14>=Inputs!$B$56,Inputs!$B$50=1),Inputs!$B$54,0) -> 0 | G14: =E14+F14 -> 354 | H14: =Inputs!$B$44*(1+Inputs!$B$20)^MAX(0,ROUNDUP(C14/12,0)-1) -> 223 | I14: =IF(C14=0,0,E14*H14+F14*Inputs!$B$55) -> 78942 | J14: =IF(C14=0,0,Inputs!$B$47) -> 6500 | K14: =I14+J14 -> 85442 | L14: =K14/(1+Inputs!$B$6) -> 72408.475 | M14: =(K14*Inputs!$B$49)/(1+Inputs!$B$6) -> 724.08475 | N14: =IF(C14=0,Inputs!$B$34,'Operating Costs'!$C$23*(1+Inputs!$B$19)^MAX(0,ROUNDUP(C14/12,0)-1)) -> 63913.729 | O14: =L14-M14-N14 -> 7770.661 | P14: {=INDEX(Financing!$J$17:$J$79,A14+1)} -> 0 | Q14: {=INDEX(Financing!$G$17:$G$79,A14+1)} -> 0 | R14: =IF(C14=0,0,Inputs!$B$18) -> 6813 | S14: =O14-R14-Q14 -> 957.66102 | T14: =W13 -> 130454.97 | U14: =MAX(0,S14-T14) -> 0 | V14: =U14*Inputs!$B$17 -> 0 | W14: =MAX(0,T14-MAX(0,S14))+MAX(0,-S14) -> 129497.31 | X14: =O14-P14-V14 -> 7770.661 | Y14: =IF(A14=Inputs!$B$63,'Startup & Funding'!$B$16,0) -> 0 | Z14: =Z13+X14+Y14 -> 139117.42 | AA14: {=INDEX(Financing!$E$17:$E$79,A14+1)+INDEX(Financing!$I$17:$I$79,A14+1)} -> 1140000 | AB14: =AB13 -> 312.46637 | AC14: =AC13 -> 424.07501 | AD14: =IF(C14=1,"REOPEN",IF(A14=Inputs!$B$15,"DEBT START",IF(AND(C14>0,MOD(C14,12)=0),"YEAR END","")))
A15: =A14+1 -> 10 | B15: =IF(A15<Inputs!$B$27,"BUILD","OPEN") -> OPEN | C15: =IF(B15="OPEN",A15-Inputs!$B$27+1,0) -> 8 | D15: =IF(C15=0,0,MIN(Inputs!$B$25,IF(C15=1,ROUND(Inputs!$B$24*Inputs!$B$28,0),IF(C15<=12,ROUND(ROUND(Inputs!$B$24*Inputs!$B$28,0)+(Inputs!$B$70-ROUND(Inputs!$B$24*Inputs!$B$28,0))*(C15-1)/11,0),IF(C15<=24,ROUND(Inputs!$B$70+(Inputs!$B$71-Inputs!$B$70)*(C15-12)/12,0),IF(C15<=36,ROUND(Inputs!$B$71+(Inputs!$B$72-Inputs!$B$71)*(C15-24)/12,0),IF(C15<=48,ROUND(Inputs!$B$72+(Inputs!$B$73-Inputs!$B$72)*(C15-36)/12,0),ROUND(Inputs!$B$73+(Inputs!$B$74-Inputs!$B$73)*MIN(C15-48,12)/12,0)))))))) -> 373 | E15: =IF(C15=0,0,IF(Inputs!$B$50=1,MIN(D15,MAX(0,Inputs!$B$57-Inputs!$B$54)),MIN(D15,Inputs!$B$57))) -> 373 | F15: =IF(AND(C15>=Inputs!$B$56,Inputs!$B$50=1),Inputs!$B$54,0) -> 0 | G15: =E15+F15 -> 373 | H15: =Inputs!$B$44*(1+Inputs!$B$20)^MAX(0,ROUNDUP(C15/12,0)-1) -> 223 | I15: =IF(C15=0,0,E15*H15+F15*Inputs!$B$55) -> 83179 | J15: =IF(C15=0,0,Inputs!$B$47) -> 6500 | K15: =I15+J15 -> 89679 | L15: =K15/(1+Inputs!$B$6) -> 75999.153 | M15: =(K15*Inputs!$B$49)/(1+Inputs!$B$6) -> 759.99153 | N15: =IF(C15=0,Inputs!$B$34,'Operating Costs'!$C$23*(1+Inputs!$B$19)^MAX(0,ROUNDUP(C15/12,0)-1)) -> 63913.729 | O15: =L15-M15-N15 -> 11325.432 | P15: {=INDEX(Financing!$J$17:$J$79,A15+1)} -> 0 | Q15: {=INDEX(Financing!$G$17:$G$79,A15+1)} -> 0 | R15: =IF(C15=0,0,Inputs!$B$18) -> 6813 | S15: =O15-R15-Q15 -> 4512.4322 | T15: =W14 -> 129497.31 | U15: =MAX(0,S15-T15) -> 0 | V15: =U15*Inputs!$B$17 -> 0 | W15: =MAX(0,T15-MAX(0,S15))+MAX(0,-S15) -> 124984.88 | X15: =O15-P15-V15 -> 11325.432 | Y15: =IF(A15=Inputs!$B$63,'Startup & Funding'!$B$16,0) -> 0 | Z15: =Z14+X15+Y15 -> 150442.85 | AA15: {=INDEX(Financing!$E$17:$E$79,A15+1)+INDEX(Financing!$I$17:$I$79,A15+1)} -> 1140000 | AB15: =AB14 -> 312.46637 | AC15: =AC14 -> 424.07501 | AD15: =IF(C15=1,"REOPEN",IF(A15=Inputs!$B$15,"DEBT START",IF(AND(C15>0,MOD(C15,12)=0),"YEAR END","")))
A16: =A15+1 -> 11 | B16: =IF(A16<Inputs!$B$27,"BUILD","OPEN") -> OPEN | C16: =IF(B16="OPEN",A16-Inputs!$B$27+1,0) -> 9 | D16: =IF(C16=0,0,MIN(Inputs!$B$25,IF(C16=1,ROUND(Inputs!$B$24*Inputs!$B$28,0),IF(C16<=12,ROUND(ROUND(Inputs!$B$24*Inputs!$B$28,0)+(Inputs!$B$70-ROUND(Inputs!$B$24*Inputs!$B$28,0))*(C16-1)/11,0),IF(C16<=24,ROUND(Inputs!$B$70+(Inputs!$B$71-Inputs!$B$70)*(C16-12)/12,0),IF(C16<=36,ROUND(Inputs!$B$71+(Inputs!$B$72-Inputs!$B$71)*(C16-24)/12,0),IF(C16<=48,ROUND(Inputs!$B$72+(Inputs!$B$73-Inputs!$B$72)*(C16-36)/12,0),ROUND(Inputs!$B$73+(Inputs!$B$74-Inputs!$B$73)*MIN(C16-48,12)/12,0)))))))) -> 392 | E16: =IF(C16=0,0,IF(Inputs!$B$50=1,MIN(D16,MAX(0,Inputs!$B$57-Inputs!$B$54)),MIN(D16,Inputs!$B$57))) -> 392 | F16: =IF(AND(C16>=Inputs!$B$56,Inputs!$B$50=1),Inputs!$B$54,0) -> 0 | G16: =E16+F16 -> 392 | H16: =Inputs!$B$44*(1+Inputs!$B$20)^MAX(0,ROUNDUP(C16/12,0)-1) -> 223 | I16: =IF(C16=0,0,E16*H16+F16*Inputs!$B$55) -> 87416 | J16: =IF(C16=0,0,Inputs!$B$47) -> 6500 | K16: =I16+J16 -> 93916 | L16: =K16/(1+Inputs!$B$6) -> 79589.831 | M16: =(K16*Inputs!$B$49)/(1+Inputs!$B$6) -> 795.89831 | N16: =IF(C16=0,Inputs!$B$34,'Operating Costs'!$C$23*(1+Inputs!$B$19)^MAX(0,ROUNDUP(C16/12,0)-1)) -> 63913.729 | O16: =L16-M16-N16 -> 14880.203 | P16: {=INDEX(Financing!$J$17:$J$79,A16+1)} -> 0 | Q16: {=INDEX(Financing!$G$17:$G$79,A16+1)} -> 0 | R16: =IF(C16=0,0,Inputs!$B$18) -> 6813 | S16: =O16-R16-Q16 -> 8067.2034 | T16: =W15 -> 124984.88 | U16: =MAX(0,S16-T16) -> 0 | V16: =U16*Inputs!$B$17 -> 0 | W16: =MAX(0,T16-MAX(0,S16))+MAX(0,-S16) -> 116917.68 | X16: =O16-P16-V16 -> 14880.203 | Y16: =IF(A16=Inputs!$B$63,'Startup & Funding'!$B$16,0) -> 0 | Z16: =Z15+X16+Y16 -> 165323.05 | AA16: {=INDEX(Financing!$E$17:$E$79,A16+1)+INDEX(Financing!$I$17:$I$79,A16+1)} -> 1140000 | AB16: =AB15 -> 312.46637 | AC16: =AC15 -> 424.07501 | AD16: =IF(C16=1,"REOPEN",IF(A16=Inputs!$B$15,"DEBT START",IF(AND(C16>0,MOD(C16,12)=0),"YEAR END","")))
A17: =A16+1 -> 12 | B17: =IF(A17<Inputs!$B$27,"BUILD","OPEN") -> OPEN | C17: =IF(B17="OPEN",A17-Inputs!$B$27+1,0) -> 10 | D17: =IF(C17=0,0,MIN(Inputs!$B$25,IF(C17=1,ROUND(Inputs!$B$24*Inputs!$B$28,0),IF(C17<=12,ROUND(ROUND(Inputs!$B$24*Inputs!$B$28,0)+(Inputs!$B$70-ROUND(Inputs!$B$24*Inputs!$B$28,0))*(C17-1)/11,0),IF(C17<=24,ROUND(Inputs!$B$70+(Inputs!$B$71-Inputs!$B$70)*(C17-12)/12,0),IF(C17<=36,ROUND(Inputs!$B$71+(Inputs!$B$72-Inputs!$B$71)*(C17-24)/12,0),IF(C17<=48,ROUND(Inputs!$B$72+(Inputs!$B$73-Inputs!$B$72)*(C17-36)/12,0),ROUND(Inputs!$B$73+(Inputs!$B$74-Inputs!$B$73)*MIN(C17-48,12)/12,0)))))))) -> 411 | E17: =IF(C17=0,0,IF(Inputs!$B$50=1,MIN(D17,MAX(0,Inputs!$B$57-Inputs!$B$54)),MIN(D17,Inputs!$B$57))) -> 411 | F17: =IF(AND(C17>=Inputs!$B$56,Inputs!$B$50=1),Inputs!$B$54,0) -> 0 | G17: =E17+F17 -> 411 | H17: =Inputs!$B$44*(1+Inputs!$B$20)^MAX(0,ROUNDUP(C17/12,0)-1) -> 223 | I17: =IF(C17=0,0,E17*H17+F17*Inputs!$B$55) -> 91653 | J17: =IF(C17=0,0,Inputs!$B$47) -> 6500 | K17: =I17+J17 -> 98153 | L17: =K17/(1+Inputs!$B$6) -> 83180.508 | M17: =(K17*Inputs!$B$49)/(1+Inputs!$B$6) -> 831.80508 | N17: =IF(C17=0,Inputs!$B$34,'Operating Costs'!$C$23*(1+Inputs!$B$19)^MAX(0,ROUNDUP(C17/12,0)-1)) -> 63913.729 | O17: =L17-M17-N17 -> 18434.975 | P17: {=INDEX(Financing!$J$17:$J$79,A17+1)} -> 20881.221 | Q17: {=INDEX(Financing!$G$17:$G$79,A17+1)} -> 3562.5 | R17: =IF(C17=0,0,Inputs!$B$18) -> 6813 | S17: =O17-R17-Q17 -> 8059.4746 | T17: =W16 -> 116917.68 | U17: =MAX(0,S17-T17) -> 0 | V17: =U17*Inputs!$B$17 -> 0 | W17: =MAX(0,T17-MAX(0,S17))+MAX(0,-S17) -> 108858.2 | X17: =O17-P17-V17 -> -2446.2462 | Y17: =IF(A17=Inputs!$B$63,'Startup & Funding'!$B$16,0) -> 0 | Z17: =Z16+X17+Y17 -> 162876.81 | AA17: {=INDEX(Financing!$E$17:$E$79,A17+1)+INDEX(Financing!$I$17:$I$79,A17+1)} -> 1122681.3 | AB17: =AB16 -> 312.46637 | AC17: =AC16 -> 424.07501 | AD17: =IF(C17=1,"REOPEN",IF(A17=Inputs!$B$15,"DEBT START",IF(AND(C17>0,MOD(C17,12)=0),"YEAR END",""))) -> DEBT START
... A67: =A66+1 -> 62 | B67: =IF(A67<Inputs!$B$27,"BUILD","OPEN") -> OPEN | C67: =IF(B67="OPEN",A67-Inputs!$B$27+1,0) -> 60 | D67: =IF(C67=0,0,MIN(Inputs!$B$25,IF(C67=1,ROUND(Inputs!$B$24*Inputs!$B$28,0),IF(C67<=12,ROUND(ROUND(Inputs!$B$24*Inputs!$B$28,0)+(Inputs!$B$70-ROUND(Inputs!$B$24*Inputs!$B$28,0))*(C67-1)/11,0),IF(C67<=24,ROUND(Inputs!$B$70+(Inputs!$B$71-Inputs!$B$70)*(C67-12)/12,0),IF(C67<=36,ROUND(Inputs!$B$71+(Inputs!$B$72-Inputs!$B$71)*(C67-24)/12,0),IF(C67<=48,ROUND(Inputs!$B$72+(Inputs!$B$73-Inputs!$B$72)*(C67-36)/12,0),ROUND(Inputs!$B$73+(Inputs!$B$74-Inputs!$B$73)*MIN(C67-48,12)/12,0)))))))) -> 850 | E67: =IF(C67=0,0,IF(Inputs!$B$50=1,MIN(D67,MAX(0,Inputs!$B$57-Inputs!$B$54)),MIN(D67,Inputs!$B$57))) -> 850 | F67: =IF(AND(C67>=Inputs!$B$56,Inputs!$B$50=1),Inputs!$B$54,0) -> 0 | G67: =E67+F67 -> 850 | H67: =Inputs!$B$44*(1+Inputs!$B$20)^MAX(0,ROUNDUP(C67/12,0)-1) -> 223 | I67: =IF(C67=0,0,E67*H67+F67*Inputs!$B$55) -> 189550 | J67: =IF(C67=0,0,Inputs!$B$47) -> 6500 | K67: =I67+J67 -> 196050 | L67: =K67/(1+Inputs!$B$6) -> 166144.07 | M67: =(K67*Inputs!$B$49)/(1+Inputs!$B$6) -> 1661.4407 | N67: =IF(C67=0,Inputs!$B$34,'Operating Costs'!$C$23*(1+Inputs!$B$19)^MAX(0,ROUNDUP(C67/12,0)-1)) -> 63913.729 | O67: =L67-M67-N67 -> 100568.9 | P67: {=INDEX(Financing!$J$17:$J$79,A67+1)} -> 20881.221 | Q67: {=INDEX(Financing!$G$17:$G$79,A67+1)} -> 653.8948 | R67: =IF(C67=0,0,Inputs!$B$18) -> 6813 | S67: =O67-R67-Q67 -> 93102.004 | T67: =W66 -> 0 | U67: =MAX(0,S67-T67) -> 93102.004 | V67: =U67*Inputs!$B$17 -> 21413.461 | W67: =MAX(0,T67-MAX(0,S67))+MAX(0,-S67) -> 0 | X67: =O67-P67-V67 -> 58274.217 | Y67: =IF(A67=Inputs!$B$63,'Startup & Funding'!$B$16,0) -> 0 | Z67: =Z66+X67+Y67 -> 1949791.8 | AA67: {=INDEX(Financing!$E$17:$E$79,A67+1)+INDEX(Financing!$I$17:$I$79,A67+1)} -> 184967.15 | AB67: =AB66 -> 312.46637 | AC67: =AC66 -> 424.07501 | AD67: =IF(C67=1,"REOPEN",IF(A67=Inputs!$B$15,"DEBT START",IF(AND(C67>0,MOD(C67,12)=0),"YEAR END",""))) -> YEAR END

Sheet 5-Year Summary
A1: 5 Operating Years - Target-Driven Plan
A2: Year 1 means the first 12 months AFTER reopening. The 3 build months are shown separately in the 63-month liquidity timeline.
A4: Metric | B4: Operating Year 1 | C4: Year 2 | D4: Year 3 | E4: Year 4 | F4: Year 5 | G4: Comment
A5: Avg total members incl. Moatza | B5: =AVERAGE('Monthly Base'!G8:G19) -> 344 | C5: =AVERAGE('Monthly Base'!G20:G31) -> 531.5 | D5: =AVERAGE('Monthly Base'!G32:G43) -> 667.75 | E5: =AVERAGE('Monthly Base'!G44:G55) -> 765.75 | F5: =AVERAGE('Monthly Base'!G56:G67) -> 827.16667 | G5: Target-driven monthly ramp
A6: End total members incl. Moatza | B6: ='Monthly Base'!G19 -> 450 | C6: ='Monthly Base'!G31 -> 600 | D6: ='Monthly Base'!G43 -> 725 | E6: ='Monthly Base'!G55 -> 800 | F6: ='Monthly Base'!G67 -> 850
A7: Gross billings | B7: =SUM('Monthly Base'!K8:K19) -> 998544 | C7: =SUM('Monthly Base'!K20:K31) -> 1500294 | D7: =SUM('Monthly Base'!K32:K43) -> 1864899 | E7: =SUM('Monthly Base'!K44:K55) -> 2127147 | F7: =SUM('Monthly Base'!K56:K67) -> 2291498 | G7: Incl VAT
A8: Net revenue ex VAT | B8: =SUM('Monthly Base'!L8:L19) -> 846223.73 | C8: =SUM('Monthly Base'!L20:L31) -> 1271435.6 | D8: =SUM('Monthly Base'!L32:L43) -> 1580422.9 | E8: =SUM('Monthly Base'!L44:L55) -> 1802666.9 | F8: =SUM('Monthly Base'!L56:L67) -> 1941947.5 | G8: P&L revenue
A9: EBITDA | B9: =SUM('Monthly Base'!O8:O19) -> 70796.746 | C9: =SUM('Monthly Base'!O20:O31) -> 491756.49 | D9: =SUM('Monthly Base'!O32:O43) -> 797653.91 | E9: =SUM('Monthly Base'!O44:O55) -> 1017675.5 | F9: =SUM('Monthly Base'!O56:O67) -> 1155563.2 | G9: Before financing/tax
A10: Total debt payments incl. semiannual lump-sum prepay | B10: =SUM('Owner Pay'!L24:L35)+SUM('Owner Pay'!U24:V35) -> 81666.476 | C10: =SUM('Owner Pay'!L36:L47)+SUM('Owner Pay'!U36:V47) -> 424218.24 | D10: =SUM('Owner Pay'!L48:L59)+SUM('Owner Pay'!U48:V59) -> 636626.7 | E10: =SUM('Owner Pay'!L60:L71)+SUM('Owner Pay'!U60:V71) -> 58610.857 | F10: =SUM('Owner Pay'!L72:L83)+SUM('Owner Pay'!U72:V83) -> 0 | G10: Grace ends during Year 1 because build consumes grace
A11: Corporate tax — debt-first plan | B11: =SUM('Owner Pay'!R24:R35) -> 0 | C11: =SUM('Owner Pay'!R36:R47) -> 67538.255 | D11: =SUM('Owner Pay'!R48:R59) -> 161027.21 | E11: =SUM('Owner Pay'!R60:R71) -> 215261.49 | F11: =SUM('Owner Pay'!R72:R83) -> 246975.66 | G11: Loss-carryforward model
A12: Net cash after debt, tax & owner salaries | B12: =SUM('Owner Pay'!D24:D35)-B10-B11-SUM('Owner Pay'!P24:P35) -> -10869.73 | C12: =SUM('Owner Pay'!D36:D47)-C10-C11-SUM('Owner Pay'!P36:P47) -> 0 | D12: =SUM('Owner Pay'!D48:D59)-D10-D11-SUM('Owner Pay'!P48:P59) -> 2.910383e-10 | E12: =SUM('Owner Pay'!D60:D71)-E10-E11-SUM('Owner Pay'!P60:P71) -> 743803.18 | F12: =SUM('Owner Pay'!D72:D83)-F10-F11-SUM('Owner Pay'!P72:P83) -> 908587.57 | G12: After debt + tax
A13: Contractual DSCR | B13: =IF(SUM('Owner Pay'!L24:L35)=0,0,B9/SUM('Owner Pay'!L24:L35)) -> 1.1301502 | C13: =IF(SUM('Owner Pay'!L36:L47)=0,0,C9/SUM('Owner Pay'!L36:L47)) -> 1.9625149 | D13: =IF(SUM('Owner Pay'!L48:L59)=0,0,D9/SUM('Owner Pay'!L48:L59)) -> 3.1832985 | E13: =IF(SUM('Owner Pay'!L60:L71)=0,0,E9/SUM('Owner Pay'!L60:L71)) -> 42.403147 | F13: =IF(SUM('Owner Pay'!L72:L83)=0,0,F9/SUM('Owner Pay'!L72:L83)) -> 0 | G13: EBITDA / debt service
A14: Year-end company cash — no distributions | B14: ='Owner Pay'!Z35 -> 150000 | C14: ='Owner Pay'!Z47 -> 150000 | D14: ='Owner Pay'!Z59 -> 150000 | E14: ='Owner Pay'!Z71 -> 893803.18 | F14: ='Owner Pay'!Z83 -> 1802390.8 | G14: Includes startup headroom + build VAT refund
A15: Year-end debt balance | B15: ='Owner Pay'!Y35 -> 1068862.7 | C15: ='Owner Pay'!Y47 -> 679457.94 | D15: ='Owner Pay'!Y59 -> 58610.857 | E15: ='Owner Pay'!Y71 -> 0 | F15: ='Owner Pay'!Y83 -> 0
A16: Cumulative net cash after debt/tax/salaries | B16: =B12 -> -10869.73 | C16: =B16+C12 -> -10869.73 | D16: =C16+D12 -> -10869.73 | E16: =D16+E12 -> 732933.45 | F16: =E16+F12 -> 1641521 | G16: Excludes one-time VAT refund/headroom
A17: Partner 1 50% of year-end distributable cash | B17: =IF(B15=0,MAX(0,B14-Inputs!$B$80)*Inputs!$B$7,0) -> 0 | C17: =IF(C15=0,MAX(0,C14-Inputs!$B$80)*Inputs!$B$7,0) -> 0 | D17: =IF(D15=0,MAX(0,D14-Inputs!$B$80)*Inputs!$B$7,0) -> 0 | E17: =IF(E15=0,MAX(0,E14-Inputs!$B$80)*Inputs!$B$7,0) -> 371901.59 | F17: =IF(F15=0,MAX(0,F14-Inputs!$B$80)*Inputs!$B$7,0) -> 826195.38 | G17: Not take-home
A18: Partner 2 50% of year-end distributable cash | B18: =IF(B15=0,MAX(0,B14-Inputs!$B$80)*Inputs!$B$8,0) -> 0 | C18: =IF(C15=0,MAX(0,C14-Inputs!$B$80)*Inputs!$B$8,0) -> 0 | D18: =IF(D15=0,MAX(0,D14-Inputs!$B$80)*Inputs!$B$8,0) -> 0 | E18: =IF(E15=0,MAX(0,E14-Inputs!$B$80)*Inputs!$B$8,0) -> 371901.59 | F18: =IF(F15=0,MAX(0,F14-Inputs!$B$80)*Inputs!$B$8,0) -> 826195.38 | G18: Not take-home
A19: Owner gross salaries paid | B19: =SUM('Owner Pay'!N24:O35) -> 0 | C19: =SUM('Owner Pay'!N36:O47) -> 0 | D19: =SUM('Owner Pay'!N48:O59) -> 0 | E19: =SUM('Owner Pay'!N60:O71) -> 0 | F19: =SUM('Owner Pay'!N72:O83) -> 0 | I19: Metric | J19: Y1 | K19: Y2 | L19: Y3 | M19: Y4 | N19: Y5
A20: Company owner payroll cost | B20: =SUM('Owner Pay'!P24:P35) -> 0 | C20: =SUM('Owner Pay'!P36:P47) -> 0 | D20: =SUM('Owner Pay'!P48:P59) -> 0 | E20: =SUM('Owner Pay'!P60:P71) -> 0 | F20: =SUM('Owner Pay'!P72:P83) -> 0 | I20: EBITDA | J20: =B9 -> 70796.746 | K20: =C9 -> 491756.49 | L20: =D9 -> 797653.91 | M20: =E9 -> 1017675.5 | N20: =F9 -> 1155563.2
A21: Key thresholds | I21: Debt service | J21: =B10 -> 81666.476 | K21: =C10 -> 424218.24 | L21: =D10 -> 636626.7 | M21: =E10 -> 58610.857 | N21: =F10 -> 0
A22: Metric | B22: Result | C22: Interpretation | I22: Pre-owner cash | J22: =B12 -> -10869.73 | K22: =C12 -> 0 | L22: =D12 -> 2.910383e-10 | M22: =E12 -> 743803.18 | N22: =F12 -> 908587.57
A23: Reopening members | B23: =ROUND(Inputs!$B$24*Inputs!$B$28,0) -> 238 | C23: 75% of 317
A24: Operating break-even members | B24: ='Monthly Base'!AB5 -> 312.46637 | C24: Before debt / tax
A25: Post-debt break-even members | B25: ='Monthly Base'!AC5 -> 424.07501 | C25: After loan payments start
A26: Operating month payments begin | B26: =Financing!$D$13 -> 10 | C26: Build months consume grace
A27: Operating month base reaches post-debt break-even | B27: =MIN(60,IFERROR(MATCH(B25,'Monthly Base'!G8:G67,0),MATCH(B25,'Monthly Base'!G8:G67,1)+1)) -> 11 | C27: Based on the target-driven membership ramp
A28: Operating month reaches Year-1 member target | B28: 12 | C28: By design: end of operating Year 1
A29: Operating month reaches 600 members | B29: =MIN(60,IFERROR(MATCH(600,'Monthly Base'!G8:G67,0),MATCH(600,'Monthly Base'!G8:G67,1)+1)) -> 24 | C29: Growth milestone
A30: Minimum cash balance in full timeline | B30: {=MIN(MIN('Owner Pay'!Z21:Z83),INDEX('Owner Pay'!F21:F83,Inputs!$B$63+1)+INDEX('Owner Pay'!D21:D83,Inputs!$B$63+1))} -> 8936.0014 | C30: Primary runway test incl. pre-refund low
A31: Debt-free operating month | B31: ='Owner Pay'!B9 -> 42 | C31: Semiannual debt-sweep plan
A32: Owner salaries start operating month | B32: ='Owner Pay'!B10 -> OFF | C32: Month after all debt is repaid
A33: Interest saved vs scheduled amortization | B33: ='Owner Pay'!B13 -> 48787.14 | C33: Estimated interest avoided
A34: Contractual monthly debt service eliminated | B34: ='Owner Pay'!B14 -> 20881.221 | C34: Cash flow freed once debt is gone
A35: Company monthly owner payroll after debt | B35: ='Owner Pay'!B12 -> 24000 | C35: Includes employer load
A36: Year 5 cash available for distribution | B36: ='Owner Pay'!B16 -> 1652390.8 | C36: Above reserve; not automatically distributed
A37: Partner 1 50% if fully distributed | B37: ='Owner Pay'!B17 -> 826195.38 | C37: Before personal/dividend tax
A38: Partner 2 50% if fully distributed | B38: ='Owner Pay'!B16*Inputs!$B$8 -> 826195.38 | C38: Before personal/dividend tax
A39: Debt-sweep cash reserve target | B39: =Inputs!$B$80 -> 150000 | C39: Kept in company for resilience / peace of mind
A40: Months debt eliminated early | B40: ='Owner Pay'!B18 -> 27 | C40: Vs scheduled maturity

Sheet Owner Pay
A1: Semiannual Debt-Sweep Capital Allocation & Owner Pay
A2: Current base case: debt-max policy with equal 50/50 owner salaries after debt. Both partners work in the business; Hodaya is staff. See Salary Scenarios for alternatives.
A4: Metric | B4: Result | C4: Interpretation
A5: Debt-sweep cash reserve target | B5: =Inputs!$B$80 -> 150000 | C5: Cash deliberately retained in the company.
A6: Excess cash used at each sweep | B6: =Inputs!$B$81 -> 1 | C6: Semiannual lump-sum review; Prime debt first.
A7: Debt repayment priority | B7: =Inputs!$B$83 -> Loan B (Prime) → Loan A (0%) | C7: Prime debt first, then 0% debt.
A8: Debt-free timeline month | B8: {=IFERROR(INDEX(A21:A83,MATCH(0,Y21:Y83,0)),"Beyond model")} -> 44 | C8: Timeline includes the renovation months.
A9: Debt-free operating month | B9: {=IFERROR(INDEX(C21:C83,MATCH(0,Y21:Y83,0)),"Beyond model")} -> 42 | C9: Month after reopening when total debt reaches zero.
A10: Salaries start operating month | B10: =IF(Inputs!$B$84=1,IF(ISNUMBER(B9),B9+1,"Beyond model"),"OFF") -> OFF | C10: Starts the month after all debt is gone.
A11: Post-debt owner gross salaries / month | B11: =Inputs!$B$85+Inputs!$B$86 -> 20000 | C11: Current base: ₪10k gross per partner, equal 50/50.
A12: Company owner payroll cost / month | B12: =B11*(1+Inputs!$B$66) -> 24000 | C12: Includes modeled 20% employer load.
A13: Interest saved vs scheduled amortization | B13: =SUM(Financing!$G$17:$G$79)-SUM(J21:J83) -> 48787.14 | C13: Estimated Loan B interest avoided by accelerated payoff.
A14: Contractual monthly debt service eliminated | B14: =Financing!$D$10 -> 20881.221 | C14: Monthly contractual payment freed once debt is gone.
A15: Year 5 company cash — no distributions | B15: =Z83 -> 1802390.8 | C15: Cash remains in company unless owners choose a distribution.
A16: Year 5 cash available for distribution | B16: =IF(Y83=0,MAX(0,Z83-Inputs!$B$80),0) -> 1652390.8 | C16: Above the reserve floor only; no automatic distribution modeled.
A17: 50% per partner if fully distributed | B17: =B16*Inputs!$B$7 -> 826195.38 | C17: Before personal/dividend taxes; not automatically paid.
A18: Months debt eliminated early | B18: =MAX(0,Inputs!$B$15+Inputs!$B$16-1-B8) -> 27 | C18: Compared with the 12-month grace + 60 scheduled-payment maturity.
A19: 63-Month Semiannual Debt-Sweep Capital Schedule
A20: Timeline Mo | B20: Phase | C20: Operating Mo | D20: EBITDA | E20: Build VAT Refund | F20: Opening Cash | G20: Loan A Opening | H20: Loan B Opening | I20: Loan A Scheduled | J20: Loan B Interest | K20: Loan B Scheduled | L20: Scheduled Debt | M20: Tax Loss CF Begin | N20: Partner 1 Gross | O20: Partner 2 Gross | P20: Owner Payroll Cost | Q20: Taxable Before Loss | R20: Corporate Tax | S20: Tax Loss CF End | T20: Cash Before Extra Debt | U20: Extra to Loan B | V20: Extra to Loan A | W20: Loan A Closing | X20: Loan B Closing | Y20: Total Debt | Z20: Ending Cash
A21: 0 | B21: {=INDEX('Monthly Base'!$B$5:$B$67,A21+1)} -> BUILD | C21: {=INDEX('Monthly Base'!$C$5:$C$67,A21+1)} -> 0 | D21: {=INDEX('Monthly Base'!$O$5:$O$67,A21+1)} -> -20018 | E21: {=INDEX('Monthly Base'!$Y$5:$Y$67,A21+1)} -> 0 | F21: ='Startup & Funding'!$B$19 -> 68990.001 | G21: =Inputs!$B$9 -> 240000 | H21: =Inputs!$B$10 -> 900000 | I21: =IF(OR(A21<Inputs!$B$15,G21<=0),0,MIN(Financing!$B$10,G21)) -> 0 | J21: =IF(OR(A21<Inputs!$B$15,H21<=0),0,H21*Inputs!$B$13/12) -> 0 | K21: =IF(OR(A21<Inputs!$B$15,H21<=0),0,MIN(Financing!$C$10,H21+J21)) -> 0 | L21: =I21+K21 -> 0 | M21: 0 | N21: 0 | O21: 0 | P21: =(N21+O21)*(1+Inputs!$B$66) -> 0 | Q21: =D21-J21-IF(C21=0,0,Inputs!$B$18)-P21 -> -20018 | R21: =MAX(0,Q21-M21)*Inputs!$B$17 -> 0 | S21: =MAX(0,M21-MAX(0,Q21))+MAX(0,-Q21) -> 20018 | T21: =F21+D21+E21-L21-P21-R21 -> 48972.001 | U21: =IF(AND(Inputs!$B$79=1,B21="OPEN",A21>=Inputs!$B$82,C21>=Inputs!$B$91,MOD(C21-Inputs!$B$91,Inputs!$B$90)=0),MIN(MAX(0,T21-Inputs!$B$80)*Inputs!$B$81,MAX(0,H21+J21-K21)),0) -> 0 | V21: =IF(AND(Inputs!$B$79=1,B21="OPEN",A21>=Inputs!$B$82,C21>=Inputs!$B$91,MOD(C21-Inputs!$B$91,Inputs!$B$90)=0),MIN(MAX(0,MAX(0,T21-Inputs!$B$80)*Inputs!$B$81-U21),MAX(0,G21-I21)),0) -> 0 | W21: =MAX(0,G21-I21-V21) -> 240000 | X21: =MAX(0,H21+J21-K21-U21) -> 900000 | Y21: =W21+X21 -> 1140000 | Z21: =T21-U21-V21 -> 48972.001
A22: =A21+1 -> 1 | B22: {=INDEX('Monthly Base'!$B$5:$B$67,A22+1)} -> BUILD | C22: {=INDEX('Monthly Base'!$C$5:$C$67,A22+1)} -> 0 | D22: {=INDEX('Monthly Base'!$O$5:$O$67,A22+1)} -> -20018 | E22: {=INDEX('Monthly Base'!$Y$5:$Y$67,A22+1)} -> 0 | F22: =Z21 -> 48972.001 | G22: =W21 -> 240000 | H22: =X21 -> 900000 | I22: =IF(OR(A22<Inputs!$B$15,G22<=0),0,MIN(Financing!$B$10,G22)) -> 0 | J22: =IF(OR(A22<Inputs!$B$15,H22<=0),0,H22*Inputs!$B$13/12) -> 0 | K22: =IF(OR(A22<Inputs!$B$15,H22<=0),0,MIN(Financing!$C$10,H22+J22)) -> 0 | L22: =I22+K22 -> 0 | M22: =S21 -> 20018 | N22: =IF(AND(Inputs!$B$84=1,B22="OPEN",Y21=0),Inputs!$B$85*(1+Inputs!$B$88)^MAX(0,ROUNDUP(C22/12,0)-1),0) -> 0 | O22: =IF(AND(Inputs!$B$84=1,B22="OPEN",Y21=0),Inputs!$B$86*(1+Inputs!$B$88)^MAX(0,ROUNDUP(C22/12,0)-1),0) -> 0 | P22: =(N22+O22)*(1+Inputs!$B$66) -> 0 | Q22: =D22-J22-IF(C22=0,0,Inputs!$B$18)-P22 -> -20018 | R22: =MAX(0,Q22-M22)*Inputs!$B$17 -> 0 | S22: =MAX(0,M22-MAX(0,Q22))+MAX(0,-Q22) -> 40036 | T22: =F22+D22+E22-L22-P22-R22 -> 28954.001 | U22: =IF(AND(Inputs!$B$79=1,B22="OPEN",A22>=Inputs!$B$82,C22>=Inputs!$B$91,MOD(C22-Inputs!$B$91,Inputs!$B$90)=0),MIN(MAX(0,T22-Inputs!$B$80)*Inputs!$B$81,MAX(0,H22+J22-K22)),0) -> 0 | V22: =IF(AND(Inputs!$B$79=1,B22="OPEN",A22>=Inputs!$B$82,C22>=Inputs!$B$91,MOD(C22-Inputs!$B$91,Inputs!$B$90)=0),MIN(MAX(0,MAX(0,T22-Inputs!$B$80)*Inputs!$B$81-U22),MAX(0,G22-I22)),0) -> 0 | W22: =MAX(0,G22-I22-V22) -> 240000 | X22: =MAX(0,H22+J22-K22-U22) -> 900000 | Y22: =W22+X22 -> 1140000 | Z22: =T22-U22-V22 -> 28954.001
A23: =A22+1 -> 2 | B23: {=INDEX('Monthly Base'!$B$5:$B$67,A23+1)} -> BUILD | C23: {=INDEX('Monthly Base'!$C$5:$C$67,A23+1)} -> 0 | D23: {=INDEX('Monthly Base'!$O$5:$O$67,A23+1)} -> -20018 | E23: {=INDEX('Monthly Base'!$Y$5:$Y$67,A23+1)} -> 151933.73 | F23: =Z22 -> 28954.001 | G23: =W22 -> 240000 | H23: =X22 -> 900000 | I23: =IF(OR(A23<Inputs!$B$15,G23<=0),0,MIN(Financing!$B$10,G23)) -> 0 | J23: =IF(OR(A23<Inputs!$B$15,H23<=0),0,H23*Inputs!$B$13/12) -> 0 | K23: =IF(OR(A23<Inputs!$B$15,H23<=0),0,MIN(Financing!$C$10,H23+J23)) -> 0 | L23: =I23+K23 -> 0 | M23: =S22 -> 40036 | N23: =IF(AND(Inputs!$B$84=1,B23="OPEN",Y22=0),Inputs!$B$85*(1+Inputs!$B$88)^MAX(0,ROUNDUP(C23/12,0)-1),0) -> 0 | O23: =IF(AND(Inputs!$B$84=1,B23="OPEN",Y22=0),Inputs!$B$86*(1+Inputs!$B$88)^MAX(0,ROUNDUP(C23/12,0)-1),0) -> 0 | P23: =(N23+O23)*(1+Inputs!$B$66) -> 0 | Q23: =D23-J23-IF(C23=0,0,Inputs!$B$18)-P23 -> -20018 | R23: =MAX(0,Q23-M23)*Inputs!$B$17 -> 0 | S23: =MAX(0,M23-MAX(0,Q23))+MAX(0,-Q23) -> 60054 | T23: =F23+D23+E23-L23-P23-R23 -> 160869.73 | U23: =IF(AND(Inputs!$B$79=1,B23="OPEN",A23>=Inputs!$B$82,C23>=Inputs!$B$91,MOD(C23-Inputs!$B$91,Inputs!$B$90)=0),MIN(MAX(0,T23-Inputs!$B$80)*Inputs!$B$81,MAX(0,H23+J23-K23)),0) -> 0 | V23: =IF(AND(Inputs!$B$79=1,B23="OPEN",A23>=Inputs!$B$82,C23>=Inputs!$B$91,MOD(C23-Inputs!$B$91,Inputs!$B$90)=0),MIN(MAX(0,MAX(0,T23-Inputs!$B$80)*Inputs!$B$81-U23),MAX(0,G23-I23)),0) -> 0 | W23: =MAX(0,G23-I23-V23) -> 240000 | X23: =MAX(0,H23+J23-K23-U23) -> 900000 | Y23: =W23+X23 -> 1140000 | Z23: =T23-U23-V23 -> 160869.73
A24: =A23+1 -> 3 | B24: {=INDEX('Monthly Base'!$B$5:$B$67,A24+1)} -> OPEN | C24: {=INDEX('Monthly Base'!$C$5:$C$67,A24+1)} -> 1 | D24: {=INDEX('Monthly Base'!$O$5:$O$67,A24+1)} -> -13932.153 | E24: {=INDEX('Monthly Base'!$Y$5:$Y$67,A24+1)} -> 0 | F24: =Z23 -> 160869.73 | G24: =W23 -> 240000 | H24: =X23 -> 900000 | I24: =IF(OR(A24<Inputs!$B$15,G24<=0),0,MIN(Financing!$B$10,G24)) -> 0 | J24: =IF(OR(A24<Inputs!$B$15,H24<=0),0,H24*Inputs!$B$13/12) -> 0 | K24: =IF(OR(A24<Inputs!$B$15,H24<=0),0,MIN(Financing!$C$10,H24+J24)) -> 0 | L24: =I24+K24 -> 0 | M24: =S23 -> 60054 | N24: =IF(AND(Inputs!$B$84=1,B24="OPEN",Y23=0),Inputs!$B$85*(1+Inputs!$B$88)^MAX(0,ROUNDUP(C24/12,0)-1),0) -> 0 | O24: =IF(AND(Inputs!$B$84=1,B24="OPEN",Y23=0),Inputs!$B$86*(1+Inputs!$B$88)^MAX(0,ROUNDUP(C24/12,0)-1),0) -> 0 | P24: =(N24+O24)*(1+Inputs!$B$66) -> 0 | Q24: =D24-J24-IF(C24=0,0,Inputs!$B$18)-P24 -> -20745.153 | R24: =MAX(0,Q24-M24)*Inputs!$B$17 -> 0 | S24: =MAX(0,M24-MAX(0,Q24))+MAX(0,-Q24) -> 80799.153 | T24: =F24+D24+E24-L24-P24-R24 -> 146937.58 | U24: =IF(AND(Inputs!$B$79=1,B24="OPEN",A24>=Inputs!$B$82,C24>=Inputs!$B$91,MOD(C24-Inputs!$B$91,Inputs!$B$90)=0),MIN(MAX(0,T24-Inputs!$B$80)*Inputs!$B$81,MAX(0,H24+J24-K24)),0) -> 0 | V24: =IF(AND(Inputs!$B$79=1,B24="OPEN",A24>=Inputs!$B$82,C24>=Inputs!$B$91,MOD(C24-Inputs!$B$91,Inputs!$B$90)=0),MIN(MAX(0,MAX(0,T24-Inputs!$B$80)*Inputs!$B$81-U24),MAX(0,G24-I24)),0) -> 0 | W24: =MAX(0,G24-I24-V24) -> 240000 | X24: =MAX(0,H24+J24-K24-U24) -> 900000 | Y24: =W24+X24 -> 1140000 | Z24: =T24-U24-V24 -> 146937.58
A25: =A24+1 -> 4 | B25: {=INDEX('Monthly Base'!$B$5:$B$67,A25+1)} -> OPEN | C25: {=INDEX('Monthly Base'!$C$5:$C$67,A25+1)} -> 2 | D25: {=INDEX('Monthly Base'!$O$5:$O$67,A25+1)} -> -10377.381 | E25: {=INDEX('Monthly Base'!$Y$5:$Y$67,A25+1)} -> 0 | F25: =Z24 -> 146937.58 | G25: =W24 -> 240000 | H25: =X24 -> 900000 | I25: =IF(OR(A25<Inputs!$B$15,G25<=0),0,MIN(Financing!$B$10,G25)) -> 0 | J25: =IF(OR(A25<Inputs!$B$15,H25<=0),0,H25*Inputs!$B$13/12) -> 0 | K25: =IF(OR(A25<Inputs!$B$15,H25<=0),0,MIN(Financing!$C$10,H25+J25)) -> 0 | L25: =I25+K25 -> 0 | M25: =S24 -> 80799.153 | N25: =IF(AND(Inputs!$B$84=1,B25="OPEN",Y24=0),Inputs!$B$85*(1+Inputs!$B$88)^MAX(0,ROUNDUP(C25/12,0)-1),0) -> 0 | O25: =IF(AND(Inputs!$B$84=1,B25="OPEN",Y24=0),Inputs!$B$86*(1+Inputs!$B$88)^MAX(0,ROUNDUP(C25/12,0)-1),0) -> 0 | P25: =(N25+O25)*(1+Inputs!$B$66) -> 0 | Q25: =D25-J25-IF(C25=0,0,Inputs!$B$18)-P25 -> -17190.381 | R25: =MAX(0,Q25-M25)*Inputs!$B$17 -> 0 | S25: =MAX(0,M25-MAX(0,Q25))+MAX(0,-Q25) -> 97989.534 | T25: =F25+D25+E25-L25-P25-R25 -> 136560.2 | U25: =IF(AND(Inputs!$B$79=1,B25="OPEN",A25>=Inputs!$B$82,C25>=Inputs!$B$91,MOD(C25-Inputs!$B$91,Inputs!$B$90)=0),MIN(MAX(0,T25-Inputs!$B$80)*Inputs!$B$81,MAX(0,H25+J25-K25)),0) -> 0 | V25: =IF(AND(Inputs!$B$79=1,B25="OPEN",A25>=Inputs!$B$82,C25>=Inputs!$B$91,MOD(C25-Inputs!$B$91,Inputs!$B$90)=0),MIN(MAX(0,MAX(0,T25-Inputs!$B$80)*Inputs!$B$81-U25),MAX(0,G25-I25)),0) -> 0 | W25: =MAX(0,G25-I25-V25) -> 240000 | X25: =MAX(0,H25+J25-K25-U25) -> 900000 | Y25: =W25+X25 -> 1140000 | Z25: =T25-U25-V25 -> 136560.2
A26: =A25+1 -> 5 | B26: {=INDEX('Monthly Base'!$B$5:$B$67,A26+1)} -> OPEN | C26: {=INDEX('Monthly Base'!$C$5:$C$67,A26+1)} -> 3 | D26: {=INDEX('Monthly Base'!$O$5:$O$67,A26+1)} -> -6635.5169 | E26: {=INDEX('Monthly Base'!$Y$5:$Y$67,A26+1)} -> 0 | F26: =Z25 -> 136560.2 | G26: =W25 -> 240000 | H26: =X25 -> 900000 | I26: =IF(OR(A26<Inputs!$B$15,G26<=0),0,MIN(Financing!$B$10,G26)) -> 0 | J26: =IF(OR(A26<Inputs!$B$15,H26<=0),0,H26*Inputs!$B$13/12) -> 0 | K26: =IF(OR(A26<Inputs!$B$15,H26<=0),0,MIN(Financing!$C$10,H26+J26)) -> 0 | L26: =I26+K26 -> 0 | M26: =S25 -> 97989.534 | N26: =IF(AND(Inputs!$B$84=1,B26="OPEN",Y25=0),Inputs!$B$85*(1+Inputs!$B$88)^MAX(0,ROUNDUP(C26/12,0)-1),0) -> 0 | O26: =IF(AND(Inputs!$B$84=1,B26="OPEN",Y25=0),Inputs!$B$86*(1+Inputs!$B$88)^MAX(0,ROUNDUP(C26/12,0)-1),0) -> 0 | P26: =(N26+O26)*(1+Inputs!$B$66) -> 0 | Q26: =D26-J26-IF(C26=0,0,Inputs!$B$18)-P26 -> -13448.517 | R26: =MAX(0,Q26-M26)*Inputs!$B$17 -> 0 | S26: =MAX(0,M26-MAX(0,Q26))+MAX(0,-Q26) -> 111438.05 | T26: =F26+D26+E26-L26-P26-R26 -> 129924.68 | U26: =IF(AND(Inputs!$B$79=1,B26="OPEN",A26>=Inputs!$B$82,C26>=Inputs!$B$91,MOD(C26-Inputs!$B$91,Inputs!$B$90)=0),MIN(MAX(0,T26-Inputs!$B$80)*Inputs!$B$81,MAX(0,H26+J26-K26)),0) -> 0 | V26: =IF(AND(Inputs!$B$79=1,B26="OPEN",A26>=Inputs!$B$82,C26>=Inputs!$B$91,MOD(C26-Inputs!$B$91,Inputs!$B$90)=0),MIN(MAX(0,MAX(0,T26-Inputs!$B$80)*Inputs!$B$81-U26),MAX(0,G26-I26)),0) -> 0 | W26: =MAX(0,G26-I26-V26) -> 240000 | X26: =MAX(0,H26+J26-K26-U26) -> 900000 | Y26: =W26+X26 -> 1140000 | Z26: =T26-U26-V26 -> 129924.68
A27: =A26+1 -> 6 | B27: {=INDEX('Monthly Base'!$B$5:$B$67,A27+1)} -> OPEN | C27: {=INDEX('Monthly Base'!$C$5:$C$67,A27+1)} -> 4 | D27: {=INDEX('Monthly Base'!$O$5:$O$67,A27+1)} -> -3080.7458 | E27: {=INDEX('Monthly Base'!$Y$5:$Y$67,A27+1)} -> 0 | F27: =Z26 -> 129924.68 | G27: =W26 -> 240000 | H27: =X26 -> 900000 | I27: =IF(OR(A27<Inputs!$B$15,G27<=0),0,MIN(Financing!$B$10,G27)) -> 0 | J27: =IF(OR(A27<Inputs!$B$15,H27<=0),0,H27*Inputs!$B$13/12) -> 0 | K27: =IF(OR(A27<Inputs!$B$15,H27<=0),0,MIN(Financing!$C$10,H27+J27)) -> 0 | L27: =I27+K27 -> 0 | M27: =S26 -> 111438.05 | N27: =IF(AND(Inputs!$B$84=1,B27="OPEN",Y26=0),Inputs!$B$85*(1+Inputs!$B$88)^MAX(0,ROUNDUP(C27/12,0)-1),0) -> 0 | O27: =IF(AND(Inputs!$B$84=1,B27="OPEN",Y26=0),Inputs!$B$86*(1+Inputs!$B$88)^MAX(0,ROUNDUP(C27/12,0)-1),0) -> 0 | P27: =(N27+O27)*(1+Inputs!$B$66) -> 0 | Q27: =D27-J27-IF(C27=0,0,Inputs!$B$18)-P27 -> -9893.7458 | R27: =MAX(0,Q27-M27)*Inputs!$B$17 -> 0 | S27: =MAX(0,M27-MAX(0,Q27))+MAX(0,-Q27) -> 121331.8 | T27: =F27+D27+E27-L27-P27-R27 -> 126843.93 | U27: =IF(AND(Inputs!$B$79=1,B27="OPEN",A27>=Inputs!$B$82,C27>=Inputs!$B$91,MOD(C27-Inputs!$B$91,Inputs!$B$90)=0),MIN(MAX(0,T27-Inputs!$B$80)*Inputs!$B$81,MAX(0,H27+J27-K27)),0) -> 0 | V27: =IF(AND(Inputs!$B$79=1,B27="OPEN",A27>=Inputs!$B$82,C27>=Inputs!$B$91,MOD(C27-Inputs!$B$91,Inputs!$B$90)=0),MIN(MAX(0,MAX(0,T27-Inputs!$B$80)*Inputs!$B$81-U27),MAX(0,G27-I27)),0) -> 0 | W27: =MAX(0,G27-I27-V27) -> 240000 | X27: =MAX(0,H27+J27-K27-U27) -> 900000 | Y27: =W27+X27 -> 1140000 | Z27: =T27-U27-V27 -> 126843.93
A28: =A27+1 -> 7 | B28: {=INDEX('Monthly Base'!$B$5:$B$67,A28+1)} -> OPEN | C28: {=INDEX('Monthly Base'!$C$5:$C$67,A28+1)} -> 5 | D28: {=INDEX('Monthly Base'!$O$5:$O$67,A28+1)} -> 474.02542 | E28: {=INDEX('Monthly Base'!$Y$5:$Y$67,A28+1)} -> 0 | F28: =Z27 -> 126843.93 | G28: =W27 -> 240000 | H28: =X27 -> 900000 | I28: =IF(OR(A28<Inputs!$B$15,G28<=0),0,MIN(Financing!$B$10,G28)) -> 0 | J28: =IF(OR(A28<Inputs!$B$15,H28<=0),0,H28*Inputs!$B$13/12) -> 0 | K28: =IF(OR(A28<Inputs!$B$15,H28<=0),0,MIN(Financing!$C$10,H28+J28)) -> 0 | L28: =I28+K28 -> 0 | M28: =S27 -> 121331.8 | N28: =IF(AND(Inputs!$B$84=1,B28="OPEN",Y27=0),Inputs!$B$85*(1+Inputs!$B$88)^MAX(0,ROUNDUP(C28/12,0)-1),0) -> 0 | O28: =IF(AND(Inputs!$B$84=1,B28="OPEN",Y27=0),Inputs!$B$86*(1+Inputs!$B$88)^MAX(0,ROUNDUP(C28/12,0)-1),0) -> 0 | P28: =(N28+O28)*(1+Inputs!$B$66) -> 0 | Q28: =D28-J28-IF(C28=0,0,Inputs!$B$18)-P28 -> -6338.9746 | R28: =MAX(0,Q28-M28)*Inputs!$B$17 -> 0 | S28: =MAX(0,M28-MAX(0,Q28))+MAX(0,-Q28) -> 127670.77 | T28: =F28+D28+E28-L28-P28-R28 -> 127317.96 | U28: =IF(AND(Inputs!$B$79=1,B28="OPEN",A28>=Inputs!$B$82,C28>=Inputs!$B$91,MOD(C28-Inputs!$B$91,Inputs!$B$90)=0),MIN(MAX(0,T28-Inputs!$B$80)*Inputs!$B$81,MAX(0,H28+J28-K28)),0) -> 0 | V28: =IF(AND(Inputs!$B$79=1,B28="OPEN",A28>=Inputs!$B$82,C28>=Inputs!$B$91,MOD(C28-Inputs!$B$91,Inputs!$B$90)=0),MIN(MAX(0,MAX(0,T28-Inputs!$B$80)*Inputs!$B$81-U28),MAX(0,G28-I28)),0) -> 0 | W28: =MAX(0,G28-I28-V28) -> 240000 | X28: =MAX(0,H28+J28-K28-U28) -> 900000 | Y28: =W28+X28 -> 1140000 | Z28: =T28-U28-V28 -> 127317.96
A29: =A28+1 -> 8 | B29: {=INDEX('Monthly Base'!$B$5:$B$67,A29+1)} -> OPEN | C29: {=INDEX('Monthly Base'!$C$5:$C$67,A29+1)} -> 6 | D29: {=INDEX('Monthly Base'!$O$5:$O$67,A29+1)} -> 4028.7966 | E29: {=INDEX('Monthly Base'!$Y$5:$Y$67,A29+1)} -> 0 | F29: =Z28 -> 127317.96 | G29: =W28 -> 240000 | H29: =X28 -> 900000 | I29: =IF(OR(A29<Inputs!$B$15,G29<=0),0,MIN(Financing!$B$10,G29)) -> 0 | J29: =IF(OR(A29<Inputs!$B$15,H29<=0),0,H29*Inputs!$B$13/12) -> 0 | K29: =IF(OR(A29<Inputs!$B$15,H29<=0),0,MIN(Financing!$C$10,H29+J29)) -> 0 | L29: =I29+K29 -> 0 | M29: =S28 -> 127670.77 | N29: =IF(AND(Inputs!$B$84=1,B29="OPEN",Y28=0),Inputs!$B$85*(1+Inputs!$B$88)^MAX(0,ROUNDUP(C29/12,0)-1),0) -> 0 | O29: =IF(AND(Inputs!$B$84=1,B29="OPEN",Y28=0),Inputs!$B$86*(1+Inputs!$B$88)^MAX(0,ROUNDUP(C29/12,0)-1),0) -> 0 | P29: =(N29+O29)*(1+Inputs!$B$66) -> 0 | Q29: =D29-J29-IF(C29=0,0,Inputs!$B$18)-P29 -> -2784.2034 | R29: =MAX(0,Q29-M29)*Inputs!$B$17 -> 0 | S29: =MAX(0,M29-MAX(0,Q29))+MAX(0,-Q29) -> 130454.97 | T29: =F29+D29+E29-L29-P29-R29 -> 131346.76 | U29: =IF(AND(Inputs!$B$79=1,B29="OPEN",A29>=Inputs!$B$82,C29>=Inputs!$B$91,MOD(C29-Inputs!$B$91,Inputs!$B$90)=0),MIN(MAX(0,T29-Inputs!$B$80)*Inputs!$B$81,MAX(0,H29+J29-K29)),0) -> 0 | V29: =IF(AND(Inputs!$B$79=1,B29="OPEN",A29>=Inputs!$B$82,C29>=Inputs!$B$91,MOD(C29-Inputs!$B$91,Inputs!$B$90)=0),MIN(MAX(0,MAX(0,T29-Inputs!$B$80)*Inputs!$B$81-U29),MAX(0,G29-I29)),0) -> 0 | W29: =MAX(0,G29-I29-V29) -> 240000 | X29: =MAX(0,H29+J29-K29-U29) -> 900000 | Y29: =W29+X29 -> 1140000 | Z29: =T29-U29-V29 -> 131346.76
A30: =A29+1 -> 9 | B30: {=INDEX('Monthly Base'!$B$5:$B$67,A30+1)} -> OPEN | C30: {=INDEX('Monthly Base'!$C$5:$C$67,A30+1)} -> 7 | D30: {=INDEX('Monthly Base'!$O$5:$O$67,A30+1)} -> 7770.661 | E30: {=INDEX('Monthly Base'!$Y$5:$Y$67,A30+1)} -> 0 | F30: =Z29 -> 131346.76 | G30: =W29 -> 240000 | H30: =X29 -> 900000 | I30: =IF(OR(A30<Inputs!$B$15,G30<=0),0,MIN(Financing!$B$10,G30)) -> 0 | J30: =IF(OR(A30<Inputs!$B$15,H30<=0),0,H30*Inputs!$B$13/12) -> 0 | K30: =IF(OR(A30<Inputs!$B$15,H30<=0),0,MIN(Financing!$C$10,H30+J30)) -> 0 | L30: =I30+K30 -> 0 | M30: =S29 -> 130454.97 | N30: =IF(AND(Inputs!$B$84=1,B30="OPEN",Y29=0),Inputs!$B$85*(1+Inputs!$B$88)^MAX(0,ROUNDUP(C30/12,0)-1),0) -> 0 | O30: =IF(AND(Inputs!$B$84=1,B30="OPEN",Y29=0),Inputs!$B$86*(1+Inputs!$B$88)^MAX(0,ROUNDUP(C30/12,0)-1),0) -> 0 | P30: =(N30+O30)*(1+Inputs!$B$66) -> 0 | Q30: =D30-J30-IF(C30=0,0,Inputs!$B$18)-P30 -> 957.66102 | R30: =MAX(0,Q30-M30)*Inputs!$B$17 -> 0 | S30: =MAX(0,M30-MAX(0,Q30))+MAX(0,-Q30) -> 129497.31 | T30: =F30+D30+E30-L30-P30-R30 -> 139117.42 | U30: =IF(AND(Inputs!$B$79=1,B30="OPEN",A30>=Inputs!$B$82,C30>=Inputs!$B$91,MOD(C30-Inputs!$B$91,Inputs!$B$90)=0),MIN(MAX(0,T30-Inputs!$B$80)*Inputs!$B$81,MAX(0,H30+J30-K30)),0) -> 0 | V30: =IF(AND(Inputs!$B$79=1,B30="OPEN",A30>=Inputs!$B$82,C30>=Inputs!$B$91,MOD(C30-Inputs!$B$91,Inputs!$B$90)=0),MIN(MAX(0,MAX(0,T30-Inputs!$B$80)*Inputs!$B$81-U30),MAX(0,G30-I30)),0) -> 0 | W30: =MAX(0,G30-I30-V30) -> 240000 | X30: =MAX(0,H30+J30-K30-U30) -> 900000 | Y30: =W30+X30 -> 1140000 | Z30: =T30-U30-V30 -> 139117.42
A31: =A30+1 -> 10 | B31: {=INDEX('Monthly Base'!$B$5:$B$67,A31+1)} -> OPEN | C31: {=INDEX('Monthly Base'!$C$5:$C$67,A31+1)} -> 8 | D31: {=INDEX('Monthly Base'!$O$5:$O$67,A31+1)} -> 11325.432 | E31: {=INDEX('Monthly Base'!$Y$5:$Y$67,A31+1)} -> 0 | F31: =Z30 -> 139117.42 | G31: =W30 -> 240000 | H31: =X30 -> 900000 | I31: =IF(OR(A31<Inputs!$B$15,G31<=0),0,MIN(Financing!$B$10,G31)) -> 0 | J31: =IF(OR(A31<Inputs!$B$15,H31<=0),0,H31*Inputs!$B$13/12) -> 0 | K31: =IF(OR(A31<Inputs!$B$15,H31<=0),0,MIN(Financing!$C$10,H31+J31)) -> 0 | L31: =I31+K31 -> 0 | M31: =S30 -> 129497.31 | N31: =IF(AND(Inputs!$B$84=1,B31="OPEN",Y30=0),Inputs!$B$85*(1+Inputs!$B$88)^MAX(0,ROUNDUP(C31/12,0)-1),0) -> 0 | O31: =IF(AND(Inputs!$B$84=1,B31="OPEN",Y30=0),Inputs!$B$86*(1+Inputs!$B$88)^MAX(0,ROUNDUP(C31/12,0)-1),0) -> 0 | P31: =(N31+O31)*(1+Inputs!$B$66) -> 0 | Q31: =D31-J31-IF(C31=0,0,Inputs!$B$18)-P31 -> 4512.4322 | R31: =MAX(0,Q31-M31)*Inputs!$B$17 -> 0 | S31: =MAX(0,M31-MAX(0,Q31))+MAX(0,-Q31) -> 124984.88 | T31: =F31+D31+E31-L31-P31-R31 -> 150442.85 | U31: =IF(AND(Inputs!$B$79=1,B31="OPEN",A31>=Inputs!$B$82,C31>=Inputs!$B$91,MOD(C31-Inputs!$B$91,Inputs!$B$90)=0),MIN(MAX(0,T31-Inputs!$B$80)*Inputs!$B$81,MAX(0,H31+J31-K31)),0) -> 0 | V31: =IF(AND(Inputs!$B$79=1,B31="OPEN",A31>=Inputs!$B$82,C31>=Inputs!$B$91,MOD(C31-Inputs!$B$91,Inputs!$B$90)=0),MIN(MAX(0,MAX(0,T31-Inputs!$B$80)*Inputs!$B$81-U31),MAX(0,G31-I31)),0) -> 0 | W31: =MAX(0,G31-I31-V31) -> 240000 | X31: =MAX(0,H31+J31-K31-U31) -> 900000 | Y31: =W31+X31 -> 1140000 | Z31: =T31-U31-V31 -> 150442.85
A32: =A31+1 -> 11 | B32: {=INDEX('Monthly Base'!$B$5:$B$67,A32+1)} -> OPEN | C32: {=INDEX('Monthly Base'!$C$5:$C$67,A32+1)} -> 9 | D32: {=INDEX('Monthly Base'!$O$5:$O$67,A32+1)} -> 14880.203 | E32: {=INDEX('Monthly Base'!$Y$5:$Y$67,A32+1)} -> 0 | F32: =Z31 -> 150442.85 | G32: =W31 -> 240000 | H32: =X31 -> 900000 | I32: =IF(OR(A32<Inputs!$B$15,G32<=0),0,MIN(Financing!$B$10,G32)) -> 0 | J32: =IF(OR(A32<Inputs!$B$15,H32<=0),0,H32*Inputs!$B$13/12) -> 0 | K32: =IF(OR(A32<Inputs!$B$15,H32<=0),0,MIN(Financing!$C$10,H32+J32)) -> 0 | L32: =I32+K32 -> 0 | M32: =S31 -> 124984.88 | N32: =IF(AND(Inputs!$B$84=1,B32="OPEN",Y31=0),Inputs!$B$85*(1+Inputs!$B$88)^MAX(0,ROUNDUP(C32/12,0)-1),0) -> 0 | O32: =IF(AND(Inputs!$B$84=1,B32="OPEN",Y31=0),Inputs!$B$86*(1+Inputs!$B$88)^MAX(0,ROUNDUP(C32/12,0)-1),0) -> 0 | P32: =(N32+O32)*(1+Inputs!$B$66) -> 0 | Q32: =D32-J32-IF(C32=0,0,Inputs!$B$18)-P32 -> 8067.2034 | R32: =MAX(0,Q32-M32)*Inputs!$B$17 -> 0 | S32: =MAX(0,M32-MAX(0,Q32))+MAX(0,-Q32) -> 116917.68 | T32: =F32+D32+E32-L32-P32-R32 -> 165323.05 | U32: =IF(AND(Inputs!$B$79=1,B32="OPEN",A32>=Inputs!$B$82,C32>=Inputs!$B$91,MOD(C32-Inputs!$B$91,Inputs!$B$90)=0),MIN(MAX(0,T32-Inputs!$B$80)*Inputs!$B$81,MAX(0,H32+J32-K32)),0) -> 0 | V32: =IF(AND(Inputs!$B$79=1,B32="OPEN",A32>=Inputs!$B$82,C32>=Inputs!$B$91,MOD(C32-Inputs!$B$91,Inputs!$B$90)=0),MIN(MAX(0,MAX(0,T32-Inputs!$B$80)*Inputs!$B$81-U32),MAX(0,G32-I32)),0) -> 0 | W32: =MAX(0,G32-I32-V32) -> 240000 | X32: =MAX(0,H32+J32-K32-U32) -> 900000 | Y32: =W32+X32 -> 1140000 | Z32: =T32-U32-V32 -> 165323.05
A33: =A32+1 -> 12 | B33: {=INDEX('Monthly Base'!$B$5:$B$67,A33+1)} -> OPEN | C33: {=INDEX('Monthly Base'!$C$5:$C$67,A33+1)} -> 10 | D33: {=INDEX('Monthly Base'!$O$5:$O$67,A33+1)} -> 18434.975 | E33: {=INDEX('Monthly Base'!$Y$5:$Y$67,A33+1)} -> 0 | F33: =Z32 -> 165323.05 | G33: =W32 -> 240000 | H33: =X32 -> 900000 | I33: =IF(OR(A33<Inputs!$B$15,G33<=0),0,MIN(Financing!$B$10,G33)) -> 4000 | J33: =IF(OR(A33<Inputs!$B$15,H33<=0),0,H33*Inputs!$B$13/12) -> 3562.5 | K33: =IF(OR(A33<Inputs!$B$15,H33<=0),0,MIN(Financing!$C$10,H33+J33)) -> 16881.221 | L33: =I33+K33 -> 20881.221 | M33: =S32 -> 116917.68 | N33: =IF(AND(Inputs!$B$84=1,B33="OPEN",Y32=0),Inputs!$B$85*(1+Inputs!$B$88)^MAX(0,ROUNDUP(C33/12,0)-1),0) -> 0 | O33: =IF(AND(Inputs!$B$84=1,B33="OPEN",Y32=0),Inputs!$B$86*(1+Inputs!$B$88)^MAX(0,ROUNDUP(C33/12,0)-1),0) -> 0 | P33: =(N33+O33)*(1+Inputs!$B$66) -> 0 | Q33: =D33-J33-IF(C33=0,0,Inputs!$B$18)-P33 -> 8059.4746 | R33: =MAX(0,Q33-M33)*Inputs!$B$17 -> 0 | S33: =MAX(0,M33-MAX(0,Q33))+MAX(0,-Q33) -> 108858.2 | T33: =F33+D33+E33-L33-P33-R33 -> 162876.81 | U33: =IF(AND(Inputs!$B$79=1,B33="OPEN",A33>=Inputs!$B$82,C33>=Inputs!$B$91,MOD(C33-Inputs!$B$91,Inputs!$B$90)=0),MIN(MAX(0,T33-Inputs!$B$80)*Inputs!$B$81,MAX(0,H33+J33-K33)),0) -> 0 | V33: =IF(AND(Inputs!$B$79=1,B33="OPEN",A33>=Inputs!$B$82,C33>=Inputs!$B$91,MOD(C33-Inputs!$B$91,Inputs!$B$90)=0),MIN(MAX(0,MAX(0,T33-Inputs!$B$80)*Inputs!$B$81-U33),MAX(0,G33-I33)),0) -> 0 | W33: =MAX(0,G33-I33-V33) -> 236000 | X33: =MAX(0,H33+J33-K33-U33) -> 886681.28 | Y33: =W33+X33 -> 1122681.3 | Z33: =T33-U33-V33 -> 162876.81
... A83: =A82+1 -> 62 | B83: {=INDEX('Monthly Base'!$B$5:$B$67,A83+1)} -> OPEN | C83: {=INDEX('Monthly Base'!$C$5:$C$67,A83+1)} -> 60 | D83: {=INDEX('Monthly Base'!$O$5:$O$67,A83+1)} -> 100568.9 | E83: {=INDEX('Monthly Base'!$Y$5:$Y$67,A83+1)} -> 0 | F83: =Z82 -> 1723385.7 | G83: =W82 -> 0 | H83: =X82 -> 0 | I83: =IF(OR(A83<Inputs!$B$15,G83<=0),0,MIN(Financing!$B$10,G83)) -> 0 | J83: =IF(OR(A83<Inputs!$B$15,H83<=0),0,H83*Inputs!$B$13/12) -> 0 | K83: =IF(OR(A83<Inputs!$B$15,H83<=0),0,MIN(Financing!$C$10,H83+J83)) -> 0 | L83: =I83+K83 -> 0 | M83: =S82 -> 0 | N83: =IF(AND(Inputs!$B$84=1,B83="OPEN",Y82=0),Inputs!$B$85*(1+Inputs!$B$88)^MAX(0,ROUNDUP(C83/12,0)-1),0) -> 0 | O83: =IF(AND(Inputs!$B$84=1,B83="OPEN",Y82=0),Inputs!$B$86*(1+Inputs!$B$88)^MAX(0,ROUNDUP(C83/12,0)-1),0) -> 0 | P83: =(N83+O83)*(1+Inputs!$B$66) -> 0 | Q83: =D83-J83-IF(C83=0,0,Inputs!$B$18)-P83 -> 93755.898 | R83: =MAX(0,Q83-M83)*Inputs!$B$17 -> 21563.857 | S83: =MAX(0,M83-MAX(0,Q83))+MAX(0,-Q83) -> 0 | T83: =F83+D83+E83-L83-P83-R83 -> 1802390.8 | U83: =IF(AND(Inputs!$B$79=1,B83="OPEN",A83>=Inputs!$B$82,C83>=Inputs!$B$91,MOD(C83-Inputs!$B$91,Inputs!$B$90)=0),MIN(MAX(0,T83-Inputs!$B$80)*Inputs!$B$81,MAX(0,H83+J83-K83)),0) -> 0 | V83: =IF(AND(Inputs!$B$79=1,B83="OPEN",A83>=Inputs!$B$82,C83>=Inputs!$B$91,MOD(C83-Inputs!$B$91,Inputs!$B$90)=0),MIN(MAX(0,MAX(0,T83-Inputs!$B$80)*Inputs!$B$81-U83),MAX(0,G83-I83)),0) -> 0 | W83: =MAX(0,G83-I83-V83) -> 0 | X83: =MAX(0,H83+J83-K83-U83) -> 0 | Y83: =W83+X83 -> 0 | Z83: =T83-U83-V83 -> 1802390.8

Sheet Salary Scenarios
A1: Owner Salary & Debt-Payoff Scenarios
A2: Both partners are 50/50, both work in the business, and all modeled owner salaries are equal per partner. Hodaya remains staff. No automatic distributions are modeled while debt remains.
A4: Assumption / Output | B4: A — Debt-Max | C4: B — Balanced | D4: C — Earlier Owner Pay | E4: D — Early Balanced
A5: Pre-debt salary start operating month | B5: 0 | C5: 13 | D5: 7 | E5: 7
A6: Pre-debt gross salary / partner / month | B6: 0 | C6: 5000 | D6: 10000 | E6: 5000
A7: Post-debt gross salary / partner / month | B7: 10000 | C7: 10000 | D7: 10000 | E7: 10000
A8: Debt-sweep cash reserve target | B8: =Inputs!$B$80 -> 150000 | C8: =Inputs!$B$80 -> 150000 | D8: =Inputs!$B$80 -> 150000 | E8: =Inputs!$B$80 -> 150000
A9: Debt sweep frequency (operating months) | B9: =Inputs!$B$90 -> 6 | C9: =Inputs!$B$90 -> 6 | D9: =Inputs!$B$90 -> 6 | E9: =Inputs!$B$90 -> 6
A10: First debt sweep operating month | B10: =Inputs!$B$91 -> 12 | C10: =Inputs!$B$91 -> 12 | D10: =Inputs!$B$91 -> 12 | E10: =Inputs!$B$91 -> 12
A11: Employer load on owner payroll | B11: =Inputs!$B$66 -> 0.2 | C11: =Inputs!$B$66 -> 0.2 | D11: =Inputs!$B$66 -> 0.2 | E11: =Inputs!$B$66 -> 0.2
A13: Debt-free operating month | B13: {=IFERROR(INDEX(C31:C93,MATCH(0,Y31:Y93,0)),"Beyond model")} -> 42 | C13: {=IFERROR(INDEX(C101:C163,MATCH(0,Y101:Y163,0)),"Beyond model")} -> 42 | D13: {=IFERROR(INDEX(C171:C233,MATCH(0,Y171:Y233,0)),"Beyond model")} -> 54 | E13: {=IFERROR(INDEX(C241:C303,MATCH(0,Y241:Y303,0)),"Beyond model")} -> 47
A14: Prime loan debt-free operating month | B14: {=IFERROR(INDEX(C31:C93,MATCH(0,X31:X93,0)),"Beyond model")} -> 36 | C14: {=IFERROR(INDEX(C101:C163,MATCH(0,X101:X163,0)),"Beyond model")} -> 42 | D14: {=IFERROR(INDEX(C171:C233,MATCH(0,X171:X233,0)),"Beyond model")} -> 48 | E14: {=IFERROR(INDEX(C241:C303,MATCH(0,X241:X303,0)),"Beyond model")} -> 42
A15: First owner salary operating month | B15: =IFERROR(__xludf.DUMMYFUNCTION("IFERROR(MIN(FILTER(C31:C93,N31:N93>0,C31:C93>0)),""None"")"),43.0) -> 43 | C15: =IFERROR(__xludf.DUMMYFUNCTION("IFERROR(MIN(FILTER(C101:C163,N101:N163>0,C101:C163>0)),""None"")"),13.0) -> 13 | D15: =IFERROR(__xludf.DUMMYFUNCTION("IFERROR(MIN(FILTER(C171:C233,N171:N233>0,C171:C233>0)),""None"")"),7.0) -> 7 | E15: =IFERROR(__xludf.DUMMYFUNCTION("IFERROR(MIN(FILTER(C241:C303,N241:N303>0,C241:C303>0)),""None"")"),7.0) -> 7
A16: Total owner gross salaries paid — 5 years | B16: =SUM(N31:O93) -> 360000 | C16: =SUM(N101:O163) -> 660000 | D16: =SUM(N171:O233) -> 1080000 | E16: =SUM(N241:O303) -> 670000
A17: Company owner payroll cost — 5 years | B17: =SUM(P31:P93) -> 432000 | C17: =SUM(P101:P163) -> 792000 | D17: =SUM(P171:P233) -> 1296000 | E17: =SUM(P241:P303) -> 804000
A18: Interest saved vs scheduled amortization | B18: =SUM(Financing!$G$17:$G$79)-SUM(J31:J93) -> 48787.14 | C18: =SUM(Financing!$G$17:$G$79)-SUM(J101:J163) -> 37952.115 | D18: =SUM(Financing!$G$17:$G$79)-SUM(J171:J233) -> 17002.607 | E18: =SUM(Financing!$G$17:$G$79)-SUM(J241:J303) -> 32748.362
A19: Total extra lump-sum debt prepayments | B19: =SUM(U31:V93) -> 613329.31 | C19: =SUM(U101:V163) -> 522877.01 | D19: =SUM(U171:V233) -> 394539.19 | E19: =SUM(U241:V303) -> 509480.12
A20: Year 5 company cash — no distributions | B20: =Z93 -> 1469750.8 | C20: =Z163 -> 1184207.8 | D20: =Z233 -> 779996.67 | E20: =Z303 -> 1170960.9
A21: Year 5 cash available for distribution | B21: =IF(Y93=0,MAX(0,Z93-B8),0) -> 1319750.8 | C21: =IF(Y163=0,MAX(0,Z163-C8),0) -> 1034207.8 | D21: =IF(Y233=0,MAX(0,Z233-D8),0) -> 629996.67 | E21: =IF(Y303=0,MAX(0,Z303-E8),0) -> 1020960.9
A22: 50% per partner if fully distributed | B22: =B21*0.5 -> 659875.38 | C22: =C21*0.5 -> 517103.89 | D22: =D21*0.5 -> 314998.33 | E22: =E21*0.5 -> 510480.45
A23: Months debt eliminated early | B23: {=IFERROR(MAX(0,Inputs!$B$15+Inputs!$B$16-1-INDEX(A31:A93,MATCH(0,Y31:Y93,0))),0)} -> 27 | C23: {=IFERROR(MAX(0,Inputs!$B$15+Inputs!$B$16-1-INDEX(A101:A163,MATCH(0,Y101:Y163,0))),0)} -> 27 | D23: {=IFERROR(MAX(0,Inputs!$B$15+Inputs!$B$16-1-INDEX(A171:A233,MATCH(0,Y171:Y233,0))),0)} -> 15 | E23: {=IFERROR(MAX(0,Inputs!$B$15+Inputs!$B$16-1-INDEX(A241:A303,MATCH(0,Y241:Y303,0))),0)} -> 22
A24: Year 5 ending debt balance | B24: =Y93 -> 0 | C24: =Y163 -> 0 | D24: =Y233 -> 0 | E24: =Y303 -> 0
A25: Minimum cash balance — full timeline | B25: =MIN(Z31:Z93) -> 28954.001 | C25: =MIN(Z101:Z163) -> 28954.001 | D25: =MIN(Z171:Z233) -> -43607.936 | E25: =MIN(Z241:Z303) -> 28954.001
A26: Scenario definitions | B26: Debt-Max: no salary before debt-free. | C26: Balanced: ₪5k gross each from op month 13; ₪10k each after debt-free. | D26: Earlier Owner Pay: ₪10k gross each from op month 7 and thereafter. | E26: Early Balanced: ₪5k gross each from op month 7; ₪10k each after debt-free.
A27: Minimum operating cash after reopening | B27: =IFERROR(__xludf.DUMMYFUNCTION("MIN(FILTER(Z31:Z93,C31:C93>0))"),126843.9333898304) -> 126843.93 | C27: =IFERROR(__xludf.DUMMYFUNCTION("MIN(FILTER(Z101:Z163,C101:C163>0))"),126843.9333898304) -> 126843.93 | D27: =IFERROR(__xludf.DUMMYFUNCTION("MIN(FILTER(Z171:Z233,C171:C233>0))"),-43607.93588131549) -> -43607.936 | E27: =IFERROR(__xludf.DUMMYFUNCTION("MIN(FILTER(Z241:Z303,C241:C303>0))"),89793.0663297601) -> 89793.066
A28: Current Dashboard / Owner Pay tab remains Scenario A until you choose another policy. The scenario assumptions above are editable.
A30: Timeline Mo | B30: Phase | C30: Operating Mo | D30: EBITDA | E30: Build VAT Refund | F30: Opening Cash | G30: Loan A Opening | H30: Loan B Opening | I30: Loan A Scheduled | J30: Loan B Interest | K30: Loan B Scheduled | L30: Scheduled Debt | M30: Tax Loss CF Begin | N30: Partner 1 Gross | O30: Partner 2 Gross | P30: Owner Payroll Cost | Q30: Taxable Before Loss | R30: Corporate Tax | S30: Tax Loss CF End | T30: Cash Before Extra Debt | U30: Extra to Loan B | V30: Extra to Loan A | W30: Loan A Closing | X30: Loan B Closing | Y30: Total Debt | Z30: Ending Cash
A31: 0 | B31: {=INDEX('Monthly Base'!$B$5:$B$67,A31+1)} -> BUILD | C31: {=INDEX('Monthly Base'!$C$5:$C$67,A31+1)} -> 0 | D31: {=INDEX('Monthly Base'!$O$5:$O$67,A31+1)} -> -20018 | E31: {=INDEX('Monthly Base'!$Y$5:$Y$67,A31+1)} -> 0 | F31: ='Startup & Funding'!$B$19 -> 68990.001 | G31: =Inputs!$B$9 -> 240000 | H31: =Inputs!$B$10 -> 900000 | I31: =IF(OR(A31<Inputs!$B$15,G31<=0),0,MIN(Financing!$B$10,G31)) -> 0 | J31: =IF(OR(A31<Inputs!$B$15,H31<=0),0,H31*Inputs!$B$13/12) -> 0 | K31: =IF(OR(A31<Inputs!$B$15,H31<=0),0,MIN(Financing!$C$10,H31+J31)) -> 0 | L31: =I31+K31 -> 0 | M31: 0 | N31: 0 | O31: 0 | P31: =(N31+O31)*(1+$B$11) -> 0 | Q31: =D31-J31-IF(C31=0,0,Inputs!$B$18)-P31 -> -20018 | R31: =MAX(0,Q31-M31)*Inputs!$B$17 -> 0 | S31: =MAX(0,M31-MAX(0,Q31))+MAX(0,-Q31) -> 20018 | T31: =F31+D31+E31-L31-P31-R31 -> 48972.001 | U31: =IF(AND(Inputs!$B$79=1,B31="OPEN",A31>=Inputs!$B$82,C31>=$B$10,MOD(C31-$B$10,$B$9)=0),MIN(MAX(0,T31-$B$8)*Inputs!$B$81,MAX(0,H31+J31-K31)),0) -> 0 | V31: =IF(AND(Inputs!$B$79=1,B31="OPEN",A31>=Inputs!$B$82,C31>=$B$10,MOD(C31-$B$10,$B$9)=0),MIN(MAX(0,MAX(0,T31-$B$8)*Inputs!$B$81-U31),MAX(0,G31-I31)),0) -> 0 | W31: =MAX(0,G31-I31-V31) -> 240000 | X31: =MAX(0,H31+J31-K31-U31) -> 900000 | Y31: =W31+X31 -> 1140000 | Z31: =T31-U31-V31 -> 48972.001
A32: =A31+1 -> 1 | B32: {=INDEX('Monthly Base'!$B$5:$B$67,A32+1)} -> BUILD | C32: {=INDEX('Monthly Base'!$C$5:$C$67,A32+1)} -> 0 | D32: {=INDEX('Monthly Base'!$O$5:$O$67,A32+1)} -> -20018 | E32: {=INDEX('Monthly Base'!$Y$5:$Y$67,A32+1)} -> 0 | F32: =Z31 -> 48972.001 | G32: =W31 -> 240000 | H32: =X31 -> 900000 | I32: =IF(OR(A32<Inputs!$B$15,G32<=0),0,MIN(Financing!$B$10,G32)) -> 0 | J32: =IF(OR(A32<Inputs!$B$15,H32<=0),0,H32*Inputs!$B$13/12) -> 0 | K32: =IF(OR(A32<Inputs!$B$15,H32<=0),0,MIN(Financing!$C$10,H32+J32)) -> 0 | L32: =I32+K32 -> 0 | M32: =S31 -> 20018 | N32: =IF(B32="OPEN",IF(Y31=0,$B$7,IF(AND(C32>0,C32>=$B$5,$B$6>0),$B$6,0)),0) -> 0 | O32: =IF(B32="OPEN",IF(Y31=0,$B$7,IF(AND(C32>0,C32>=$B$5,$B$6>0),$B$6,0)),0) -> 0 | P32: =(N32+O32)*(1+$B$11) -> 0 | Q32: =D32-J32-IF(C32=0,0,Inputs!$B$18)-P32 -> -20018 | R32: =MAX(0,Q32-M32)*Inputs!$B$17 -> 0 | S32: =MAX(0,M32-MAX(0,Q32))+MAX(0,-Q32) -> 40036 | T32: =F32+D32+E32-L32-P32-R32 -> 28954.001 | U32: =IF(AND(Inputs!$B$79=1,B32="OPEN",A32>=Inputs!$B$82,C32>=$B$10,MOD(C32-$B$10,$B$9)=0),MIN(MAX(0,T32-$B$8)*Inputs!$B$81,MAX(0,H32+J32-K32)),0) -> 0 | V32: =IF(AND(Inputs!$B$79=1,B32="OPEN",A32>=Inputs!$B$82,C32>=$B$10,MOD(C32-$B$10,$B$9)=0),MIN(MAX(0,MAX(0,T32-$B$8)*Inputs!$B$81-U32),MAX(0,G32-I32)),0) -> 0 | W32: =MAX(0,G32-I32-V32) -> 240000 | X32: =MAX(0,H32+J32-K32-U32) -> 900000 | Y32: =W32+X32 -> 1140000 | Z32: =T32-U32-V32 -> 28954.001
A33: =A32+1 -> 2 | B33: {=INDEX('Monthly Base'!$B$5:$B$67,A33+1)} -> BUILD | C33: {=INDEX('Monthly Base'!$C$5:$C$67,A33+1)} -> 0 | D33: {=INDEX('Monthly Base'!$O$5:$O$67,A33+1)} -> -20018 | E33: {=INDEX('Monthly Base'!$Y$5:$Y$67,A33+1)} -> 151933.73 | F33: =Z32 -> 28954.001 | G33: =W32 -> 240000 | H33: =X32 -> 900000 | I33: =IF(OR(A33<Inputs!$B$15,G33<=0),0,MIN(Financing!$B$10,G33)) -> 0 | J33: =IF(OR(A33<Inputs!$B$15,H33<=0),0,H33*Inputs!$B$13/12) -> 0 | K33: =IF(OR(A33<Inputs!$B$15,H33<=0),0,MIN(Financing!$C$10,H33+J33)) -> 0 | L33: =I33+K33 -> 0 | M33: =S32 -> 40036 | N33: =IF(B33="OPEN",IF(Y32=0,$B$7,IF(AND(C33>0,C33>=$B$5,$B$6>0),$B$6,0)),0) -> 0 | O33: =IF(B33="OPEN",IF(Y32=0,$B$7,IF(AND(C33>0,C33>=$B$5,$B$6>0),$B$6,0)),0) -> 0 | P33: =(N33+O33)*(1+$B$11) -> 0 | Q33: =D33-J33-IF(C33=0,0,Inputs!$B$18)-P33 -> -20018 | R33: =MAX(0,Q33-M33)*Inputs!$B$17 -> 0 | S33: =MAX(0,M33-MAX(0,Q33))+MAX(0,-Q33) -> 60054 | T33: =F33+D33+E33-L33-P33-R33 -> 160869.73 | U33: =IF(AND(Inputs!$B$79=1,B33="OPEN",A33>=Inputs!$B$82,C33>=$B$10,MOD(C33-$B$10,$B$9)=0),MIN(MAX(0,T33-$B$8)*Inputs!$B$81,MAX(0,H33+J33-K33)),0) -> 0 | V33: =IF(AND(Inputs!$B$79=1,B33="OPEN",A33>=Inputs!$B$82,C33>=$B$10,MOD(C33-$B$10,$B$9)=0),MIN(MAX(0,MAX(0,T33-$B$8)*Inputs!$B$81-U33),MAX(0,G33-I33)),0) -> 0 | W33: =MAX(0,G33-I33-V33) -> 240000 | X33: =MAX(0,H33+J33-K33-U33) -> 900000 | Y33: =W33+X33 -> 1140000 | Z33: =T33-U33-V33 -> 160869.73
A34: =A33+1 -> 3 | B34: {=INDEX('Monthly Base'!$B$5:$B$67,A34+1)} -> OPEN | C34: {=INDEX('Monthly Base'!$C$5:$C$67,A34+1)} -> 1 | D34: {=INDEX('Monthly Base'!$O$5:$O$67,A34+1)} -> -13932.153 | E34: {=INDEX('Monthly Base'!$Y$5:$Y$67,A34+1)} -> 0 | F34: =Z33 -> 160869.73 | G34: =W33 -> 240000 | H34: =X33 -> 900000 | I34: =IF(OR(A34<Inputs!$B$15,G34<=0),0,MIN(Financing!$B$10,G34)) -> 0 | J34: =IF(OR(A34<Inputs!$B$15,H34<=0),0,H34*Inputs!$B$13/12) -> 0 | K34: =IF(OR(A34<Inputs!$B$15,H34<=0),0,MIN(Financing!$C$10,H34+J34)) -> 0 | L34: =I34+K34 -> 0 | M34: =S33 -> 60054 | N34: =IF(B34="OPEN",IF(Y33=0,$B$7,IF(AND(C34>0,C34>=$B$5,$B$6>0),$B$6,0)),0) -> 0 | O34: =IF(B34="OPEN",IF(Y33=0,$B$7,IF(AND(C34>0,C34>=$B$5,$B$6>0),$B$6,0)),0) -> 0 | P34: =(N34+O34)*(1+$B$11) -> 0 | Q34: =D34-J34-IF(C34=0,0,Inputs!$B$18)-P34 -> -20745.153 | R34: =MAX(0,Q34-M34)*Inputs!$B$17 -> 0 | S34: =MAX(0,M34-MAX(0,Q34))+MAX(0,-Q34) -> 80799.153 | T34: =F34+D34+E34-L34-P34-R34 -> 146937.58 | U34: =IF(AND(Inputs!$B$79=1,B34="OPEN",A34>=Inputs!$B$82,C34>=$B$10,MOD(C34-$B$10,$B$9)=0),MIN(MAX(0,T34-$B$8)*Inputs!$B$81,MAX(0,H34+J34-K34)),0) -> 0 | V34: =IF(AND(Inputs!$B$79=1,B34="OPEN",A34>=Inputs!$B$82,C34>=$B$10,MOD(C34-$B$10,$B$9)=0),MIN(MAX(0,MAX(0,T34-$B$8)*Inputs!$B$81-U34),MAX(0,G34-I34)),0) -> 0 | W34: =MAX(0,G34-I34-V34) -> 240000 | X34: =MAX(0,H34+J34-K34-U34) -> 900000 | Y34: =W34+X34 -> 1140000 | Z34: =T34-U34-V34 -> 146937.58
A35: =A34+1 -> 4 | B35: {=INDEX('Monthly Base'!$B$5:$B$67,A35+1)} -> OPEN | C35: {=INDEX('Monthly Base'!$C$5:$C$67,A35+1)} -> 2 | D35: {=INDEX('Monthly Base'!$O$5:$O$67,A35+1)} -> -10377.381 | E35: {=INDEX('Monthly Base'!$Y$5:$Y$67,A35+1)} -> 0 | F35: =Z34 -> 146937.58 | G35: =W34 -> 240000 | H35: =X34 -> 900000 | I35: =IF(OR(A35<Inputs!$B$15,G35<=0),0,MIN(Financing!$B$10,G35)) -> 0 | J35: =IF(OR(A35<Inputs!$B$15,H35<=0),0,H35*Inputs!$B$13/12) -> 0 | K35: =IF(OR(A35<Inputs!$B$15,H35<=0),0,MIN(Financing!$C$10,H35+J35)) -> 0 | L35: =I35+K35 -> 0 | M35: =S34 -> 80799.153 | N35: =IF(B35="OPEN",IF(Y34=0,$B$7,IF(AND(C35>0,C35>=$B$5,$B$6>0),$B$6,0)),0) -> 0 | O35: =IF(B35="OPEN",IF(Y34=0,$B$7,IF(AND(C35>0,C35>=$B$5,$B$6>0),$B$6,0)),0) -> 0 | P35: =(N35+O35)*(1+$B$11) -> 0 | Q35: =D35-J35-IF(C35=0,0,Inputs!$B$18)-P35 -> -17190.381 | R35: =MAX(0,Q35-M35)*Inputs!$B$17 -> 0 | S35: =MAX(0,M35-MAX(0,Q35))+MAX(0,-Q35) -> 97989.534 | T35: =F35+D35+E35-L35-P35-R35 -> 136560.2 | U35: =IF(AND(Inputs!$B$79=1,B35="OPEN",A35>=Inputs!$B$82,C35>=$B$10,MOD(C35-$B$10,$B$9)=0),MIN(MAX(0,T35-$B$8)*Inputs!$B$81,MAX(0,H35+J35-K35)),0) -> 0 | V35: =IF(AND(Inputs!$B$79=1,B35="OPEN",A35>=Inputs!$B$82,C35>=$B$10,MOD(C35-$B$10,$B$9)=0),MIN(MAX(0,MAX(0,T35-$B$8)*Inputs!$B$81-U35),MAX(0,G35-I35)),0) -> 0 | W35: =MAX(0,G35-I35-V35) -> 240000 | X35: =MAX(0,H35+J35-K35-U35) -> 900000 | Y35: =W35+X35 -> 1140000 | Z35: =T35-U35-V35 -> 136560.2
A36: =A35+1 -> 5 | B36: {=INDEX('Monthly Base'!$B$5:$B$67,A36+1)} -> OPEN | C36: {=INDEX('Monthly Base'!$C$5:$C$67,A36+1)} -> 3 | D36: {=INDEX('Monthly Base'!$O$5:$O$67,A36+1)} -> -6635.5169 | E36: {=INDEX('Monthly Base'!$Y$5:$Y$67,A36+1)} -> 0 | F36: =Z35 -> 136560.2 | G36: =W35 -> 240000 | H36: =X35 -> 900000 | I36: =IF(OR(A36<Inputs!$B$15,G36<=0),0,MIN(Financing!$B$10,G36)) -> 0 | J36: =IF(OR(A36<Inputs!$B$15,H36<=0),0,H36*Inputs!$B$13/12) -> 0 | K36: =IF(OR(A36<Inputs!$B$15,H36<=0),0,MIN(Financing!$C$10,H36+J36)) -> 0 | L36: =I36+K36 -> 0 | M36: =S35 -> 97989.534 | N36: =IF(B36="OPEN",IF(Y35=0,$B$7,IF(AND(C36>0,C36>=$B$5,$B$6>0),$B$6,0)),0) -> 0 | O36: =IF(B36="OPEN",IF(Y35=0,$B$7,IF(AND(C36>0,C36>=$B$5,$B$6>0),$B$6,0)),0) -> 0 | P36: =(N36+O36)*(1+$B$11) -> 0 | Q36: =D36-J36-IF(C36=0,0,Inputs!$B$18)-P36 -> -13448.517 | R36: =MAX(0,Q36-M36)*Inputs!$B$17 -> 0 | S36: =MAX(0,M36-MAX(0,Q36))+MAX(0,-Q36) -> 111438.05 | T36: =F36+D36+E36-L36-P36-R36 -> 129924.68 | U36: =IF(AND(Inputs!$B$79=1,B36="OPEN",A36>=Inputs!$B$82,C36>=$B$10,MOD(C36-$B$10,$B$9)=0),MIN(MAX(0,T36-$B$8)*Inputs!$B$81,MAX(0,H36+J36-K36)),0) -> 0 | V36: =IF(AND(Inputs!$B$79=1,B36="OPEN",A36>=Inputs!$B$82,C36>=$B$10,MOD(C36-$B$10,$B$9)=0),MIN(MAX(0,MAX(0,T36-$B$8)*Inputs!$B$81-U36),MAX(0,G36-I36)),0) -> 0 | W36: =MAX(0,G36-I36-V36) -> 240000 | X36: =MAX(0,H36+J36-K36-U36) -> 900000 | Y36: =W36+X36 -> 1140000 | Z36: =T36-U36-V36 -> 129924.68
A37: =A36+1 -> 6 | B37: {=INDEX('Monthly Base'!$B$5:$B$67,A37+1)} -> OPEN | C37: {=INDEX('Monthly Base'!$C$5:$C$67,A37+1)} -> 4 | D37: {=INDEX('Monthly Base'!$O$5:$O$67,A37+1)} -> -3080.7458 | E37: {=INDEX('Monthly Base'!$Y$5:$Y$67,A37+1)} -> 0 | F37: =Z36 -> 129924.68 | G37: =W36 -> 240000 | H37: =X36 -> 900000 | I37: =IF(OR(A37<Inputs!$B$15,G37<=0),0,MIN(Financing!$B$10,G37)) -> 0 | J37: =IF(OR(A37<Inputs!$B$15,H37<=0),0,H37*Inputs!$B$13/12) -> 0 | K37: =IF(OR(A37<Inputs!$B$15,H37<=0),0,MIN(Financing!$C$10,H37+J37)) -> 0 | L37: =I37+K37 -> 0 | M37: =S36 -> 111438.05 | N37: =IF(B37="OPEN",IF(Y36=0,$B$7,IF(AND(C37>0,C37>=$B$5,$B$6>0),$B$6,0)),0) -> 0 | O37: =IF(B37="OPEN",IF(Y36=0,$B$7,IF(AND(C37>0,C37>=$B$5,$B$6>0),$B$6,0)),0) -> 0 | P37: =(N37+O37)*(1+$B$11) -> 0 | Q37: =D37-J37-IF(C37=0,0,Inputs!$B$18)-P37 -> -9893.7458 | R37: =MAX(0,Q37-M37)*Inputs!$B$17 -> 0 | S37: =MAX(0,M37-MAX(0,Q37))+MAX(0,-Q37) -> 121331.8 | T37: =F37+D37+E37-L37-P37-R37 -> 126843.93 | U37: =IF(AND(Inputs!$B$79=1,B37="OPEN",A37>=Inputs!$B$82,C37>=$B$10,MOD(C37-$B$10,$B$9)=0),MIN(MAX(0,T37-$B$8)*Inputs!$B$81,MAX(0,H37+J37-K37)),0) -> 0 | V37: =IF(AND(Inputs!$B$79=1,B37="OPEN",A37>=Inputs!$B$82,C37>=$B$10,MOD(C37-$B$10,$B$9)=0),MIN(MAX(0,MAX(0,T37-$B$8)*Inputs!$B$81-U37),MAX(0,G37-I37)),0) -> 0 | W37: =MAX(0,G37-I37-V37) -> 240000 | X37: =MAX(0,H37+J37-K37-U37) -> 900000 | Y37: =W37+X37 -> 1140000 | Z37: =T37-U37-V37 -> 126843.93
A38: =A37+1 -> 7 | B38: {=INDEX('Monthly Base'!$B$5:$B$67,A38+1)} -> OPEN | C38: {=INDEX('Monthly Base'!$C$5:$C$67,A38+1)} -> 5 | D38: {=INDEX('Monthly Base'!$O$5:$O$67,A38+1)} -> 474.02542 | E38: {=INDEX('Monthly Base'!$Y$5:$Y$67,A38+1)} -> 0 | F38: =Z37 -> 126843.93 | G38: =W37 -> 240000 | H38: =X37 -> 900000 | I38: =IF(OR(A38<Inputs!$B$15,G38<=0),0,MIN(Financing!$B$10,G38)) -> 0 | J38: =IF(OR(A38<Inputs!$B$15,H38<=0),0,H38*Inputs!$B$13/12) -> 0 | K38: =IF(OR(A38<Inputs!$B$15,H38<=0),0,MIN(Financing!$C$10,H38+J38)) -> 0 | L38: =I38+K38 -> 0 | M38: =S37 -> 121331.8 | N38: =IF(B38="OPEN",IF(Y37=0,$B$7,IF(AND(C38>0,C38>=$B$5,$B$6>0),$B$6,0)),0) -> 0 | O38: =IF(B38="OPEN",IF(Y37=0,$B$7,IF(AND(C38>0,C38>=$B$5,$B$6>0),$B$6,0)),0) -> 0 | P38: =(N38+O38)*(1+$B$11) -> 0 | Q38: =D38-J38-IF(C38=0,0,Inputs!$B$18)-P38 -> -6338.9746 | R38: =MAX(0,Q38-M38)*Inputs!$B$17 -> 0 | S38: =MAX(0,M38-MAX(0,Q38))+MAX(0,-Q38) -> 127670.77 | T38: =F38+D38+E38-L38-P38-R38 -> 127317.96 | U38: =IF(AND(Inputs!$B$79=1,B38="OPEN",A38>=Inputs!$B$82,C38>=$B$10,MOD(C38-$B$10,$B$9)=0),MIN(MAX(0,T38-$B$8)*Inputs!$B$81,MAX(0,H38+J38-K38)),0) -> 0 | V38: =IF(AND(Inputs!$B$79=1,B38="OPEN",A38>=Inputs!$B$82,C38>=$B$10,MOD(C38-$B$10,$B$9)=0),MIN(MAX(0,MAX(0,T38-$B$8)*Inputs!$B$81-U38),MAX(0,G38-I38)),0) -> 0 | W38: =MAX(0,G38-I38-V38) -> 240000 | X38: =MAX(0,H38+J38-K38-U38) -> 900000 | Y38: =W38+X38 -> 1140000 | Z38: =T38-U38-V38 -> 127317.96
A39: =A38+1 -> 8 | B39: {=INDEX('Monthly Base'!$B$5:$B$67,A39+1)} -> OPEN | C39: {=INDEX('Monthly Base'!$C$5:$C$67,A39+1)} -> 6 | D39: {=INDEX('Monthly Base'!$O$5:$O$67,A39+1)} -> 4028.7966 | E39: {=INDEX('Monthly Base'!$Y$5:$Y$67,A39+1)} -> 0 | F39: =Z38 -> 127317.96 | G39: =W38 -> 240000 | H39: =X38 -> 900000 | I39: =IF(OR(A39<Inputs!$B$15,G39<=0),0,MIN(Financing!$B$10,G39)) -> 0 | J39: =IF(OR(A39<Inputs!$B$15,H39<=0),0,H39*Inputs!$B$13/12) -> 0 | K39: =IF(OR(A39<Inputs!$B$15,H39<=0),0,MIN(Financing!$C$10,H39+J39)) -> 0 | L39: =I39+K39 -> 0 | M39: =S38 -> 127670.77 | N39: =IF(B39="OPEN",IF(Y38=0,$B$7,IF(AND(C39>0,C39>=$B$5,$B$6>0),$B$6,0)),0) -> 0 | O39: =IF(B39="OPEN",IF(Y38=0,$B$7,IF(AND(C39>0,C39>=$B$5,$B$6>0),$B$6,0)),0) -> 0 | P39: =(N39+O39)*(1+$B$11) -> 0 | Q39: =D39-J39-IF(C39=0,0,Inputs!$B$18)-P39 -> -2784.2034 | R39: =MAX(0,Q39-M39)*Inputs!$B$17 -> 0 | S39: =MAX(0,M39-MAX(0,Q39))+MAX(0,-Q39) -> 130454.97 | T39: =F39+D39+E39-L39-P39-R39 -> 131346.76 | U39: =IF(AND(Inputs!$B$79=1,B39="OPEN",A39>=Inputs!$B$82,C39>=$B$10,MOD(C39-$B$10,$B$9)=0),MIN(MAX(0,T39-$B$8)*Inputs!$B$81,MAX(0,H39+J39-K39)),0) -> 0 | V39: =IF(AND(Inputs!$B$79=1,B39="OPEN",A39>=Inputs!$B$82,C39>=$B$10,MOD(C39-$B$10,$B$9)=0),MIN(MAX(0,MAX(0,T39-$B$8)*Inputs!$B$81-U39),MAX(0,G39-I39)),0) -> 0 | W39: =MAX(0,G39-I39-V39) -> 240000 | X39: =MAX(0,H39+J39-K39-U39) -> 900000 | Y39: =W39+X39 -> 1140000 | Z39: =T39-U39-V39 -> 131346.76
A40: =A39+1 -> 9 | B40: {=INDEX('Monthly Base'!$B$5:$B$67,A40+1)} -> OPEN | C40: {=INDEX('Monthly Base'!$C$5:$C$67,A40+1)} -> 7 | D40: {=INDEX('Monthly Base'!$O$5:$O$67,A40+1)} -> 7770.661 | E40: {=INDEX('Monthly Base'!$Y$5:$Y$67,A40+1)} -> 0 | F40: =Z39 -> 131346.76 | G40: =W39 -> 240000 | H40: =X39 -> 900000 | I40: =IF(OR(A40<Inputs!$B$15,G40<=0),0,MIN(Financing!$B$10,G40)) -> 0 | J40: =IF(OR(A40<Inputs!$B$15,H40<=0),0,H40*Inputs!$B$13/12) -> 0 | K40: =IF(OR(A40<Inputs!$B$15,H40<=0),0,MIN(Financing!$C$10,H40+J40)) -> 0 | L40: =I40+K40 -> 0 | M40: =S39 -> 130454.97 | N40: =IF(B40="OPEN",IF(Y39=0,$B$7,IF(AND(C40>0,C40>=$B$5,$B$6>0),$B$6,0)),0) -> 0 | O40: =IF(B40="OPEN",IF(Y39=0,$B$7,IF(AND(C40>0,C40>=$B$5,$B$6>0),$B$6,0)),0) -> 0 | P40: =(N40+O40)*(1+$B$11) -> 0 | Q40: =D40-J40-IF(C40=0,0,Inputs!$B$18)-P40 -> 957.66102 | R40: =MAX(0,Q40-M40)*Inputs!$B$17 -> 0 | S40: =MAX(0,M40-MAX(0,Q40))+MAX(0,-Q40) -> 129497.31 | T40: =F40+D40+E40-L40-P40-R40 -> 139117.42 | U40: =IF(AND(Inputs!$B$79=1,B40="OPEN",A40>=Inputs!$B$82,C40>=$B$10,MOD(C40-$B$10,$B$9)=0),MIN(MAX(0,T40-$B$8)*Inputs!$B$81,MAX(0,H40+J40-K40)),0) -> 0 | V40: =IF(AND(Inputs!$B$79=1,B40="OPEN",A40>=Inputs!$B$82,C40>=$B$10,MOD(C40-$B$10,$B$9)=0),MIN(MAX(0,MAX(0,T40-$B$8)*Inputs!$B$81-U40),MAX(0,G40-I40)),0) -> 0 | W40: =MAX(0,G40-I40-V40) -> 240000 | X40: =MAX(0,H40+J40-K40-U40) -> 900000 | Y40: =W40+X40 -> 1140000 | Z40: =T40-U40-V40 -> 139117.42
A41: =A40+1 -> 10 | B41: {=INDEX('Monthly Base'!$B$5:$B$67,A41+1)} -> OPEN | C41: {=INDEX('Monthly Base'!$C$5:$C$67,A41+1)} -> 8 | D41: {=INDEX('Monthly Base'!$O$5:$O$67,A41+1)} -> 11325.432 | E41: {=INDEX('Monthly Base'!$Y$5:$Y$67,A41+1)} -> 0 | F41: =Z40 -> 139117.42 | G41: =W40 -> 240000 | H41: =X40 -> 900000 | I41: =IF(OR(A41<Inputs!$B$15,G41<=0),0,MIN(Financing!$B$10,G41)) -> 0 | J41: =IF(OR(A41<Inputs!$B$15,H41<=0),0,H41*Inputs!$B$13/12) -> 0 | K41: =IF(OR(A41<Inputs!$B$15,H41<=0),0,MIN(Financing!$C$10,H41+J41)) -> 0 | L41: =I41+K41 -> 0 | M41: =S40 -> 129497.31 | N41: =IF(B41="OPEN",IF(Y40=0,$B$7,IF(AND(C41>0,C41>=$B$5,$B$6>0),$B$6,0)),0) -> 0 | O41: =IF(B41="OPEN",IF(Y40=0,$B$7,IF(AND(C41>0,C41>=$B$5,$B$6>0),$B$6,0)),0) -> 0 | P41: =(N41+O41)*(1+$B$11) -> 0 | Q41: =D41-J41-IF(C41=0,0,Inputs!$B$18)-P41 -> 4512.4322 | R41: =MAX(0,Q41-M41)*Inputs!$B$17 -> 0 | S41: =MAX(0,M41-MAX(0,Q41))+MAX(0,-Q41) -> 124984.88 | T41: =F41+D41+E41-L41-P41-R41 -> 150442.85 | U41: =IF(AND(Inputs!$B$79=1,B41="OPEN",A41>=Inputs!$B$82,C41>=$B$10,MOD(C41-$B$10,$B$9)=0),MIN(MAX(0,T41-$B$8)*Inputs!$B$81,MAX(0,H41+J41-K41)),0) -> 0 | V41: =IF(AND(Inputs!$B$79=1,B41="OPEN",A41>=Inputs!$B$82,C41>=$B$10,MOD(C41-$B$10,$B$9)=0),MIN(MAX(0,MAX(0,T41-$B$8)*Inputs!$B$81-U41),MAX(0,G41-I41)),0) -> 0 | W41: =MAX(0,G41-I41-V41) -> 240000 | X41: =MAX(0,H41+J41-K41-U41) -> 900000 | Y41: =W41+X41 -> 1140000 | Z41: =T41-U41-V41 -> 150442.85
A42: =A41+1 -> 11 | B42: {=INDEX('Monthly Base'!$B$5:$B$67,A42+1)} -> OPEN | C42: {=INDEX('Monthly Base'!$C$5:$C$67,A42+1)} -> 9 | D42: {=INDEX('Monthly Base'!$O$5:$O$67,A42+1)} -> 14880.203 | E42: {=INDEX('Monthly Base'!$Y$5:$Y$67,A42+1)} -> 0 | F42: =Z41 -> 150442.85 | G42: =W41 -> 240000 | H42: =X41 -> 900000 | I42: =IF(OR(A42<Inputs!$B$15,G42<=0),0,MIN(Financing!$B$10,G42)) -> 0 | J42: =IF(OR(A42<Inputs!$B$15,H42<=0),0,H42*Inputs!$B$13/12) -> 0 | K42: =IF(OR(A42<Inputs!$B$15,H42<=0),0,MIN(Financing!$C$10,H42+J42)) -> 0 | L42: =I42+K42 -> 0 | M42: =S41 -> 124984.88 | N42: =IF(B42="OPEN",IF(Y41=0,$B$7,IF(AND(C42>0,C42>=$B$5,$B$6>0),$B$6,0)),0) -> 0 | O42: =IF(B42="OPEN",IF(Y41=0,$B$7,IF(AND(C42>0,C42>=$B$5,$B$6>0),$B$6,0)),0) -> 0 | P42: =(N42+O42)*(1+$B$11) -> 0 | Q42: =D42-J42-IF(C42=0,0,Inputs!$B$18)-P42 -> 8067.2034 | R42: =MAX(0,Q42-M42)*Inputs!$B$17 -> 0 | S42: =MAX(0,M42-MAX(0,Q42))+MAX(0,-Q42) -> 116917.68 | T42: =F42+D42+E42-L42-P42-R42 -> 165323.05 | U42: =IF(AND(Inputs!$B$79=1,B42="OPEN",A42>=Inputs!$B$82,C42>=$B$10,MOD(C42-$B$10,$B$9)=0),MIN(MAX(0,T42-$B$8)*Inputs!$B$81,MAX(0,H42+J42-K42)),0) -> 0 | V42: =IF(AND(Inputs!$B$79=1,B42="OPEN",A42>=Inputs!$B$82,C42>=$B$10,MOD(C42-$B$10,$B$9)=0),MIN(MAX(0,MAX(0,T42-$B$8)*Inputs!$B$81-U42),MAX(0,G42-I42)),0) -> 0 | W42: =MAX(0,G42-I42-V42) -> 240000 | X42: =MAX(0,H42+J42-K42-U42) -> 900000 | Y42: =W42+X42 -> 1140000 | Z42: =T42-U42-V42 -> 165323.05
A43: =A42+1 -> 12 | B43: {=INDEX('Monthly Base'!$B$5:$B$67,A43+1)} -> OPEN | C43: {=INDEX('Monthly Base'!$C$5:$C$67,A43+1)} -> 10 | D43: {=INDEX('Monthly Base'!$O$5:$O$67,A43+1)} -> 18434.975 | E43: {=INDEX('Monthly Base'!$Y$5:$Y$67,A43+1)} -> 0 | F43: =Z42 -> 165323.05 | G43: =W42 -> 240000 | H43: =X42 -> 900000 | I43: =IF(OR(A43<Inputs!$B$15,G43<=0),0,MIN(Financing!$B$10,G43)) -> 4000 | J43: =IF(OR(A43<Inputs!$B$15,H43<=0),0,H43*Inputs!$B$13/12) -> 3562.5 | K43: =IF(OR(A43<Inputs!$B$15,H43<=0),0,MIN(Financing!$C$10,H43+J43)) -> 16881.221 | L43: =I43+K43 -> 20881.221 | M43: =S42 -> 116917.68 | N43: =IF(B43="OPEN",IF(Y42=0,$B$7,IF(AND(C43>0,C43>=$B$5,$B$6>0),$B$6,0)),0) -> 0 | O43: =IF(B43="OPEN",IF(Y42=0,$B$7,IF(AND(C43>0,C43>=$B$5,$B$6>0),$B$6,0)),0) -> 0 | P43: =(N43+O43)*(1+$B$11) -> 0 | Q43: =D43-J43-IF(C43=0,0,Inputs!$B$18)-P43 -> 8059.4746 | R43: =MAX(0,Q43-M43)*Inputs!$B$17 -> 0 | S43: =MAX(0,M43-MAX(0,Q43))+MAX(0,-Q43) -> 108858.2 | T43: =F43+D43+E43-L43-P43-R43 -> 162876.81 | U43: =IF(AND(Inputs!$B$79=1,B43="OPEN",A43>=Inputs!$B$82,C43>=$B$10,MOD(C43-$B$10,$B$9)=0),MIN(MAX(0,T43-$B$8)*Inputs!$B$81,MAX(0,H43+J43-K43)),0) -> 0 | V43: =IF(AND(Inputs!$B$79=1,B43="OPEN",A43>=Inputs!$B$82,C43>=$B$10,MOD(C43-$B$10,$B$9)=0),MIN(MAX(0,MAX(0,T43-$B$8)*Inputs!$B$81-U43),MAX(0,G43-I43)),0) -> 0 | W43: =MAX(0,G43-I43-V43) -> 236000 | X43: =MAX(0,H43+J43-K43-U43) -> 886681.28 | Y43: =W43+X43 -> 1122681.3 | Z43: =T43-U43-V43 -> 162876.81
... A93: =A92+1 -> 62 | B93: {=INDEX('Monthly Base'!$B$5:$B$67,A93+1)} -> OPEN | C93: {=INDEX('Monthly Base'!$C$5:$C$67,A93+1)} -> 60 | D93: {=INDEX('Monthly Base'!$O$5:$O$67,A93+1)} -> 100568.9 | E93: {=INDEX('Monthly Base'!$Y$5:$Y$67,A93+1)} -> 0 | F93: =Z92 -> 1409225.7 | G93: =W92 -> 0 | H93: =X92 -> 0 | I93: =IF(OR(A93<Inputs!$B$15,G93<=0),0,MIN(Financing!$B$10,G93)) -> 0 | J93: =IF(OR(A93<Inputs!$B$15,H93<=0),0,H93*Inputs!$B$13/12) -> 0 | K93: =IF(OR(A93<Inputs!$B$15,H93<=0),0,MIN(Financing!$C$10,H93+J93)) -> 0 | L93: =I93+K93 -> 0 | M93: =S92 -> 0 | N93: =IF(B93="OPEN",IF(Y92=0,$B$7,IF(AND(C93>0,C93>=$B$5,$B$6>0),$B$6,0)),0) -> 10000 | O93: =IF(B93="OPEN",IF(Y92=0,$B$7,IF(AND(C93>0,C93>=$B$5,$B$6>0),$B$6,0)),0) -> 10000 | P93: =(N93+O93)*(1+$B$11) -> 24000 | Q93: =D93-J93-IF(C93=0,0,Inputs!$B$18)-P93 -> 69755.898 | R93: =MAX(0,Q93-M93)*Inputs!$B$17 -> 16043.857 | S93: =MAX(0,M93-MAX(0,Q93))+MAX(0,-Q93) -> 0 | T93: =F93+D93+E93-L93-P93-R93 -> 1469750.8 | U93: =IF(AND(Inputs!$B$79=1,B93="OPEN",A93>=Inputs!$B$82,C93>=$B$10,MOD(C93-$B$10,$B$9)=0),MIN(MAX(0,T93-$B$8)*Inputs!$B$81,MAX(0,H93+J93-K93)),0) -> 0 | V93: =IF(AND(Inputs!$B$79=1,B93="OPEN",A93>=Inputs!$B$82,C93>=$B$10,MOD(C93-$B$10,$B$9)=0),MIN(MAX(0,MAX(0,T93-$B$8)*Inputs!$B$81-U93),MAX(0,G93-I93)),0) -> 0 | W93: =MAX(0,G93-I93-V93) -> 0 | X93: =MAX(0,H93+J93-K93-U93) -> 0 | Y93: =W93+X93 -> 0 | Z93: =T93-U93-V93 -> 1469750.8
A100: Timeline Mo | B100: Phase | C100: Operating Mo | D100: EBITDA | E100: Build VAT Refund | F100: Opening Cash | G100: Loan A Opening | H100: Loan B Opening | I100: Loan A Scheduled | J100: Loan B Interest | K100: Loan B Scheduled | L100: Scheduled Debt | M100: Tax Loss CF Begin | N100: Partner 1 Gross | O100: Partner 2 Gross | P100: Owner Payroll Cost | Q100: Taxable Before Loss | R100: Corporate Tax | S100: Tax Loss CF End | T100: Cash Before Extra Debt | U100: Extra to Loan B | V100: Extra to Loan A | W100: Loan A Closing | X100: Loan B Closing | Y100: Total Debt | Z100: Ending Cash
A101: 0 | B101: {=INDEX('Monthly Base'!$B$5:$B$67,A101+1)} -> BUILD | C101: {=INDEX('Monthly Base'!$C$5:$C$67,A101+1)} -> 0 | D101: {=INDEX('Monthly Base'!$O$5:$O$67,A101+1)} -> -20018 | E101: {=INDEX('Monthly Base'!$Y$5:$Y$67,A101+1)} -> 0 | F101: ='Startup & Funding'!$B$19 -> 68990.001 | G101: =Inputs!$B$9 -> 240000 | H101: =Inputs!$B$10 -> 900000 | I101: =IF(OR(A101<Inputs!$B$15,G101<=0),0,MIN(Financing!$B$10,G101)) -> 0 | J101: =IF(OR(A101<Inputs!$B$15,H101<=0),0,H101*Inputs!$B$13/12) -> 0 | K101: =IF(OR(A101<Inputs!$B$15,H101<=0),0,MIN(Financing!$C$10,H101+J101)) -> 0 | L101: =I101+K101 -> 0 | M101: 0 | N101: 0 | O101: 0 | P101: =(N101+O101)*(1+$C$11) -> 0 | Q101: =D101-J101-IF(C101=0,0,Inputs!$B$18)-P101 -> -20018 | R101: =MAX(0,Q101-M101)*Inputs!$B$17 -> 0 | S101: =MAX(0,M101-MAX(0,Q101))+MAX(0,-Q101) -> 20018 | T101: =F101+D101+E101-L101-P101-R101 -> 48972.001 | U101: =IF(AND(Inputs!$B$79=1,B101="OPEN",A101>=Inputs!$B$82,C101>=$C$10,MOD(C101-$C$10,$C$9)=0),MIN(MAX(0,T101-$C$8)*Inputs!$B$81,MAX(0,H101+J101-K101)),0) -> 0 | V101: =IF(AND(Inputs!$B$79=1,B101="OPEN",A101>=Inputs!$B$82,C101>=$C$10,MOD(C101-$C$10,$C$9)=0),MIN(MAX(0,MAX(0,T101-$C$8)*Inputs!$B$81-U101),MAX(0,G101-I101)),0) -> 0 | W101: =MAX(0,G101-I101-V101) -> 240000 | X101: =MAX(0,H101+J101-K101-U101) -> 900000 | Y101: =W101+X101 -> 1140000 | Z101: =T101-U101-V101 -> 48972.001
A102: =A101+1 -> 1 | B102: {=INDEX('Monthly Base'!$B$5:$B$67,A102+1)} -> BUILD | C102: {=INDEX('Monthly Base'!$C$5:$C$67,A102+1)} -> 0 | D102: {=INDEX('Monthly Base'!$O$5:$O$67,A102+1)} -> -20018 | E102: {=INDEX('Monthly Base'!$Y$5:$Y$67,A102+1)} -> 0 | F102: =Z101 -> 48972.001 | G102: =W101 -> 240000 | H102: =X101 -> 900000 | I102: =IF(OR(A102<Inputs!$B$15,G102<=0),0,MIN(Financing!$B$10,G102)) -> 0 | J102: =IF(OR(A102<Inputs!$B$15,H102<=0),0,H102*Inputs!$B$13/12) -> 0 | K102: =IF(OR(A102<Inputs!$B$15,H102<=0),0,MIN(Financing!$C$10,H102+J102)) -> 0 | L102: =I102+K102 -> 0 | M102: =S101 -> 20018 | N102: =IF(B102="OPEN",IF(Y101=0,$C$7,IF(AND(C102>0,C102>=$C$5,$C$6>0),$C$6,0)),0) -> 0 | O102: =IF(B102="OPEN",IF(Y101=0,$C$7,IF(AND(C102>0,C102>=$C$5,$C$6>0),$C$6,0)),0) -> 0 | P102: =(N102+O102)*(1+$C$11) -> 0 | Q102: =D102-J102-IF(C102=0,0,Inputs!$B$18)-P102 -> -20018 | R102: =MAX(0,Q102-M102)*Inputs!$B$17 -> 0 | S102: =MAX(0,M102-MAX(0,Q102))+MAX(0,-Q102) -> 40036 | T102: =F102+D102+E102-L102-P102-R102 -> 28954.001 | U102: =IF(AND(Inputs!$B$79=1,B102="OPEN",A102>=Inputs!$B$82,C102>=$C$10,MOD(C102-$C$10,$C$9)=0),MIN(MAX(0,T102-$C$8)*Inputs!$B$81,MAX(0,H102+J102-K102)),0) -> 0 | V102: =IF(AND(Inputs!$B$79=1,B102="OPEN",A102>=Inputs!$B$82,C102>=$C$10,MOD(C102-$C$10,$C$9)=0),MIN(MAX(0,MAX(0,T102-$C$8)*Inputs!$B$81-U102),MAX(0,G102-I102)),0) -> 0 | W102: =MAX(0,G102-I102-V102) -> 240000 | X102: =MAX(0,H102+J102-K102-U102) -> 900000 | Y102: =W102+X102 -> 1140000 | Z102: =T102-U102-V102 -> 28954.001
A103: =A102+1 -> 2 | B103: {=INDEX('Monthly Base'!$B$5:$B$67,A103+1)} -> BUILD | C103: {=INDEX('Monthly Base'!$C$5:$C$67,A103+1)} -> 0 | D103: {=INDEX('Monthly Base'!$O$5:$O$67,A103+1)} -> -20018 | E103: {=INDEX('Monthly Base'!$Y$5:$Y$67,A103+1)} -> 151933.73 | F103: =Z102 -> 28954.001 | G103: =W102 -> 240000 | H103: =X102 -> 900000 | I103: =IF(OR(A103<Inputs!$B$15,G103<=0),0,MIN(Financing!$B$10,G103)) -> 0 | J103: =IF(OR(A103<Inputs!$B$15,H103<=0),0,H103*Inputs!$B$13/12) -> 0 | K103: =IF(OR(A103<Inputs!$B$15,H103<=0),0,MIN(Financing!$C$10,H103+J103)) -> 0 | L103: =I103+K103 -> 0 | M103: =S102 -> 40036 | N103: =IF(B103="OPEN",IF(Y102=0,$C$7,IF(AND(C103>0,C103>=$C$5,$C$6>0),$C$6,0)),0) -> 0 | O103: =IF(B103="OPEN",IF(Y102=0,$C$7,IF(AND(C103>0,C103>=$C$5,$C$6>0),$C$6,0)),0) -> 0 | P103: =(N103+O103)*(1+$C$11) -> 0 | Q103: =D103-J103-IF(C103=0,0,Inputs!$B$18)-P103 -> -20018 | R103: =MAX(0,Q103-M103)*Inputs!$B$17 -> 0 | S103: =MAX(0,M103-MAX(0,Q103))+MAX(0,-Q103) -> 60054 | T103: =F103+D103+E103-L103-P103-R103 -> 160869.73 | U103: =IF(AND(Inputs!$B$79=1,B103="OPEN",A103>=Inputs!$B$82,C103>=$C$10,MOD(C103-$C$10,$C$9)=0),MIN(MAX(0,T103-$C$8)*Inputs!$B$81,MAX(0,H103+J103-K103)),0) -> 0 | V103: =IF(AND(Inputs!$B$79=1,B103="OPEN",A103>=Inputs!$B$82,C103>=$C$10,MOD(C103-$C$10,$C$9)=0),MIN(MAX(0,MAX(0,T103-$C$8)*Inputs!$B$81-U103),MAX(0,G103-I103)),0) -> 0 | W103: =MAX(0,G103-I103-V103) -> 240000 | X103: =MAX(0,H103+J103-K103-U103) -> 900000 | Y103: =W103+X103 -> 1140000 | Z103: =T103-U103-V103 -> 160869.73
A104: =A103+1 -> 3 | B104: {=INDEX('Monthly Base'!$B$5:$B$67,A104+1)} -> OPEN | C104: {=INDEX('Monthly Base'!$C$5:$C$67,A104+1)} -> 1 | D104: {=INDEX('Monthly Base'!$O$5:$O$67,A104+1)} -> -13932.153 | E104: {=INDEX('Monthly Base'!$Y$5:$Y$67,A104+1)} -> 0 | F104: =Z103 -> 160869.73 | G104: =W103 -> 240000 | H104: =X103 -> 900000 | I104: =IF(OR(A104<Inputs!$B$15,G104<=0),0,MIN(Financing!$B$10,G104)) -> 0 | J104: =IF(OR(A104<Inputs!$B$15,H104<=0),0,H104*Inputs!$B$13/12) -> 0 | K104: =IF(OR(A104<Inputs!$B$15,H104<=0),0,MIN(Financing!$C$10,H104+J104)) -> 0 | L104: =I104+K104 -> 0 | M104: =S103 -> 60054 | N104: =IF(B104="OPEN",IF(Y103=0,$C$7,IF(AND(C104>0,C104>=$C$5,$C$6>0),$C$6,0)),0) -> 0 | O104: =IF(B104="OPEN",IF(Y103=0,$C$7,IF(AND(C104>0,C104>=$C$5,$C$6>0),$C$6,0)),0) -> 0 | P104: =(N104+O104)*(1+$C$11) -> 0 | Q104: =D104-J104-IF(C104=0,0,Inputs!$B$18)-P104 -> -20745.153 | R104: =MAX(0,Q104-M104)*Inputs!$B$17 -> 0 | S104: =MAX(0,M104-MAX(0,Q104))+MAX(0,-Q104) -> 80799.153 | T104: =F104+D104+E104-L104-P104-R104 -> 146937.58 | U104: =IF(AND(Inputs!$B$79=1,B104="OPEN",A104>=Inputs!$B$82,C104>=$C$10,MOD(C104-$C$10,$C$9)=0),MIN(MAX(0,T104-$C$8)*Inputs!$B$81,MAX(0,H104+J104-K104)),0) -> 0 | V104: =IF(AND(Inputs!$B$79=1,B104="OPEN",A104>=Inputs!$B$82,C104>=$C$10,MOD(C104-$C$10,$C$9)=0),MIN(MAX(0,MAX(0,T104-$C$8)*Inputs!$B$81-U104),MAX(0,G104-I104)),0) -> 0 | W104: =MAX(0,G104-I104-V104) -> 240000 | X104: =MAX(0,H104+J104-K104-U104) -> 900000 | Y104: =W104+X104 -> 1140000 | Z104: =T104-U104-V104 -> 146937.58
A105: =A104+1 -> 4 | B105: {=INDEX('Monthly Base'!$B$5:$B$67,A105+1)} -> OPEN | C105: {=INDEX('Monthly Base'!$C$5:$C$67,A105+1)} -> 2 | D105: {=INDEX('Monthly Base'!$O$5:$O$67,A105+1)} -> -10377.381 | E105: {=INDEX('Monthly Base'!$Y$5:$Y$67,A105+1)} -> 0 | F105: =Z104 -> 146937.58 | G105: =W104 -> 240000 | H105: =X104 -> 900000 | I105: =IF(OR(A105<Inputs!$B$15,G105<=0),0,MIN(Financing!$B$10,G105)) -> 0 | J105: =IF(OR(A105<Inputs!$B$15,H105<=0),0,H105*Inputs!$B$13/12) -> 0 | K105: =IF(OR(A105<Inputs!$B$15,H105<=0),0,MIN(Financing!$C$10,H105+J105)) -> 0 | L105: =I105+K105 -> 0 | M105: =S104 -> 80799.153 | N105: =IF(B105="OPEN",IF(Y104=0,$C$7,IF(AND(C105>0,C105>=$C$5,$C$6>0),$C$6,0)),0) -> 0 | O105: =IF(B105="OPEN",IF(Y104=0,$C$7,IF(AND(C105>0,C105>=$C$5,$C$6>0),$C$6,0)),0) -> 0 | P105: =(N105+O105)*(1+$C$11) -> 0 | Q105: =D105-J105-IF(C105=0,0,Inputs!$B$18)-P105 -> -17190.381 | R105: =MAX(0,Q105-M105)*Inputs!$B$17 -> 0 | S105: =MAX(0,M105-MAX(0,Q105))+MAX(0,-Q105) -> 97989.534 | T105: =F105+D105+E105-L105-P105-R105 -> 136560.2 | U105: =IF(AND(Inputs!$B$79=1,B105="OPEN",A105>=Inputs!$B$82,C105>=$C$10,MOD(C105-$C$10,$C$9)=0),MIN(MAX(0,T105-$C$8)*Inputs!$B$81,MAX(0,H105+J105-K105)),0) -> 0 | V105: =IF(AND(Inputs!$B$79=1,B105="OPEN",A105>=Inputs!$B$82,C105>=$C$10,MOD(C105-$C$10,$C$9)=0),MIN(MAX(0,MAX(0,T105-$C$8)*Inputs!$B$81-U105),MAX(0,G105-I105)),0) -> 0 | W105: =MAX(0,G105-I105-V105) -> 240000 | X105: =MAX(0,H105+J105-K105-U105) -> 900000 | Y105: =W105+X105 -> 1140000 | Z105: =T105-U105-V105 -> 136560.2
A106: =A105+1 -> 5 | B106: {=INDEX('Monthly Base'!$B$5:$B$67,A106+1)} -> OPEN | C106: {=INDEX('Monthly Base'!$C$5:$C$67,A106+1)} -> 3 | D106: {=INDEX('Monthly Base'!$O$5:$O$67,A106+1)} -> -6635.5169 | E106: {=INDEX('Monthly Base'!$Y$5:$Y$67,A106+1)} -> 0 | F106: =Z105 -> 136560.2 | G106: =W105 -> 240000 | H106: =X105 -> 900000 | I106: =IF(OR(A106<Inputs!$B$15,G106<=0),0,MIN(Financing!$B$10,G106)) -> 0 | J106: =IF(OR(A106<Inputs!$B$15,H106<=0),0,H106*Inputs!$B$13/12) -> 0 | K106: =IF(OR(A106<Inputs!$B$15,H106<=0),0,MIN(Financing!$C$10,H106+J106)) -> 0 | L106: =I106+K106 -> 0 | M106: =S105 -> 97989.534 | N106: =IF(B106="OPEN",IF(Y105=0,$C$7,IF(AND(C106>0,C106>=$C$5,$C$6>0),$C$6,0)),0) -> 0 | O106: =IF(B106="OPEN",IF(Y105=0,$C$7,IF(AND(C106>0,C106>=$C$5,$C$6>0),$C$6,0)),0) -> 0 | P106: =(N106+O106)*(1+$C$11) -> 0 | Q106: =D106-J106-IF(C106=0,0,Inputs!$B$18)-P106 -> -13448.517 | R106: =MAX(0,Q106-M106)*Inputs!$B$17 -> 0 | S106: =MAX(0,M106-MAX(0,Q106))+MAX(0,-Q106) -> 111438.05 | T106: =F106+D106+E106-L106-P106-R106 -> 129924.68 | U106: =IF(AND(Inputs!$B$79=1,B106="OPEN",A106>=Inputs!$B$82,C106>=$C$10,MOD(C106-$C$10,$C$9)=0),MIN(MAX(0,T106-$C$8)*Inputs!$B$81,MAX(0,H106+J106-K106)),0) -> 0 | V106: =IF(AND(Inputs!$B$79=1,B106="OPEN",A106>=Inputs!$B$82,C106>=$C$10,MOD(C106-$C$10,$C$9)=0),MIN(MAX(0,MAX(0,T106-$C$8)*Inputs!$B$81-U106),MAX(0,G106-I106)),0) -> 0 | W106: =MAX(0,G106-I106-V106) -> 240000 | X106: =MAX(0,H106+J106-K106-U106) -> 900000 | Y106: =W106+X106 -> 1140000 | Z106: =T106-U106-V106 -> 129924.68
A107: =A106+1 -> 6 | B107: {=INDEX('Monthly Base'!$B$5:$B$67,A107+1)} -> OPEN | C107: {=INDEX('Monthly Base'!$C$5:$C$67,A107+1)} -> 4 | D107: {=INDEX('Monthly Base'!$O$5:$O$67,A107+1)} -> -3080.7458 | E107: {=INDEX('Monthly Base'!$Y$5:$Y$67,A107+1)} -> 0 | F107: =Z106 -> 129924.68 | G107: =W106 -> 240000 | H107: =X106 -> 900000 | I107: =IF(OR(A107<Inputs!$B$15,G107<=0),0,MIN(Financing!$B$10,G107)) -> 0 | J107: =IF(OR(A107<Inputs!$B$15,H107<=0),0,H107*Inputs!$B$13/12) -> 0 | K107: =IF(OR(A107<Inputs!$B$15,H107<=0),0,MIN(Financing!$C$10,H107+J107)) -> 0 | L107: =I107+K107 -> 0 | M107: =S106 -> 111438.05 | N107: =IF(B107="OPEN",IF(Y106=0,$C$7,IF(AND(C107>0,C107>=$C$5,$C$6>0),$C$6,0)),0) -> 0 | O107: =IF(B107="OPEN",IF(Y106=0,$C$7,IF(AND(C107>0,C107>=$C$5,$C$6>0),$C$6,0)),0) -> 0 | P107: =(N107+O107)*(1+$C$11) -> 0 | Q107: =D107-J107-IF(C107=0,0,Inputs!$B$18)-P107 -> -9893.7458 | R107: =MAX(0,Q107-M107)*Inputs!$B$17 -> 0 | S107: =MAX(0,M107-MAX(0,Q107))+MAX(0,-Q107) -> 121331.8 | T107: =F107+D107+E107-L107-P107-R107 -> 126843.93 | U107: =IF(AND(Inputs!$B$79=1,B107="OPEN",A107>=Inputs!$B$82,C107>=$C$10,MOD(C107-$C$10,$C$9)=0),MIN(MAX(0,T107-$C$8)*Inputs!$B$81,MAX(0,H107+J107-K107)),0) -> 0 | V107: =IF(AND(Inputs!$B$79=1,B107="OPEN",A107>=Inputs!$B$82,C107>=$C$10,MOD(C107-$C$10,$C$9)=0),MIN(MAX(0,MAX(0,T107-$C$8)*Inputs!$B$81-U107),MAX(0,G107-I107)),0) -> 0 | W107: =MAX(0,G107-I107-V107) -> 240000 | X107: =MAX(0,H107+J107-K107-U107) -> 900000 | Y107: =W107+X107 -> 1140000 | Z107: =T107-U107-V107 -> 126843.93
A108: =A107+1 -> 7 | B108: {=INDEX('Monthly Base'!$B$5:$B$67,A108+1)} -> OPEN | C108: {=INDEX('Monthly Base'!$C$5:$C$67,A108+1)} -> 5 | D108: {=INDEX('Monthly Base'!$O$5:$O$67,A108+1)} -> 474.02542 | E108: {=INDEX('Monthly Base'!$Y$5:$Y$67,A108+1)} -> 0 | F108: =Z107 -> 126843.93 | G108: =W107 -> 240000 | H108: =X107 -> 900000 | I108: =IF(OR(A108<Inputs!$B$15,G108<=0),0,MIN(Financing!$B$10,G108)) -> 0 | J108: =IF(OR(A108<Inputs!$B$15,H108<=0),0,H108*Inputs!$B$13/12) -> 0 | K108: =IF(OR(A108<Inputs!$B$15,H108<=0),0,MIN(Financing!$C$10,H108+J108)) -> 0 | L108: =I108+K108 -> 0 | M108: =S107 -> 121331.8 | N108: =IF(B108="OPEN",IF(Y107=0,$C$7,IF(AND(C108>0,C108>=$C$5,$C$6>0),$C$6,0)),0) -> 0 | O108: =IF(B108="OPEN",IF(Y107=0,$C$7,IF(AND(C108>0,C108>=$C$5,$C$6>0),$C$6,0)),0) -> 0 | P108: =(N108+O108)*(1+$C$11) -> 0 | Q108: =D108-J108-IF(C108=0,0,Inputs!$B$18)-P108 -> -6338.9746 | R108: =MAX(0,Q108-M108)*Inputs!$B$17 -> 0 | S108: =MAX(0,M108-MAX(0,Q108))+MAX(0,-Q108) -> 127670.77 | T108: =F108+D108+E108-L108-P108-R108 -> 127317.96 | U108: =IF(AND(Inputs!$B$79=1,B108="OPEN",A108>=Inputs!$B$82,C108>=$C$10,MOD(C108-$C$10,$C$9)=0),MIN(MAX(0,T108-$C$8)*Inputs!$B$81,MAX(0,H108+J108-K108)),0) -> 0 | V108: =IF(AND(Inputs!$B$79=1,B108="OPEN",A108>=Inputs!$B$82,C108>=$C$10,MOD(C108-$C$10,$C$9)=0),MIN(MAX(0,MAX(0,T108-$C$8)*Inputs!$B$81-U108),MAX(0,G108-I108)),0) -> 0 | W108: =MAX(0,G108-I108-V108) -> 240000 | X108: =MAX(0,H108+J108-K108-U108) -> 900000 | Y108: =W108+X108 -> 1140000 | Z108: =T108-U108-V108 -> 127317.96
A109: =A108+1 -> 8 | B109: {=INDEX('Monthly Base'!$B$5:$B$67,A109+1)} -> OPEN | C109: {=INDEX('Monthly Base'!$C$5:$C$67,A109+1)} -> 6 | D109: {=INDEX('Monthly Base'!$O$5:$O$67,A109+1)} -> 4028.7966 | E109: {=INDEX('Monthly Base'!$Y$5:$Y$67,A109+1)} -> 0 | F109: =Z108 -> 127317.96 | G109: =W108 -> 240000 | H109: =X108 -> 900000 | I109: =IF(OR(A109<Inputs!$B$15,G109<=0),0,MIN(Financing!$B$10,G109)) -> 0 | J109: =IF(OR(A109<Inputs!$B$15,H109<=0),0,H109*Inputs!$B$13/12) -> 0 | K109: =IF(OR(A109<Inputs!$B$15,H109<=0),0,MIN(Financing!$C$10,H109+J109)) -> 0 | L109: =I109+K109 -> 0 | M109: =S108 -> 127670.77 | N109: =IF(B109="OPEN",IF(Y108=0,$C$7,IF(AND(C109>0,C109>=$C$5,$C$6>0),$C$6,0)),0) -> 0 | O109: =IF(B109="OPEN",IF(Y108=0,$C$7,IF(AND(C109>0,C109>=$C$5,$C$6>0),$C$6,0)),0) -> 0 | P109: =(N109+O109)*(1+$C$11) -> 0 | Q109: =D109-J109-IF(C109=0,0,Inputs!$B$18)-P109 -> -2784.2034 | R109: =MAX(0,Q109-M109)*Inputs!$B$17 -> 0 | S109: =MAX(0,M109-MAX(0,Q109))+MAX(0,-Q109) -> 130454.97 | T109: =F109+D109+E109-L109-P109-R109 -> 131346.76 | U109: =IF(AND(Inputs!$B$79=1,B109="OPEN",A109>=Inputs!$B$82,C109>=$C$10,MOD(C109-$C$10,$C$9)=0),MIN(MAX(0,T109-$C$8)*Inputs!$B$81,MAX(0,H109+J109-K109)),0) -> 0 | V109: =IF(AND(Inputs!$B$79=1,B109="OPEN",A109>=Inputs!$B$82,C109>=$C$10,MOD(C109-$C$10,$C$9)=0),MIN(MAX(0,MAX(0,T109-$C$8)*Inputs!$B$81-U109),MAX(0,G109-I109)),0) -> 0 | W109: =MAX(0,G109-I109-V109) -> 240000 | X109: =MAX(0,H109+J109-K109-U109) -> 900000 | Y109: =W109+X109 -> 1140000 | Z109: =T109-U109-V109 -> 131346.76
A110: =A109+1 -> 9 | B110: {=INDEX('Monthly Base'!$B$5:$B$67,A110+1)} -> OPEN | C110: {=INDEX('Monthly Base'!$C$5:$C$67,A110+1)} -> 7 | D110: {=INDEX('Monthly Base'!$O$5:$O$67,A110+1)} -> 7770.661 | E110: {=INDEX('Monthly Base'!$Y$5:$Y$67,A110+1)} -> 0 | F110: =Z109 -> 131346.76 | G110: =W109 -> 240000 | H110: =X109 -> 900000 | I110: =IF(OR(A110<Inputs!$B$15,G110<=0),0,MIN(Financing!$B$10,G110)) -> 0 | J110: =IF(OR(A110<Inputs!$B$15,H110<=0),0,H110*Inputs!$B$13/12) -> 0 | K110: =IF(OR(A110<Inputs!$B$15,H110<=0),0,MIN(Financing!$C$10,H110+J110)) -> 0 | L110: =I110+K110 -> 0 | M110: =S109 -> 130454.97 | N110: =IF(B110="OPEN",IF(Y109=0,$C$7,IF(AND(C110>0,C110>=$C$5,$C$6>0),$C$6,0)),0) -> 0 | O110: =IF(B110="OPEN",IF(Y109=0,$C$7,IF(AND(C110>0,C110>=$C$5,$C$6>0),$C$6,0)),0) -> 0 | P110: =(N110+O110)*(1+$C$11) -> 0 | Q110: =D110-J110-IF(C110=0,0,Inputs!$B$18)-P110 -> 957.66102 | R110: =MAX(0,Q110-M110)*Inputs!$B$17 -> 0 | S110: =MAX(0,M110-MAX(0,Q110))+MAX(0,-Q110) -> 129497.31 | T110: =F110+D110+E110-L110-P110-R110 -> 139117.42 | U110: =IF(AND(Inputs!$B$79=1,B110="OPEN",A110>=Inputs!$B$82,C110>=$C$10,MOD(C110-$C$10,$C$9)=0),MIN(MAX(0,T110-$C$8)*Inputs!$B$81,MAX(0,H110+J110-K110)),0) -> 0 | V110: =IF(AND(Inputs!$B$79=1,B110="OPEN",A110>=Inputs!$B$82,C110>=$C$10,MOD(C110-$C$10,$C$9)=0),MIN(MAX(0,MAX(0,T110-$C$8)*Inputs!$B$81-U110),MAX(0,G110-I110)),0) -> 0 | W110: =MAX(0,G110-I110-V110) -> 240000 | X110: =MAX(0,H110+J110-K110-U110) -> 900000 | Y110: =W110+X110 -> 1140000 | Z110: =T110-U110-V110 -> 139117.42
A111: =A110+1 -> 10 | B111: {=INDEX('Monthly Base'!$B$5:$B$67,A111+1)} -> OPEN | C111: {=INDEX('Monthly Base'!$C$5:$C$67,A111+1)} -> 8 | D111: {=INDEX('Monthly Base'!$O$5:$O$67,A111+1)} -> 11325.432 | E111: {=INDEX('Monthly Base'!$Y$5:$Y$67,A111+1)} -> 0 | F111: =Z110 -> 139117.42 | G111: =W110 -> 240000 | H111: =X110 -> 900000 | I111: =IF(OR(A111<Inputs!$B$15,G111<=0),0,MIN(Financing!$B$10,G111)) -> 0 | J111: =IF(OR(A111<Inputs!$B$15,H111<=0),0,H111*Inputs!$B$13/12) -> 0 | K111: =IF(OR(A111<Inputs!$B$15,H111<=0),0,MIN(Financing!$C$10,H111+J111)) -> 0 | L111: =I111+K111 -> 0 | M111: =S110 -> 129497.31 | N111: =IF(B111="OPEN",IF(Y110=0,$C$7,IF(AND(C111>0,C111>=$C$5,$C$6>0),$C$6,0)),0) -> 0 | O111: =IF(B111="OPEN",IF(Y110=0,$C$7,IF(AND(C111>0,C111>=$C$5,$C$6>0),$C$6,0)),0) -> 0 | P111: =(N111+O111)*(1+$C$11) -> 0 | Q111: =D111-J111-IF(C111=0,0,Inputs!$B$18)-P111 -> 4512.4322 | R111: =MAX(0,Q111-M111)*Inputs!$B$17 -> 0 | S111: =MAX(0,M111-MAX(0,Q111))+MAX(0,-Q111) -> 124984.88 | T111: =F111+D111+E111-L111-P111-R111 -> 150442.85 | U111: =IF(AND(Inputs!$B$79=1,B111="OPEN",A111>=Inputs!$B$82,C111>=$C$10,MOD(C111-$C$10,$C$9)=0),MIN(MAX(0,T111-$C$8)*Inputs!$B$81,MAX(0,H111+J111-K111)),0) -> 0 | V111: =IF(AND(Inputs!$B$79=1,B111="OPEN",A111>=Inputs!$B$82,C111>=$C$10,MOD(C111-$C$10,$C$9)=0),MIN(MAX(0,MAX(0,T111-$C$8)*Inputs!$B$81-U111),MAX(0,G111-I111)),0) -> 0 | W111: =MAX(0,G111-I111-V111) -> 240000 | X111: =MAX(0,H111+J111-K111-U111) -> 900000 | Y111: =W111+X111 -> 1140000 | Z111: =T111-U111-V111 -> 150442.85
A112: =A111+1 -> 11 | B112: {=INDEX('Monthly Base'!$B$5:$B$67,A112+1)} -> OPEN | C112: {=INDEX('Monthly Base'!$C$5:$C$67,A112+1)} -> 9 | D112: {=INDEX('Monthly Base'!$O$5:$O$67,A112+1)} -> 14880.203 | E112: {=INDEX('Monthly Base'!$Y$5:$Y$67,A112+1)} -> 0 | F112: =Z111 -> 150442.85 | G112: =W111 -> 240000 | H112: =X111 -> 900000 | I112: =IF(OR(A112<Inputs!$B$15,G112<=0),0,MIN(Financing!$B$10,G112)) -> 0 | J112: =IF(OR(A112<Inputs!$B$15,H112<=0),0,H112*Inputs!$B$13/12) -> 0 | K112: =IF(OR(A112<Inputs!$B$15,H112<=0),0,MIN(Financing!$C$10,H112+J112)) -> 0 | L112: =I112+K112 -> 0 | M112: =S111 -> 124984.88 | N112: =IF(B112="OPEN",IF(Y111=0,$C$7,IF(AND(C112>0,C112>=$C$5,$C$6>0),$C$6,0)),0) -> 0 | O112: =IF(B112="OPEN",IF(Y111=0,$C$7,IF(AND(C112>0,C112>=$C$5,$C$6>0),$C$6,0)),0) -> 0 | P112: =(N112+O112)*(1+$C$11) -> 0 | Q112: =D112-J112-IF(C112=0,0,Inputs!$B$18)-P112 -> 8067.2034 | R112: =MAX(0,Q112-M112)*Inputs!$B$17 -> 0 | S112: =MAX(0,M112-MAX(0,Q112))+MAX(0,-Q112) -> 116917.68 | T112: =F112+D112+E112-L112-P112-R112 -> 165323.05 | U112: =IF(AND(Inputs!$B$79=1,B112="OPEN",A112>=Inputs!$B$82,C112>=$C$10,MOD(C112-$C$10,$C$9)=0),MIN(MAX(0,T112-$C$8)*Inputs!$B$81,MAX(0,H112+J112-K112)),0) -> 0 | V112: =IF(AND(Inputs!$B$79=1,B112="OPEN",A112>=Inputs!$B$82,C112>=$C$10,MOD(C112-$C$10,$C$9)=0),MIN(MAX(0,MAX(0,T112-$C$8)*Inputs!$B$81-U112),MAX(0,G112-I112)),0) -> 0 | W112: =MAX(0,G112-I112-V112) -> 240000 | X112: =MAX(0,H112+J112-K112-U112) -> 900000 | Y112: =W112+X112 -> 1140000 | Z112: =T112-U112-V112 -> 165323.05
A113: =A112+1 -> 12 | B113: {=INDEX('Monthly Base'!$B$5:$B$67,A113+1)} -> OPEN | C113: {=INDEX('Monthly Base'!$C$5:$C$67,A113+1)} -> 10 | D113: {=INDEX('Monthly Base'!$O$5:$O$67,A113+1)} -> 18434.975 | E113: {=INDEX('Monthly Base'!$Y$5:$Y$67,A113+1)} -> 0 | F113: =Z112 -> 165323.05 | G113: =W112 -> 240000 | H113: =X112 -> 900000 | I113: =IF(OR(A113<Inputs!$B$15,G113<=0),0,MIN(Financing!$B$10,G113)) -> 4000 | J113: =IF(OR(A113<Inputs!$B$15,H113<=0),0,H113*Inputs!$B$13/12) -> 3562.5 | K113: =IF(OR(A113<Inputs!$B$15,H113<=0),0,MIN(Financing!$C$10,H113+J113)) -> 16881.221 | L113: =I113+K113 -> 20881.221 | M113: =S112 -> 116917.68 | N113: =IF(B113="OPEN",IF(Y112=0,$C$7,IF(AND(C113>0,C113>=$C$5,$C$6>0),$C$6,0)),0) -> 0 | O113: =IF(B113="OPEN",IF(Y112=0,$C$7,IF(AND(C113>0,C113>=$C$5,$C$6>0),$C$6,0)),0) -> 0 | P113: =(N113+O113)*(1+$C$11) -> 0 | Q113: =D113-J113-IF(C113=0,0,Inputs!$B$18)-P113 -> 8059.4746 | R113: =MAX(0,Q113-M113)*Inputs!$B$17 -> 0 | S113: =MAX(0,M113-MAX(0,Q113))+MAX(0,-Q113) -> 108858.2 | T113: =F113+D113+E113-L113-P113-R113 -> 162876.81 | U113: =IF(AND(Inputs!$B$79=1,B113="OPEN",A113>=Inputs!$B$82,C113>=$C$10,MOD(C113-$C$10,$C$9)=0),MIN(MAX(0,T113-$C$8)*Inputs!$B$81,MAX(0,H113+J113-K113)),0) -> 0 | V113: =IF(AND(Inputs!$B$79=1,B113="OPEN",A113>=Inputs!$B$82,C113>=$C$10,MOD(C113-$C$10,$C$9)=0),MIN(MAX(0,MAX(0,T113-$C$8)*Inputs!$B$81-U113),MAX(0,G113-I113)),0) -> 0 | W113: =MAX(0,G113-I113-V113) -> 236000 | X113: =MAX(0,H113+J113-K113-U113) -> 886681.28 | Y113: =W113+X113 -> 1122681.3 | Z113: =T113-U113-V113 -> 162876.81
... A163: =A162+1 -> 62 | B163: {=INDEX('Monthly Base'!$B$5:$B$67,A163+1)} -> OPEN | C163: {=INDEX('Monthly Base'!$C$5:$C$67,A163+1)} -> 60 | D163: {=INDEX('Monthly Base'!$O$5:$O$67,A163+1)} -> 100568.9 | E163: {=INDEX('Monthly Base'!$Y$5:$Y$67,A163+1)} -> 0 | F163: =Z162 -> 1123682.7 | G163: =W162 -> 0 | H163: =X162 -> 0 | I163: =IF(OR(A163<Inputs!$B$15,G163<=0),0,MIN(Financing!$B$10,G163)) -> 0 | J163: =IF(OR(A163<Inputs!$B$15,H163<=0),0,H163*Inputs!$B$13/12) -> 0 | K163: =IF(OR(A163<Inputs!$B$15,H163<=0),0,MIN(Financing!$C$10,H163+J163)) -> 0 | L163: =I163+K163 -> 0 | M163: =S162 -> 0 | N163: =IF(B163="OPEN",IF(Y162=0,$C$7,IF(AND(C163>0,C163>=$C$5,$C$6>0),$C$6,0)),0) -> 10000 | O163: =IF(B163="OPEN",IF(Y162=0,$C$7,IF(AND(C163>0,C163>=$C$5,$C$6>0),$C$6,0)),0) -> 10000 | P163: =(N163+O163)*(1+$C$11) -> 24000 | Q163: =D163-J163-IF(C163=0,0,Inputs!$B$18)-P163 -> 69755.898 | R163: =MAX(0,Q163-M163)*Inputs!$B$17 -> 16043.857 | S163: =MAX(0,M163-MAX(0,Q163))+MAX(0,-Q163) -> 0 | T163: =F163+D163+E163-L163-P163-R163 -> 1184207.8 | U163: =IF(AND(Inputs!$B$79=1,B163="OPEN",A163>=Inputs!$B$82,C163>=$C$10,MOD(C163-$C$10,$C$9)=0),MIN(MAX(0,T163-$C$8)*Inputs!$B$81,MAX(0,H163+J163-K163)),0) -> 0 | V163: =IF(AND(Inputs!$B$79=1,B163="OPEN",A163>=Inputs!$B$82,C163>=$C$10,MOD(C163-$C$10,$C$9)=0),MIN(MAX(0,MAX(0,T163-$C$8)*Inputs!$B$81-U163),MAX(0,G163-I163)),0) -> 0 | W163: =MAX(0,G163-I163-V163) -> 0 | X163: =MAX(0,H163+J163-K163-U163) -> 0 | Y163: =W163+X163 -> 0 | Z163: =T163-U163-V163 -> 1184207.8
A170: Timeline Mo | B170: Phase | C170: Operating Mo | D170: EBITDA | E170: Build VAT Refund | F170: Opening Cash | G170: Loan A Opening | H170: Loan B Opening | I170: Loan A Scheduled | J170: Loan B Interest | K170: Loan B Scheduled | L170: Scheduled Debt | M170: Tax Loss CF Begin | N170: Partner 1 Gross | O170: Partner 2 Gross | P170: Owner Payroll Cost | Q170: Taxable Before Loss | R170: Corporate Tax | S170: Tax Loss CF End | T170: Cash Before Extra Debt | U170: Extra to Loan B | V170: Extra to Loan A | W170: Loan A Closing | X170: Loan B Closing | Y170: Total Debt | Z170: Ending Cash
A171: 0 | B171: {=INDEX('Monthly Base'!$B$5:$B$67,A171+1)} -> BUILD | C171: {=INDEX('Monthly Base'!$C$5:$C$67,A171+1)} -> 0 | D171: {=INDEX('Monthly Base'!$O$5:$O$67,A171+1)} -> -20018 | E171: {=INDEX('Monthly Base'!$Y$5:$Y$67,A171+1)} -> 0 | F171: ='Startup & Funding'!$B$19 -> 68990.001 | G171: =Inputs!$B$9 -> 240000 | H171: =Inputs!$B$10 -> 900000 | I171: =IF(OR(A171<Inputs!$B$15,G171<=0),0,MIN(Financing!$B$10,G171)) -> 0 | J171: =IF(OR(A171<Inputs!$B$15,H171<=0),0,H171*Inputs!$B$13/12) -> 0 | K171: =IF(OR(A171<Inputs!$B$15,H171<=0),0,MIN(Financing!$C$10,H171+J171)) -> 0 | L171: =I171+K171 -> 0 | M171: 0 | N171: 0 | O171: 0 | P171: =(N171+O171)*(1+$D$11) -> 0 | Q171: =D171-J171-IF(C171=0,0,Inputs!$B$18)-P171 -> -20018 | R171: =MAX(0,Q171-M171)*Inputs!$B$17 -> 0 | S171: =MAX(0,M171-MAX(0,Q171))+MAX(0,-Q171) -> 20018 | T171: =F171+D171+E171-L171-P171-R171 -> 48972.001 | U171: =IF(AND(Inputs!$B$79=1,B171="OPEN",A171>=Inputs!$B$82,C171>=$D$10,MOD(C171-$D$10,$D$9)=0),MIN(MAX(0,T171-$D$8)*Inputs!$B$81,MAX(0,H171+J171-K171)),0) -> 0 | V171: =IF(AND(Inputs!$B$79=1,B171="OPEN",A171>=Inputs!$B$82,C171>=$D$10,MOD(C171-$D$10,$D$9)=0),MIN(MAX(0,MAX(0,T171-$D$8)*Inputs!$B$81-U171),MAX(0,G171-I171)),0) -> 0 | W171: =MAX(0,G171-I171-V171) -> 240000 | X171: =MAX(0,H171+J171-K171-U171) -> 900000 | Y171: =W171+X171 -> 1140000 | Z171: =T171-U171-V171 -> 48972.001
A172: =A171+1 -> 1 | B172: {=INDEX('Monthly Base'!$B$5:$B$67,A172+1)} -> BUILD | C172: {=INDEX('Monthly Base'!$C$5:$C$67,A172+1)} -> 0 | D172: {=INDEX('Monthly Base'!$O$5:$O$67,A172+1)} -> -20018 | E172: {=INDEX('Monthly Base'!$Y$5:$Y$67,A172+1)} -> 0 | F172: =Z171 -> 48972.001 | G172: =W171 -> 240000 | H172: =X171 -> 900000 | I172: =IF(OR(A172<Inputs!$B$15,G172<=0),0,MIN(Financing!$B$10,G172)) -> 0 | J172: =IF(OR(A172<Inputs!$B$15,H172<=0),0,H172*Inputs!$B$13/12) -> 0 | K172: =IF(OR(A172<Inputs!$B$15,H172<=0),0,MIN(Financing!$C$10,H172+J172)) -> 0 | L172: =I172+K172 -> 0 | M172: =S171 -> 20018 | N172: =IF(B172="OPEN",IF(Y171=0,$D$7,IF(AND(C172>0,C172>=$D$5,$D$6>0),$D$6,0)),0) -> 0 | O172: =IF(B172="OPEN",IF(Y171=0,$D$7,IF(AND(C172>0,C172>=$D$5,$D$6>0),$D$6,0)),0) -> 0 | P172: =(N172+O172)*(1+$D$11) -> 0 | Q172: =D172-J172-IF(C172=0,0,Inputs!$B$18)-P172 -> -20018 | R172: =MAX(0,Q172-M172)*Inputs!$B$17 -> 0 | S172: =MAX(0,M172-MAX(0,Q172))+MAX(0,-Q172) -> 40036 | T172: =F172+D172+E172-L172-P172-R172 -> 28954.001 | U172: =IF(AND(Inputs!$B$79=1,B172="OPEN",A172>=Inputs!$B$82,C172>=$D$10,MOD(C172-$D$10,$D$9)=0),MIN(MAX(0,T172-$D$8)*Inputs!$B$81,MAX(0,H172+J172-K172)),0) -> 0 | V172: =IF(AND(Inputs!$B$79=1,B172="OPEN",A172>=Inputs!$B$82,C172>=$D$10,MOD(C172-$D$10,$D$9)=0),MIN(MAX(0,MAX(0,T172-$D$8)*Inputs!$B$81-U172),MAX(0,G172-I172)),0) -> 0 | W172: =MAX(0,G172-I172-V172) -> 240000 | X172: =MAX(0,H172+J172-K172-U172) -> 900000 | Y172: =W172+X172 -> 1140000 | Z172: =T172-U172-V172 -> 28954.001
A173: =A172+1 -> 2 | B173: {=INDEX('Monthly Base'!$B$5:$B$67,A173+1)} -> BUILD | C173: {=INDEX('Monthly Base'!$C$5:$C$67,A173+1)} -> 0 | D173: {=INDEX('Monthly Base'!$O$5:$O$67,A173+1)} -> -20018 | E173: {=INDEX('Monthly Base'!$Y$5:$Y$67,A173+1)} -> 151933.73 | F173: =Z172 -> 28954.001 | G173: =W172 -> 240000 | H173: =X172 -> 900000 | I173: =IF(OR(A173<Inputs!$B$15,G173<=0),0,MIN(Financing!$B$10,G173)) -> 0 | J173: =IF(OR(A173<Inputs!$B$15,H173<=0),0,H173*Inputs!$B$13/12) -> 0 | K173: =IF(OR(A173<Inputs!$B$15,H173<=0),0,MIN(Financing!$C$10,H173+J173)) -> 0 | L173: =I173+K173 -> 0 | M173: =S172 -> 40036 | N173: =IF(B173="OPEN",IF(Y172=0,$D$7,IF(AND(C173>0,C173>=$D$5,$D$6>0),$D$6,0)),0) -> 0 | O173: =IF(B173="OPEN",IF(Y172=0,$D$7,IF(AND(C173>0,C173>=$D$5,$D$6>0),$D$6,0)),0) -> 0 | P173: =(N173+O173)*(1+$D$11) -> 0 | Q173: =D173-J173-IF(C173=0,0,Inputs!$B$18)-P173 -> -20018 | R173: =MAX(0,Q173-M173)*Inputs!$B$17 -> 0 | S173: =MAX(0,M173-MAX(0,Q173))+MAX(0,-Q173) -> 60054 | T173: =F173+D173+E173-L173-P173-R173 -> 160869.73 | U173: =IF(AND(Inputs!$B$79=1,B173="OPEN",A173>=Inputs!$B$82,C173>=$D$10,MOD(C173-$D$10,$D$9)=0),MIN(MAX(0,T173-$D$8)*Inputs!$B$81,MAX(0,H173+J173-K173)),0) -> 0 | V173: =IF(AND(Inputs!$B$79=1,B173="OPEN",A173>=Inputs!$B$82,C173>=$D$10,MOD(C173-$D$10,$D$9)=0),MIN(MAX(0,MAX(0,T173-$D$8)*Inputs!$B$81-U173),MAX(0,G173-I173)),0) -> 0 | W173: =MAX(0,G173-I173-V173) -> 240000 | X173: =MAX(0,H173+J173-K173-U173) -> 900000 | Y173: =W173+X173 -> 1140000 | Z173: =T173-U173-V173 -> 160869.73
A174: =A173+1 -> 3 | B174: {=INDEX('Monthly Base'!$B$5:$B$67,A174+1)} -> OPEN | C174: {=INDEX('Monthly Base'!$C$5:$C$67,A174+1)} -> 1 | D174: {=INDEX('Monthly Base'!$O$5:$O$67,A174+1)} -> -13932.153 | E174: {=INDEX('Monthly Base'!$Y$5:$Y$67,A174+1)} -> 0 | F174: =Z173 -> 160869.73 | G174: =W173 -> 240000 | H174: =X173 -> 900000 | I174: =IF(OR(A174<Inputs!$B$15,G174<=0),0,MIN(Financing!$B$10,G174)) -> 0 | J174: =IF(OR(A174<Inputs!$B$15,H174<=0),0,H174*Inputs!$B$13/12) -> 0 | K174: =IF(OR(A174<Inputs!$B$15,H174<=0),0,MIN(Financing!$C$10,H174+J174)) -> 0 | L174: =I174+K174 -> 0 | M174: =S173 -> 60054 | N174: =IF(B174="OPEN",IF(Y173=0,$D$7,IF(AND(C174>0,C174>=$D$5,$D$6>0),$D$6,0)),0) -> 0 | O174: =IF(B174="OPEN",IF(Y173=0,$D$7,IF(AND(C174>0,C174>=$D$5,$D$6>0),$D$6,0)),0) -> 0 | P174: =(N174+O174)*(1+$D$11) -> 0 | Q174: =D174-J174-IF(C174=0,0,Inputs!$B$18)-P174 -> -20745.153 | R174: =MAX(0,Q174-M174)*Inputs!$B$17 -> 0 | S174: =MAX(0,M174-MAX(0,Q174))+MAX(0,-Q174) -> 80799.153 | T174: =F174+D174+E174-L174-P174-R174 -> 146937.58 | U174: =IF(AND(Inputs!$B$79=1,B174="OPEN",A174>=Inputs!$B$82,C174>=$D$10,MOD(C174-$D$10,$D$9)=0),MIN(MAX(0,T174-$D$8)*Inputs!$B$81,MAX(0,H174+J174-K174)),0) -> 0 | V174: =IF(AND(Inputs!$B$79=1,B174="OPEN",A174>=Inputs!$B$82,C174>=$D$10,MOD(C174-$D$10,$D$9)=0),MIN(MAX(0,MAX(0,T174-$D$8)*Inputs!$B$81-U174),MAX(0,G174-I174)),0) -> 0 | W174: =MAX(0,G174-I174-V174) -> 240000 | X174: =MAX(0,H174+J174-K174-U174) -> 900000 | Y174: =W174+X174 -> 1140000 | Z174: =T174-U174-V174 -> 146937.58
A175: =A174+1 -> 4 | B175: {=INDEX('Monthly Base'!$B$5:$B$67,A175+1)} -> OPEN | C175: {=INDEX('Monthly Base'!$C$5:$C$67,A175+1)} -> 2 | D175: {=INDEX('Monthly Base'!$O$5:$O$67,A175+1)} -> -10377.381 | E175: {=INDEX('Monthly Base'!$Y$5:$Y$67,A175+1)} -> 0 | F175: =Z174 -> 146937.58 | G175: =W174 -> 240000 | H175: =X174 -> 900000 | I175: =IF(OR(A175<Inputs!$B$15,G175<=0),0,MIN(Financing!$B$10,G175)) -> 0 | J175: =IF(OR(A175<Inputs!$B$15,H175<=0),0,H175*Inputs!$B$13/12) -> 0 | K175: =IF(OR(A175<Inputs!$B$15,H175<=0),0,MIN(Financing!$C$10,H175+J175)) -> 0 | L175: =I175+K175 -> 0 | M175: =S174 -> 80799.153 | N175: =IF(B175="OPEN",IF(Y174=0,$D$7,IF(AND(C175>0,C175>=$D$5,$D$6>0),$D$6,0)),0) -> 0 | O175: =IF(B175="OPEN",IF(Y174=0,$D$7,IF(AND(C175>0,C175>=$D$5,$D$6>0),$D$6,0)),0) -> 0 | P175: =(N175+O175)*(1+$D$11) -> 0 | Q175: =D175-J175-IF(C175=0,0,Inputs!$B$18)-P175 -> -17190.381 | R175: =MAX(0,Q175-M175)*Inputs!$B$17 -> 0 | S175: =MAX(0,M175-MAX(0,Q175))+MAX(0,-Q175) -> 97989.534 | T175: =F175+D175+E175-L175-P175-R175 -> 136560.2 | U175: =IF(AND(Inputs!$B$79=1,B175="OPEN",A175>=Inputs!$B$82,C175>=$D$10,MOD(C175-$D$10,$D$9)=0),MIN(MAX(0,T175-$D$8)*Inputs!$B$81,MAX(0,H175+J175-K175)),0) -> 0 | V175: =IF(AND(Inputs!$B$79=1,B175="OPEN",A175>=Inputs!$B$82,C175>=$D$10,MOD(C175-$D$10,$D$9)=0),MIN(MAX(0,MAX(0,T175-$D$8)*Inputs!$B$81-U175),MAX(0,G175-I175)),0) -> 0 | W175: =MAX(0,G175-I175-V175) -> 240000 | X175: =MAX(0,H175+J175-K175-U175) -> 900000 | Y175: =W175+X175 -> 1140000 | Z175: =T175-U175-V175 -> 136560.2
A176: =A175+1 -> 5 | B176: {=INDEX('Monthly Base'!$B$5:$B$67,A176+1)} -> OPEN | C176: {=INDEX('Monthly Base'!$C$5:$C$67,A176+1)} -> 3 | D176: {=INDEX('Monthly Base'!$O$5:$O$67,A176+1)} -> -6635.5169 | E176: {=INDEX('Monthly Base'!$Y$5:$Y$67,A176+1)} -> 0 | F176: =Z175 -> 136560.2 | G176: =W175 -> 240000 | H176: =X175 -> 900000 | I176: =IF(OR(A176<Inputs!$B$15,G176<=0),0,MIN(Financing!$B$10,G176)) -> 0 | J176: =IF(OR(A176<Inputs!$B$15,H176<=0),0,H176*Inputs!$B$13/12) -> 0 | K176: =IF(OR(A176<Inputs!$B$15,H176<=0),0,MIN(Financing!$C$10,H176+J176)) -> 0 | L176: =I176+K176 -> 0 | M176: =S175 -> 97989.534 | N176: =IF(B176="OPEN",IF(Y175=0,$D$7,IF(AND(C176>0,C176>=$D$5,$D$6>0),$D$6,0)),0) -> 0 | O176: =IF(B176="OPEN",IF(Y175=0,$D$7,IF(AND(C176>0,C176>=$D$5,$D$6>0),$D$6,0)),0) -> 0 | P176: =(N176+O176)*(1+$D$11) -> 0 | Q176: =D176-J176-IF(C176=0,0,Inputs!$B$18)-P176 -> -13448.517 | R176: =MAX(0,Q176-M176)*Inputs!$B$17 -> 0 | S176: =MAX(0,M176-MAX(0,Q176))+MAX(0,-Q176) -> 111438.05 | T176: =F176+D176+E176-L176-P176-R176 -> 129924.68 | U176: =IF(AND(Inputs!$B$79=1,B176="OPEN",A176>=Inputs!$B$82,C176>=$D$10,MOD(C176-$D$10,$D$9)=0),MIN(MAX(0,T176-$D$8)*Inputs!$B$81,MAX(0,H176+J176-K176)),0) -> 0 | V176: =IF(AND(Inputs!$B$79=1,B176="OPEN",A176>=Inputs!$B$82,C176>=$D$10,MOD(C176-$D$10,$D$9)=0),MIN(MAX(0,MAX(0,T176-$D$8)*Inputs!$B$81-U176),MAX(0,G176-I176)),0) -> 0 | W176: =MAX(0,G176-I176-V176) -> 240000 | X176: =MAX(0,H176+J176-K176-U176) -> 900000 | Y176: =W176+X176 -> 1140000 | Z176: =T176-U176-V176 -> 129924.68
A177: =A176+1 -> 6 | B177: {=INDEX('Monthly Base'!$B$5:$B$67,A177+1)} -> OPEN | C177: {=INDEX('Monthly Base'!$C$5:$C$67,A177+1)} -> 4 | D177: {=INDEX('Monthly Base'!$O$5:$O$67,A177+1)} -> -3080.7458 | E177: {=INDEX('Monthly Base'!$Y$5:$Y$67,A177+1)} -> 0 | F177: =Z176 -> 129924.68 | G177: =W176 -> 240000 | H177: =X176 -> 900000 | I177: =IF(OR(A177<Inputs!$B$15,G177<=0),0,MIN(Financing!$B$10,G177)) -> 0 | J177: =IF(OR(A177<Inputs!$B$15,H177<=0),0,H177*Inputs!$B$13/12) -> 0 | K177: =IF(OR(A177<Inputs!$B$15,H177<=0),0,MIN(Financing!$C$10,H177+J177)) -> 0 | L177: =I177+K177 -> 0 | M177: =S176 -> 111438.05 | N177: =IF(B177="OPEN",IF(Y176=0,$D$7,IF(AND(C177>0,C177>=$D$5,$D$6>0),$D$6,0)),0) -> 0 | O177: =IF(B177="OPEN",IF(Y176=0,$D$7,IF(AND(C177>0,C177>=$D$5,$D$6>0),$D$6,0)),0) -> 0 | P177: =(N177+O177)*(1+$D$11) -> 0 | Q177: =D177-J177-IF(C177=0,0,Inputs!$B$18)-P177 -> -9893.7458 | R177: =MAX(0,Q177-M177)*Inputs!$B$17 -> 0 | S177: =MAX(0,M177-MAX(0,Q177))+MAX(0,-Q177) -> 121331.8 | T177: =F177+D177+E177-L177-P177-R177 -> 126843.93 | U177: =IF(AND(Inputs!$B$79=1,B177="OPEN",A177>=Inputs!$B$82,C177>=$D$10,MOD(C177-$D$10,$D$9)=0),MIN(MAX(0,T177-$D$8)*Inputs!$B$81,MAX(0,H177+J177-K177)),0) -> 0 | V177: =IF(AND(Inputs!$B$79=1,B177="OPEN",A177>=Inputs!$B$82,C177>=$D$10,MOD(C177-$D$10,$D$9)=0),MIN(MAX(0,MAX(0,T177-$D$8)*Inputs!$B$81-U177),MAX(0,G177-I177)),0) -> 0 | W177: =MAX(0,G177-I177-V177) -> 240000 | X177: =MAX(0,H177+J177-K177-U177) -> 900000 | Y177: =W177+X177 -> 1140000 | Z177: =T177-U177-V177 -> 126843.93
A178: =A177+1 -> 7 | B178: {=INDEX('Monthly Base'!$B$5:$B$67,A178+1)} -> OPEN | C178: {=INDEX('Monthly Base'!$C$5:$C$67,A178+1)} -> 5 | D178: {=INDEX('Monthly Base'!$O$5:$O$67,A178+1)} -> 474.02542 | E178: {=INDEX('Monthly Base'!$Y$5:$Y$67,A178+1)} -> 0 | F178: =Z177 -> 126843.93 | G178: =W177 -> 240000 | H178: =X177 -> 900000 | I178: =IF(OR(A178<Inputs!$B$15,G178<=0),0,MIN(Financing!$B$10,G178)) -> 0 | J178: =IF(OR(A178<Inputs!$B$15,H178<=0),0,H178*Inputs!$B$13/12) -> 0 | K178: =IF(OR(A178<Inputs!$B$15,H178<=0),0,MIN(Financing!$C$10,H178+J178)) -> 0 | L178: =I178+K178 -> 0 | M178: =S177 -> 121331.8 | N178: =IF(B178="OPEN",IF(Y177=0,$D$7,IF(AND(C178>0,C178>=$D$5,$D$6>0),$D$6,0)),0) -> 0 | O178: =IF(B178="OPEN",IF(Y177=0,$D$7,IF(AND(C178>0,C178>=$D$5,$D$6>0),$D$6,0)),0) -> 0 | P178: =(N178+O178)*(1+$D$11) -> 0 | Q178: =D178-J178-IF(C178=0,0,Inputs!$B$18)-P178 -> -6338.9746 | R178: =MAX(0,Q178-M178)*Inputs!$B$17 -> 0 | S178: =MAX(0,M178-MAX(0,Q178))+MAX(0,-Q178) -> 127670.77 | T178: =F178+D178+E178-L178-P178-R178 -> 127317.96 | U178: =IF(AND(Inputs!$B$79=1,B178="OPEN",A178>=Inputs!$B$82,C178>=$D$10,MOD(C178-$D$10,$D$9)=0),MIN(MAX(0,T178-$D$8)*Inputs!$B$81,MAX(0,H178+J178-K178)),0) -> 0 | V178: =IF(AND(Inputs!$B$79=1,B178="OPEN",A178>=Inputs!$B$82,C178>=$D$10,MOD(C178-$D$10,$D$9)=0),MIN(MAX(0,MAX(0,T178-$D$8)*Inputs!$B$81-U178),MAX(0,G178-I178)),0) -> 0 | W178: =MAX(0,G178-I178-V178) -> 240000 | X178: =MAX(0,H178+J178-K178-U178) -> 900000 | Y178: =W178+X178 -> 1140000 | Z178: =T178-U178-V178 -> 127317.96
A179: =A178+1 -> 8 | B179: {=INDEX('Monthly Base'!$B$5:$B$67,A179+1)} -> OPEN | C179: {=INDEX('Monthly Base'!$C$5:$C$67,A179+1)} -> 6 | D179: {=INDEX('Monthly Base'!$O$5:$O$67,A179+1)} -> 4028.7966 | E179: {=INDEX('Monthly Base'!$Y$5:$Y$67,A179+1)} -> 0 | F179: =Z178 -> 127317.96 | G179: =W178 -> 240000 | H179: =X178 -> 900000 | I179: =IF(OR(A179<Inputs!$B$15,G179<=0),0,MIN(Financing!$B$10,G179)) -> 0 | J179: =IF(OR(A179<Inputs!$B$15,H179<=0),0,H179*Inputs!$B$13/12) -> 0 | K179: =IF(OR(A179<Inputs!$B$15,H179<=0),0,MIN(Financing!$C$10,H179+J179)) -> 0 | L179: =I179+K179 -> 0 | M179: =S178 -> 127670.77 | N179: =IF(B179="OPEN",IF(Y178=0,$D$7,IF(AND(C179>0,C179>=$D$5,$D$6>0),$D$6,0)),0) -> 0 | O179: =IF(B179="OPEN",IF(Y178=0,$D$7,IF(AND(C179>0,C179>=$D$5,$D$6>0),$D$6,0)),0) -> 0 | P179: =(N179+O179)*(1+$D$11) -> 0 | Q179: =D179-J179-IF(C179=0,0,Inputs!$B$18)-P179 -> -2784.2034 | R179: =MAX(0,Q179-M179)*Inputs!$B$17 -> 0 | S179: =MAX(0,M179-MAX(0,Q179))+MAX(0,-Q179) -> 130454.97 | T179: =F179+D179+E179-L179-P179-R179 -> 131346.76 | U179: =IF(AND(Inputs!$B$79=1,B179="OPEN",A179>=Inputs!$B$82,C179>=$D$10,MOD(C179-$D$10,$D$9)=0),MIN(MAX(0,T179-$D$8)*Inputs!$B$81,MAX(0,H179+J179-K179)),0) -> 0 | V179: =IF(AND(Inputs!$B$79=1,B179="OPEN",A179>=Inputs!$B$82,C179>=$D$10,MOD(C179-$D$10,$D$9)=0),MIN(MAX(0,MAX(0,T179-$D$8)*Inputs!$B$81-U179),MAX(0,G179-I179)),0) -> 0 | W179: =MAX(0,G179-I179-V179) -> 240000 | X179: =MAX(0,H179+J179-K179-U179) -> 900000 | Y179: =W179+X179 -> 1140000 | Z179: =T179-U179-V179 -> 131346.76
A180: =A179+1 -> 9 | B180: {=INDEX('Monthly Base'!$B$5:$B$67,A180+1)} -> OPEN | C180: {=INDEX('Monthly Base'!$C$5:$C$67,A180+1)} -> 7 | D180: {=INDEX('Monthly Base'!$O$5:$O$67,A180+1)} -> 7770.661 | E180: {=INDEX('Monthly Base'!$Y$5:$Y$67,A180+1)} -> 0 | F180: =Z179 -> 131346.76 | G180: =W179 -> 240000 | H180: =X179 -> 900000 | I180: =IF(OR(A180<Inputs!$B$15,G180<=0),0,MIN(Financing!$B$10,G180)) -> 0 | J180: =IF(OR(A180<Inputs!$B$15,H180<=0),0,H180*Inputs!$B$13/12) -> 0 | K180: =IF(OR(A180<Inputs!$B$15,H180<=0),0,MIN(Financing!$C$10,H180+J180)) -> 0 | L180: =I180+K180 -> 0 | M180: =S179 -> 130454.97 | N180: =IF(B180="OPEN",IF(Y179=0,$D$7,IF(AND(C180>0,C180>=$D$5,$D$6>0),$D$6,0)),0) -> 10000 | O180: =IF(B180="OPEN",IF(Y179=0,$D$7,IF(AND(C180>0,C180>=$D$5,$D$6>0),$D$6,0)),0) -> 10000 | P180: =(N180+O180)*(1+$D$11) -> 24000 | Q180: =D180-J180-IF(C180=0,0,Inputs!$B$18)-P180 -> -23042.339 | R180: =MAX(0,Q180-M180)*Inputs!$B$17 -> 0 | S180: =MAX(0,M180-MAX(0,Q180))+MAX(0,-Q180) -> 153497.31 | T180: =F180+D180+E180-L180-P180-R180 -> 115117.42 | U180: =IF(AND(Inputs!$B$79=1,B180="OPEN",A180>=Inputs!$B$82,C180>=$D$10,MOD(C180-$D$10,$D$9)=0),MIN(MAX(0,T180-$D$8)*Inputs!$B$81,MAX(0,H180+J180-K180)),0) -> 0 | V180: =IF(AND(Inputs!$B$79=1,B180="OPEN",A180>=Inputs!$B$82,C180>=$D$10,MOD(C180-$D$10,$D$9)=0),MIN(MAX(0,MAX(0,T180-$D$8)*Inputs!$B$81-U180),MAX(0,G180-I180)),0) -> 0 | W180: =MAX(0,G180-I180-V180) -> 240000 | X180: =MAX(0,H180+J180-K180-U180) -> 900000 | Y180: =W180+X180 -> 1140000 | Z180: =T180-U180-V180 -> 115117.42
A181: =A180+1 -> 10 | B181: {=INDEX('Monthly Base'!$B$5:$B$67,A181+1)} -> OPEN | C181: {=INDEX('Monthly Base'!$C$5:$C$67,A181+1)} -> 8 | D181: {=INDEX('Monthly Base'!$O$5:$O$67,A181+1)} -> 11325.432 | E181: {=INDEX('Monthly Base'!$Y$5:$Y$67,A181+1)} -> 0 | F181: =Z180 -> 115117.42 | G181: =W180 -> 240000 | H181: =X180 -> 900000 | I181: =IF(OR(A181<Inputs!$B$15,G181<=0),0,MIN(Financing!$B$10,G181)) -> 0 | J181: =IF(OR(A181<Inputs!$B$15,H181<=0),0,H181*Inputs!$B$13/12) -> 0 | K181: =IF(OR(A181<Inputs!$B$15,H181<=0),0,MIN(Financing!$C$10,H181+J181)) -> 0 | L181: =I181+K181 -> 0 | M181: =S180 -> 153497.31 | N181: =IF(B181="OPEN",IF(Y180=0,$D$7,IF(AND(C181>0,C181>=$D$5,$D$6>0),$D$6,0)),0) -> 10000 | O181: =IF(B181="OPEN",IF(Y180=0,$D$7,IF(AND(C181>0,C181>=$D$5,$D$6>0),$D$6,0)),0) -> 10000 | P181: =(N181+O181)*(1+$D$11) -> 24000 | Q181: =D181-J181-IF(C181=0,0,Inputs!$B$18)-P181 -> -19487.568 | R181: =MAX(0,Q181-M181)*Inputs!$B$17 -> 0 | S181: =MAX(0,M181-MAX(0,Q181))+MAX(0,-Q181) -> 172984.88 | T181: =F181+D181+E181-L181-P181-R181 -> 102442.85 | U181: =IF(AND(Inputs!$B$79=1,B181="OPEN",A181>=Inputs!$B$82,C181>=$D$10,MOD(C181-$D$10,$D$9)=0),MIN(MAX(0,T181-$D$8)*Inputs!$B$81,MAX(0,H181+J181-K181)),0) -> 0 | V181: =IF(AND(Inputs!$B$79=1,B181="OPEN",A181>=Inputs!$B$82,C181>=$D$10,MOD(C181-$D$10,$D$9)=0),MIN(MAX(0,MAX(0,T181-$D$8)*Inputs!$B$81-U181),MAX(0,G181-I181)),0) -> 0 | W181: =MAX(0,G181-I181-V181) -> 240000 | X181: =MAX(0,H181+J181-K181-U181) -> 900000 | Y181: =W181+X181 -> 1140000 | Z181: =T181-U181-V181 -> 102442.85
A182: =A181+1 -> 11 | B182: {=INDEX('Monthly Base'!$B$5:$B$67,A182+1)} -> OPEN | C182: {=INDEX('Monthly Base'!$C$5:$C$67,A182+1)} -> 9 | D182: {=INDEX('Monthly Base'!$O$5:$O$67,A182+1)} -> 14880.203 | E182: {=INDEX('Monthly Base'!$Y$5:$Y$67,A182+1)} -> 0 | F182: =Z181 -> 102442.85 | G182: =W181 -> 240000 | H182: =X181 -> 900000 | I182: =IF(OR(A182<Inputs!$B$15,G182<=0),0,MIN(Financing!$B$10,G182)) -> 0 | J182: =IF(OR(A182<Inputs!$B$15,H182<=0),0,H182*Inputs!$B$13/12) -> 0 | K182: =IF(OR(A182<Inputs!$B$15,H182<=0),0,MIN(Financing!$C$10,H182+J182)) -> 0 | L182: =I182+K182 -> 0 | M182: =S181 -> 172984.88 | N182: =IF(B182="OPEN",IF(Y181=0,$D$7,IF(AND(C182>0,C182>=$D$5,$D$6>0),$D$6,0)),0) -> 10000 | O182: =IF(B182="OPEN",IF(Y181=0,$D$7,IF(AND(C182>0,C182>=$D$5,$D$6>0),$D$6,0)),0) -> 10000 | P182: =(N182+O182)*(1+$D$11) -> 24000 | Q182: =D182-J182-IF(C182=0,0,Inputs!$B$18)-P182 -> -15932.797 | R182: =MAX(0,Q182-M182)*Inputs!$B$17 -> 0 | S182: =MAX(0,M182-MAX(0,Q182))+MAX(0,-Q182) -> 188917.68 | T182: =F182+D182+E182-L182-P182-R182 -> 93323.052 | U182: =IF(AND(Inputs!$B$79=1,B182="OPEN",A182>=Inputs!$B$82,C182>=$D$10,MOD(C182-$D$10,$D$9)=0),MIN(MAX(0,T182-$D$8)*Inputs!$B$81,MAX(0,H182+J182-K182)),0) -> 0 | V182: =IF(AND(Inputs!$B$79=1,B182="OPEN",A182>=Inputs!$B$82,C182>=$D$10,MOD(C182-$D$10,$D$9)=0),MIN(MAX(0,MAX(0,T182-$D$8)*Inputs!$B$81-U182),MAX(0,G182-I182)),0) -> 0 | W182: =MAX(0,G182-I182-V182) -> 240000 | X182: =MAX(0,H182+J182-K182-U182) -> 900000 | Y182: =W182+X182 -> 1140000 | Z182: =T182-U182-V182 -> 93323.052
A183: =A182+1 -> 12 | B183: {=INDEX('Monthly Base'!$B$5:$B$67,A183+1)} -> OPEN | C183: {=INDEX('Monthly Base'!$C$5:$C$67,A183+1)} -> 10 | D183: {=INDEX('Monthly Base'!$O$5:$O$67,A183+1)} -> 18434.975 | E183: {=INDEX('Monthly Base'!$Y$5:$Y$67,A183+1)} -> 0 | F183: =Z182 -> 93323.052 | G183: =W182 -> 240000 | H183: =X182 -> 900000 | I183: =IF(OR(A183<Inputs!$B$15,G183<=0),0,MIN(Financing!$B$10,G183)) -> 4000 | J183: =IF(OR(A183<Inputs!$B$15,H183<=0),0,H183*Inputs!$B$13/12) -> 3562.5 | K183: =IF(OR(A183<Inputs!$B$15,H183<=0),0,MIN(Financing!$C$10,H183+J183)) -> 16881.221 | L183: =I183+K183 -> 20881.221 | M183: =S182 -> 188917.68 | N183: =IF(B183="OPEN",IF(Y182=0,$D$7,IF(AND(C183>0,C183>=$D$5,$D$6>0),$D$6,0)),0) -> 10000 | O183: =IF(B183="OPEN",IF(Y182=0,$D$7,IF(AND(C183>0,C183>=$D$5,$D$6>0),$D$6,0)),0) -> 10000 | P183: =(N183+O183)*(1+$D$11) -> 24000 | Q183: =D183-J183-IF(C183=0,0,Inputs!$B$18)-P183 -> -15940.525 | R183: =MAX(0,Q183-M183)*Inputs!$B$17 -> 0 | S183: =MAX(0,M183-MAX(0,Q183))+MAX(0,-Q183) -> 204858.2 | T183: =F183+D183+E183-L183-P183-R183 -> 66876.806 | U183: =IF(AND(Inputs!$B$79=1,B183="OPEN",A183>=Inputs!$B$82,C183>=$D$10,MOD(C183-$D$10,$D$9)=0),MIN(MAX(0,T183-$D$8)*Inputs!$B$81,MAX(0,H183+J183-K183)),0) -> 0 | V183: =IF(AND(Inputs!$B$79=1,B183="OPEN",A183>=Inputs!$B$82,C183>=$D$10,MOD(C183-$D$10,$D$9)=0),MIN(MAX(0,MAX(0,T183-$D$8)*Inputs!$B$81-U183),MAX(0,G183-I183)),0) -> 0 | W183: =MAX(0,G183-I183-V183) -> 236000 | X183: =MAX(0,H183+J183-K183-U183) -> 886681.28 | Y183: =W183+X183 -> 1122681.3 | Z183: =T183-U183-V183 -> 66876.806
... A233: =A232+1 -> 62 | B233: {=INDEX('Monthly Base'!$B$5:$B$67,A233+1)} -> OPEN | C233: {=INDEX('Monthly Base'!$C$5:$C$67,A233+1)} -> 60 | D233: {=INDEX('Monthly Base'!$O$5:$O$67,A233+1)} -> 100568.9 | E233: {=INDEX('Monthly Base'!$Y$5:$Y$67,A233+1)} -> 0 | F233: =Z232 -> 719471.63 | G233: =W232 -> 0 | H233: =X232 -> 0 | I233: =IF(OR(A233<Inputs!$B$15,G233<=0),0,MIN(Financing!$B$10,G233)) -> 0 | J233: =IF(OR(A233<Inputs!$B$15,H233<=0),0,H233*Inputs!$B$13/12) -> 0 | K233: =IF(OR(A233<Inputs!$B$15,H233<=0),0,MIN(Financing!$C$10,H233+J233)) -> 0 | L233: =I233+K233 -> 0 | M233: =S232 -> 0 | N233: =IF(B233="OPEN",IF(Y232=0,$D$7,IF(AND(C233>0,C233>=$D$5,$D$6>0),$D$6,0)),0) -> 10000 | O233: =IF(B233="OPEN",IF(Y232=0,$D$7,IF(AND(C233>0,C233>=$D$5,$D$6>0),$D$6,0)),0) -> 10000 | P233: =(N233+O233)*(1+$D$11) -> 24000 | Q233: =D233-J233-IF(C233=0,0,Inputs!$B$18)-P233 -> 69755.898 | R233: =MAX(0,Q233-M233)*Inputs!$B$17 -> 16043.857 | S233: =MAX(0,M233-MAX(0,Q233))+MAX(0,-Q233) -> 0 | T233: =F233+D233+E233-L233-P233-R233 -> 779996.67 | U233: =IF(AND(Inputs!$B$79=1,B233="OPEN",A233>=Inputs!$B$82,C233>=$D$10,MOD(C233-$D$10,$D$9)=0),MIN(MAX(0,T233-$D$8)*Inputs!$B$81,MAX(0,H233+J233-K233)),0) -> 0 | V233: =IF(AND(Inputs!$B$79=1,B233="OPEN",A233>=Inputs!$B$82,C233>=$D$10,MOD(C233-$D$10,$D$9)=0),MIN(MAX(0,MAX(0,T233-$D$8)*Inputs!$B$81-U233),MAX(0,G233-I233)),0) -> 0 | W233: =MAX(0,G233-I233-V233) -> 0 | X233: =MAX(0,H233+J233-K233-U233) -> 0 | Y233: =W233+X233 -> 0 | Z233: =T233-U233-V233 -> 779996.67
A240: Timeline Mo | B240: Phase | C240: Operating Mo | D240: EBITDA | E240: Build VAT Refund | F240: Opening Cash | G240: Loan A Opening | H240: Loan B Opening | I240: Loan A Scheduled | J240: Loan B Interest | K240: Loan B Scheduled | L240: Scheduled Debt | M240: Tax Loss CF Begin | N240: Partner 1 Gross | O240: Partner 2 Gross | P240: Owner Payroll Cost | Q240: Taxable Before Loss | R240: Corporate Tax | S240: Tax Loss CF End | T240: Cash Before Extra Debt | U240: Extra to Loan B | V240: Extra to Loan A | W240: Loan A Closing | X240: Loan B Closing | Y240: Total Debt | Z240: Ending Cash
A241: 0 | B241: {=INDEX('Monthly Base'!$B$5:$B$67,A241+1)} -> BUILD | C241: {=INDEX('Monthly Base'!$C$5:$C$67,A241+1)} -> 0 | D241: {=INDEX('Monthly Base'!$O$5:$O$67,A241+1)} -> -20018 | E241: {=INDEX('Monthly Base'!$Y$5:$Y$67,A241+1)} -> 0 | F241: ='Startup & Funding'!$B$19 -> 68990.001 | G241: =Inputs!$B$9 -> 240000 | H241: =Inputs!$B$10 -> 900000 | I241: =IF(OR(A241<Inputs!$B$15,G241<=0),0,MIN(Financing!$B$10,G241)) -> 0 | J241: =IF(OR(A241<Inputs!$B$15,H241<=0),0,H241*Inputs!$B$13/12) -> 0 | K241: =IF(OR(A241<Inputs!$B$15,H241<=0),0,MIN(Financing!$C$10,H241+J241)) -> 0 | L241: =I241+K241 -> 0 | M241: 0 | N241: 0 | O241: 0 | P241: =(N241+O241)*(1+$E$11) -> 0 | Q241: =D241-J241-IF(C241=0,0,Inputs!$B$18)-P241 -> -20018 | R241: =MAX(0,Q241-M241)*Inputs!$B$17 -> 0 | S241: =MAX(0,M241-MAX(0,Q241))+MAX(0,-Q241) -> 20018 | T241: =F241+D241+E241-L241-P241-R241 -> 48972.001 | U241: =IF(AND(Inputs!$B$79=1,B241="OPEN",A241>=Inputs!$B$82,C241>=$E$10,MOD(C241-$E$10,$E$9)=0),MIN(MAX(0,T241-$E$8)*Inputs!$B$81,MAX(0,H241+J241-K241)),0) -> 0 | V241: =IF(AND(Inputs!$B$79=1,B241="OPEN",A241>=Inputs!$B$82,C241>=$E$10,MOD(C241-$E$10,$E$9)=0),MIN(MAX(0,MAX(0,T241-$E$8)*Inputs!$B$81-U241),MAX(0,G241-I241)),0) -> 0 | W241: =MAX(0,G241-I241-V241) -> 240000 | X241: =MAX(0,H241+J241-K241-U241) -> 900000 | Y241: =W241+X241 -> 1140000 | Z241: =T241-U241-V241 -> 48972.001
A242: =A241+1 -> 1 | B242: {=INDEX('Monthly Base'!$B$5:$B$67,A242+1)} -> BUILD | C242: {=INDEX('Monthly Base'!$C$5:$C$67,A242+1)} -> 0 | D242: {=INDEX('Monthly Base'!$O$5:$O$67,A242+1)} -> -20018 | E242: {=INDEX('Monthly Base'!$Y$5:$Y$67,A242+1)} -> 0 | F242: =Z241 -> 48972.001 | G242: =W241 -> 240000 | H242: =X241 -> 900000 | I242: =IF(OR(A242<Inputs!$B$15,G242<=0),0,MIN(Financing!$B$10,G242)) -> 0 | J242: =IF(OR(A242<Inputs!$B$15,H242<=0),0,H242*Inputs!$B$13/12) -> 0 | K242: =IF(OR(A242<Inputs!$B$15,H242<=0),0,MIN(Financing!$C$10,H242+J242)) -> 0 | L242: =I242+K242 -> 0 | M242: =S241 -> 20018 | N242: =IF(B242="OPEN",IF(Y241=0,$E$7,IF(AND(C242>0,C242>=$E$5,$E$6>0),$E$6,0)),0) -> 0 | O242: =IF(B242="OPEN",IF(Y241=0,$E$7,IF(AND(C242>0,C242>=$E$5,$E$6>0),$E$6,0)),0) -> 0 | P242: =(N242+O242)*(1+$E$11) -> 0 | Q242: =D242-J242-IF(C242=0,0,Inputs!$B$18)-P242 -> -20018 | R242: =MAX(0,Q242-M242)*Inputs!$B$17 -> 0 | S242: =MAX(0,M242-MAX(0,Q242))+MAX(0,-Q242) -> 40036 | T242: =F242+D242+E242-L242-P242-R242 -> 28954.001 | U242: =IF(AND(Inputs!$B$79=1,B242="OPEN",A242>=Inputs!$B$82,C242>=$E$10,MOD(C242-$E$10,$E$9)=0),MIN(MAX(0,T242-$E$8)*Inputs!$B$81,MAX(0,H242+J242-K242)),0) -> 0 | V242: =IF(AND(Inputs!$B$79=1,B242="OPEN",A242>=Inputs!$B$82,C242>=$E$10,MOD(C242-$E$10,$E$9)=0),MIN(MAX(0,MAX(0,T242-$E$8)*Inputs!$B$81-U242),MAX(0,G242-I242)),0) -> 0 | W242: =MAX(0,G242-I242-V242) -> 240000 | X242: =MAX(0,H242+J242-K242-U242) -> 900000 | Y242: =W242+X242 -> 1140000 | Z242: =T242-U242-V242 -> 28954.001
A243: =A242+1 -> 2 | B243: {=INDEX('Monthly Base'!$B$5:$B$67,A243+1)} -> BUILD | C243: {=INDEX('Monthly Base'!$C$5:$C$67,A243+1)} -> 0 | D243: {=INDEX('Monthly Base'!$O$5:$O$67,A243+1)} -> -20018 | E243: {=INDEX('Monthly Base'!$Y$5:$Y$67,A243+1)} -> 151933.73 | F243: =Z242 -> 28954.001 | G243: =W242 -> 240000 | H243: =X242 -> 900000 | I243: =IF(OR(A243<Inputs!$B$15,G243<=0),0,MIN(Financing!$B$10,G243)) -> 0 | J243: =IF(OR(A243<Inputs!$B$15,H243<=0),0,H243*Inputs!$B$13/12) -> 0 | K243: =IF(OR(A243<Inputs!$B$15,H243<=0),0,MIN(Financing!$C$10,H243+J243)) -> 0 | L243: =I243+K243 -> 0 | M243: =S242 -> 40036 | N243: =IF(B243="OPEN",IF(Y242=0,$E$7,IF(AND(C243>0,C243>=$E$5,$E$6>0),$E$6,0)),0) -> 0 | O243: =IF(B243="OPEN",IF(Y242=0,$E$7,IF(AND(C243>0,C243>=$E$5,$E$6>0),$E$6,0)),0) -> 0 | P243: =(N243+O243)*(1+$E$11) -> 0 | Q243: =D243-J243-IF(C243=0,0,Inputs!$B$18)-P243 -> -20018 | R243: =MAX(0,Q243-M243)*Inputs!$B$17 -> 0 | S243: =MAX(0,M243-MAX(0,Q243))+MAX(0,-Q243) -> 60054 | T243: =F243+D243+E243-L243-P243-R243 -> 160869.73 | U243: =IF(AND(Inputs!$B$79=1,B243="OPEN",A243>=Inputs!$B$82,C243>=$E$10,MOD(C243-$E$10,$E$9)=0),MIN(MAX(0,T243-$E$8)*Inputs!$B$81,MAX(0,H243+J243-K243)),0) -> 0 | V243: =IF(AND(Inputs!$B$79=1,B243="OPEN",A243>=Inputs!$B$82,C243>=$E$10,MOD(C243-$E$10,$E$9)=0),MIN(MAX(0,MAX(0,T243-$E$8)*Inputs!$B$81-U243),MAX(0,G243-I243)),0) -> 0 | W243: =MAX(0,G243-I243-V243) -> 240000 | X243: =MAX(0,H243+J243-K243-U243) -> 900000 | Y243: =W243+X243 -> 1140000 | Z243: =T243-U243-V243 -> 160869.73
A244: =A243+1 -> 3 | B244: {=INDEX('Monthly Base'!$B$5:$B$67,A244+1)} -> OPEN | C244: {=INDEX('Monthly Base'!$C$5:$C$67,A244+1)} -> 1 | D244: {=INDEX('Monthly Base'!$O$5:$O$67,A244+1)} -> -13932.153 | E244: {=INDEX('Monthly Base'!$Y$5:$Y$67,A244+1)} -> 0 | F244: =Z243 -> 160869.73 | G244: =W243 -> 240000 | H244: =X243 -> 900000 | I244: =IF(OR(A244<Inputs!$B$15,G244<=0),0,MIN(Financing!$B$10,G244)) -> 0 | J244: =IF(OR(A244<Inputs!$B$15,H244<=0),0,H244*Inputs!$B$13/12) -> 0 | K244: =IF(OR(A244<Inputs!$B$15,H244<=0),0,MIN(Financing!$C$10,H244+J244)) -> 0 | L244: =I244+K244 -> 0 | M244: =S243 -> 60054 | N244: =IF(B244="OPEN",IF(Y243=0,$E$7,IF(AND(C244>0,C244>=$E$5,$E$6>0),$E$6,0)),0) -> 0 | O244: =IF(B244="OPEN",IF(Y243=0,$E$7,IF(AND(C244>0,C244>=$E$5,$E$6>0),$E$6,0)),0) -> 0 | P244: =(N244+O244)*(1+$E$11) -> 0 | Q244: =D244-J244-IF(C244=0,0,Inputs!$B$18)-P244 -> -20745.153 | R244: =MAX(0,Q244-M244)*Inputs!$B$17 -> 0 | S244: =MAX(0,M244-MAX(0,Q244))+MAX(0,-Q244) -> 80799.153 | T244: =F244+D244+E244-L244-P244-R244 -> 146937.58 | U244: =IF(AND(Inputs!$B$79=1,B244="OPEN",A244>=Inputs!$B$82,C244>=$E$10,MOD(C244-$E$10,$E$9)=0),MIN(MAX(0,T244-$E$8)*Inputs!$B$81,MAX(0,H244+J244-K244)),0) -> 0 | V244: =IF(AND(Inputs!$B$79=1,B244="OPEN",A244>=Inputs!$B$82,C244>=$E$10,MOD(C244-$E$10,$E$9)=0),MIN(MAX(0,MAX(0,T244-$E$8)*Inputs!$B$81-U244),MAX(0,G244-I244)),0) -> 0 | W244: =MAX(0,G244-I244-V244) -> 240000 | X244: =MAX(0,H244+J244-K244-U244) -> 900000 | Y244: =W244+X244 -> 1140000 | Z244: =T244-U244-V244 -> 146937.58
A245: =A244+1 -> 4 | B245: {=INDEX('Monthly Base'!$B$5:$B$67,A245+1)} -> OPEN | C245: {=INDEX('Monthly Base'!$C$5:$C$67,A245+1)} -> 2 | D245: {=INDEX('Monthly Base'!$O$5:$O$67,A245+1)} -> -10377.381 | E245: {=INDEX('Monthly Base'!$Y$5:$Y$67,A245+1)} -> 0 | F245: =Z244 -> 146937.58 | G245: =W244 -> 240000 | H245: =X244 -> 900000 | I245: =IF(OR(A245<Inputs!$B$15,G245<=0),0,MIN(Financing!$B$10,G245)) -> 0 | J245: =IF(OR(A245<Inputs!$B$15,H245<=0),0,H245*Inputs!$B$13/12) -> 0 | K245: =IF(OR(A245<Inputs!$B$15,H245<=0),0,MIN(Financing!$C$10,H245+J245)) -> 0 | L245: =I245+K245 -> 0 | M245: =S244 -> 80799.153 | N245: =IF(B245="OPEN",IF(Y244=0,$E$7,IF(AND(C245>0,C245>=$E$5,$E$6>0),$E$6,0)),0) -> 0 | O245: =IF(B245="OPEN",IF(Y244=0,$E$7,IF(AND(C245>0,C245>=$E$5,$E$6>0),$E$6,0)),0) -> 0 | P245: =(N245+O245)*(1+$E$11) -> 0 | Q245: =D245-J245-IF(C245=0,0,Inputs!$B$18)-P245 -> -17190.381 | R245: =MAX(0,Q245-M245)*Inputs!$B$17 -> 0 | S245: =MAX(0,M245-MAX(0,Q245))+MAX(0,-Q245) -> 97989.534 | T245: =F245+D245+E245-L245-P245-R245 -> 136560.2 | U245: =IF(AND(Inputs!$B$79=1,B245="OPEN",A245>=Inputs!$B$82,C245>=$E$10,MOD(C245-$E$10,$E$9)=0),MIN(MAX(0,T245-$E$8)*Inputs!$B$81,MAX(0,H245+J245-K245)),0) -> 0 | V245: =IF(AND(Inputs!$B$79=1,B245="OPEN",A245>=Inputs!$B$82,C245>=$E$10,MOD(C245-$E$10,$E$9)=0),MIN(MAX(0,MAX(0,T245-$E$8)*Inputs!$B$81-U245),MAX(0,G245-I245)),0) -> 0 | W245: =MAX(0,G245-I245-V245) -> 240000 | X245: =MAX(0,H245+J245-K245-U245) -> 900000 | Y245: =W245+X245 -> 1140000 | Z245: =T245-U245-V245 -> 136560.2
A246: =A245+1 -> 5 | B246: {=INDEX('Monthly Base'!$B$5:$B$67,A246+1)} -> OPEN | C246: {=INDEX('Monthly Base'!$C$5:$C$67,A246+1)} -> 3 | D246: {=INDEX('Monthly Base'!$O$5:$O$67,A246+1)} -> -6635.5169 | E246: {=INDEX('Monthly Base'!$Y$5:$Y$67,A246+1)} -> 0 | F246: =Z245 -> 136560.2 | G246: =W245 -> 240000 | H246: =X245 -> 900000 | I246: =IF(OR(A246<Inputs!$B$15,G246<=0),0,MIN(Financing!$B$10,G246)) -> 0 | J246: =IF(OR(A246<Inputs!$B$15,H246<=0),0,H246*Inputs!$B$13/12) -> 0 | K246: =IF(OR(A246<Inputs!$B$15,H246<=0),0,MIN(Financing!$C$10,H246+J246)) -> 0 | L246: =I246+K246 -> 0 | M246: =S245 -> 97989.534 | N246: =IF(B246="OPEN",IF(Y245=0,$E$7,IF(AND(C246>0,C246>=$E$5,$E$6>0),$E$6,0)),0) -> 0 | O246: =IF(B246="OPEN",IF(Y245=0,$E$7,IF(AND(C246>0,C246>=$E$5,$E$6>0),$E$6,0)),0) -> 0 | P246: =(N246+O246)*(1+$E$11) -> 0 | Q246: =D246-J246-IF(C246=0,0,Inputs!$B$18)-P246 -> -13448.517 | R246: =MAX(0,Q246-M246)*Inputs!$B$17 -> 0 | S246: =MAX(0,M246-MAX(0,Q246))+MAX(0,-Q246) -> 111438.05 | T246: =F246+D246+E246-L246-P246-R246 -> 129924.68 | U246: =IF(AND(Inputs!$B$79=1,B246="OPEN",A246>=Inputs!$B$82,C246>=$E$10,MOD(C246-$E$10,$E$9)=0),MIN(MAX(0,T246-$E$8)*Inputs!$B$81,MAX(0,H246+J246-K246)),0) -> 0 | V246: =IF(AND(Inputs!$B$79=1,B246="OPEN",A246>=Inputs!$B$82,C246>=$E$10,MOD(C246-$E$10,$E$9)=0),MIN(MAX(0,MAX(0,T246-$E$8)*Inputs!$B$81-U246),MAX(0,G246-I246)),0) -> 0 | W246: =MAX(0,G246-I246-V246) -> 240000 | X246: =MAX(0,H246+J246-K246-U246) -> 900000 | Y246: =W246+X246 -> 1140000 | Z246: =T246-U246-V246 -> 129924.68
A247: =A246+1 -> 6 | B247: {=INDEX('Monthly Base'!$B$5:$B$67,A247+1)} -> OPEN | C247: {=INDEX('Monthly Base'!$C$5:$C$67,A247+1)} -> 4 | D247: {=INDEX('Monthly Base'!$O$5:$O$67,A247+1)} -> -3080.7458 | E247: {=INDEX('Monthly Base'!$Y$5:$Y$67,A247+1)} -> 0 | F247: =Z246 -> 129924.68 | G247: =W246 -> 240000 | H247: =X246 -> 900000 | I247: =IF(OR(A247<Inputs!$B$15,G247<=0),0,MIN(Financing!$B$10,G247)) -> 0 | J247: =IF(OR(A247<Inputs!$B$15,H247<=0),0,H247*Inputs!$B$13/12) -> 0 | K247: =IF(OR(A247<Inputs!$B$15,H247<=0),0,MIN(Financing!$C$10,H247+J247)) -> 0 | L247: =I247+K247 -> 0 | M247: =S246 -> 111438.05 | N247: =IF(B247="OPEN",IF(Y246=0,$E$7,IF(AND(C247>0,C247>=$E$5,$E$6>0),$E$6,0)),0) -> 0 | O247: =IF(B247="OPEN",IF(Y246=0,$E$7,IF(AND(C247>0,C247>=$E$5,$E$6>0),$E$6,0)),0) -> 0 | P247: =(N247+O247)*(1+$E$11) -> 0 | Q247: =D247-J247-IF(C247=0,0,Inputs!$B$18)-P247 -> -9893.7458 | R247: =MAX(0,Q247-M247)*Inputs!$B$17 -> 0 | S247: =MAX(0,M247-MAX(0,Q247))+MAX(0,-Q247) -> 121331.8 | T247: =F247+D247+E247-L247-P247-R247 -> 126843.93 | U247: =IF(AND(Inputs!$B$79=1,B247="OPEN",A247>=Inputs!$B$82,C247>=$E$10,MOD(C247-$E$10,$E$9)=0),MIN(MAX(0,T247-$E$8)*Inputs!$B$81,MAX(0,H247+J247-K247)),0) -> 0 | V247: =IF(AND(Inputs!$B$79=1,B247="OPEN",A247>=Inputs!$B$82,C247>=$E$10,MOD(C247-$E$10,$E$9)=0),MIN(MAX(0,MAX(0,T247-$E$8)*Inputs!$B$81-U247),MAX(0,G247-I247)),0) -> 0 | W247: =MAX(0,G247-I247-V247) -> 240000 | X247: =MAX(0,H247+J247-K247-U247) -> 900000 | Y247: =W247+X247 -> 1140000 | Z247: =T247-U247-V247 -> 126843.93
A248: =A247+1 -> 7 | B248: {=INDEX('Monthly Base'!$B$5:$B$67,A248+1)} -> OPEN | C248: {=INDEX('Monthly Base'!$C$5:$C$67,A248+1)} -> 5 | D248: {=INDEX('Monthly Base'!$O$5:$O$67,A248+1)} -> 474.02542 | E248: {=INDEX('Monthly Base'!$Y$5:$Y$67,A248+1)} -> 0 | F248: =Z247 -> 126843.93 | G248: =W247 -> 240000 | H248: =X247 -> 900000 | I248: =IF(OR(A248<Inputs!$B$15,G248<=0),0,MIN(Financing!$B$10,G248)) -> 0 | J248: =IF(OR(A248<Inputs!$B$15,H248<=0),0,H248*Inputs!$B$13/12) -> 0 | K248: =IF(OR(A248<Inputs!$B$15,H248<=0),0,MIN(Financing!$C$10,H248+J248)) -> 0 | L248: =I248+K248 -> 0 | M248: =S247 -> 121331.8 | N248: =IF(B248="OPEN",IF(Y247=0,$E$7,IF(AND(C248>0,C248>=$E$5,$E$6>0),$E$6,0)),0) -> 0 | O248: =IF(B248="OPEN",IF(Y247=0,$E$7,IF(AND(C248>0,C248>=$E$5,$E$6>0),$E$6,0)),0) -> 0 | P248: =(N248+O248)*(1+$E$11) -> 0 | Q248: =D248-J248-IF(C248=0,0,Inputs!$B$18)-P248 -> -6338.9746 | R248: =MAX(0,Q248-M248)*Inputs!$B$17 -> 0 | S248: =MAX(0,M248-MAX(0,Q248))+MAX(0,-Q248) -> 127670.77 | T248: =F248+D248+E248-L248-P248-R248 -> 127317.96 | U248: =IF(AND(Inputs!$B$79=1,B248="OPEN",A248>=Inputs!$B$82,C248>=$E$10,MOD(C248-$E$10,$E$9)=0),MIN(MAX(0,T248-$E$8)*Inputs!$B$81,MAX(0,H248+J248-K248)),0) -> 0 | V248: =IF(AND(Inputs!$B$79=1,B248="OPEN",A248>=Inputs!$B$82,C248>=$E$10,MOD(C248-$E$10,$E$9)=0),MIN(MAX(0,MAX(0,T248-$E$8)*Inputs!$B$81-U248),MAX(0,G248-I248)),0) -> 0 | W248: =MAX(0,G248-I248-V248) -> 240000 | X248: =MAX(0,H248+J248-K248-U248) -> 900000 | Y248: =W248+X248 -> 1140000 | Z248: =T248-U248-V248 -> 127317.96
A249: =A248+1 -> 8 | B249: {=INDEX('Monthly Base'!$B$5:$B$67,A249+1)} -> OPEN | C249: {=INDEX('Monthly Base'!$C$5:$C$67,A249+1)} -> 6 | D249: {=INDEX('Monthly Base'!$O$5:$O$67,A249+1)} -> 4028.7966 | E249: {=INDEX('Monthly Base'!$Y$5:$Y$67,A249+1)} -> 0 | F249: =Z248 -> 127317.96 | G249: =W248 -> 240000 | H249: =X248 -> 900000 | I249: =IF(OR(A249<Inputs!$B$15,G249<=0),0,MIN(Financing!$B$10,G249)) -> 0 | J249: =IF(OR(A249<Inputs!$B$15,H249<=0),0,H249*Inputs!$B$13/12) -> 0 | K249: =IF(OR(A249<Inputs!$B$15,H249<=0),0,MIN(Financing!$C$10,H249+J249)) -> 0 | L249: =I249+K249 -> 0 | M249: =S248 -> 127670.77 | N249: =IF(B249="OPEN",IF(Y248=0,$E$7,IF(AND(C249>0,C249>=$E$5,$E$6>0),$E$6,0)),0) -> 0 | O249: =IF(B249="OPEN",IF(Y248=0,$E$7,IF(AND(C249>0,C249>=$E$5,$E$6>0),$E$6,0)),0) -> 0 | P249: =(N249+O249)*(1+$E$11) -> 0 | Q249: =D249-J249-IF(C249=0,0,Inputs!$B$18)-P249 -> -2784.2034 | R249: =MAX(0,Q249-M249)*Inputs!$B$17 -> 0 | S249: =MAX(0,M249-MAX(0,Q249))+MAX(0,-Q249) -> 130454.97 | T249: =F249+D249+E249-L249-P249-R249 -> 131346.76 | U249: =IF(AND(Inputs!$B$79=1,B249="OPEN",A249>=Inputs!$B$82,C249>=$E$10,MOD(C249-$E$10,$E$9)=0),MIN(MAX(0,T249-$E$8)*Inputs!$B$81,MAX(0,H249+J249-K249)),0) -> 0 | V249: =IF(AND(Inputs!$B$79=1,B249="OPEN",A249>=Inputs!$B$82,C249>=$E$10,MOD(C249-$E$10,$E$9)=0),MIN(MAX(0,MAX(0,T249-$E$8)*Inputs!$B$81-U249),MAX(0,G249-I249)),0) -> 0 | W249: =MAX(0,G249-I249-V249) -> 240000 | X249: =MAX(0,H249+J249-K249-U249) -> 900000 | Y249: =W249+X249 -> 1140000 | Z249: =T249-U249-V249 -> 131346.76
A250: =A249+1 -> 9 | B250: {=INDEX('Monthly Base'!$B$5:$B$67,A250+1)} -> OPEN | C250: {=INDEX('Monthly Base'!$C$5:$C$67,A250+1)} -> 7 | D250: {=INDEX('Monthly Base'!$O$5:$O$67,A250+1)} -> 7770.661 | E250: {=INDEX('Monthly Base'!$Y$5:$Y$67,A250+1)} -> 0 | F250: =Z249 -> 131346.76 | G250: =W249 -> 240000 | H250: =X249 -> 900000 | I250: =IF(OR(A250<Inputs!$B$15,G250<=0),0,MIN(Financing!$B$10,G250)) -> 0 | J250: =IF(OR(A250<Inputs!$B$15,H250<=0),0,H250*Inputs!$B$13/12) -> 0 | K250: =IF(OR(A250<Inputs!$B$15,H250<=0),0,MIN(Financing!$C$10,H250+J250)) -> 0 | L250: =I250+K250 -> 0 | M250: =S249 -> 130454.97 | N250: =IF(B250="OPEN",IF(Y249=0,$E$7,IF(AND(C250>0,C250>=$E$5,$E$6>0),$E$6,0)),0) -> 5000 | O250: =IF(B250="OPEN",IF(Y249=0,$E$7,IF(AND(C250>0,C250>=$E$5,$E$6>0),$E$6,0)),0) -> 5000 | P250: =(N250+O250)*(1+$E$11) -> 12000 | Q250: =D250-J250-IF(C250=0,0,Inputs!$B$18)-P250 -> -11042.339 | R250: =MAX(0,Q250-M250)*Inputs!$B$17 -> 0 | S250: =MAX(0,M250-MAX(0,Q250))+MAX(0,-Q250) -> 141497.31 | T250: =F250+D250+E250-L250-P250-R250 -> 127117.42 | U250: =IF(AND(Inputs!$B$79=1,B250="OPEN",A250>=Inputs!$B$82,C250>=$E$10,MOD(C250-$E$10,$E$9)=0),MIN(MAX(0,T250-$E$8)*Inputs!$B$81,MAX(0,H250+J250-K250)),0) -> 0 | V250: =IF(AND(Inputs!$B$79=1,B250="OPEN",A250>=Inputs!$B$82,C250>=$E$10,MOD(C250-$E$10,$E$9)=0),MIN(MAX(0,MAX(0,T250-$E$8)*Inputs!$B$81-U250),MAX(0,G250-I250)),0) -> 0 | W250: =MAX(0,G250-I250-V250) -> 240000 | X250: =MAX(0,H250+J250-K250-U250) -> 900000 | Y250: =W250+X250 -> 1140000 | Z250: =T250-U250-V250 -> 127117.42
A251: =A250+1 -> 10 | B251: {=INDEX('Monthly Base'!$B$5:$B$67,A251+1)} -> OPEN | C251: {=INDEX('Monthly Base'!$C$5:$C$67,A251+1)} -> 8 | D251: {=INDEX('Monthly Base'!$O$5:$O$67,A251+1)} -> 11325.432 | E251: {=INDEX('Monthly Base'!$Y$5:$Y$67,A251+1)} -> 0 | F251: =Z250 -> 127117.42 | G251: =W250 -> 240000 | H251: =X250 -> 900000 | I251: =IF(OR(A251<Inputs!$B$15,G251<=0),0,MIN(Financing!$B$10,G251)) -> 0 | J251: =IF(OR(A251<Inputs!$B$15,H251<=0),0,H251*Inputs!$B$13/12) -> 0 | K251: =IF(OR(A251<Inputs!$B$15,H251<=0),0,MIN(Financing!$C$10,H251+J251)) -> 0 | L251: =I251+K251 -> 0 | M251: =S250 -> 141497.31 | N251: =IF(B251="OPEN",IF(Y250=0,$E$7,IF(AND(C251>0,C251>=$E$5,$E$6>0),$E$6,0)),0) -> 5000 | O251: =IF(B251="OPEN",IF(Y250=0,$E$7,IF(AND(C251>0,C251>=$E$5,$E$6>0),$E$6,0)),0) -> 5000 | P251: =(N251+O251)*(1+$E$11) -> 12000 | Q251: =D251-J251-IF(C251=0,0,Inputs!$B$18)-P251 -> -7487.5678 | R251: =MAX(0,Q251-M251)*Inputs!$B$17 -> 0 | S251: =MAX(0,M251-MAX(0,Q251))+MAX(0,-Q251) -> 148984.88 | T251: =F251+D251+E251-L251-P251-R251 -> 126442.85 | U251: =IF(AND(Inputs!$B$79=1,B251="OPEN",A251>=Inputs!$B$82,C251>=$E$10,MOD(C251-$E$10,$E$9)=0),MIN(MAX(0,T251-$E$8)*Inputs!$B$81,MAX(0,H251+J251-K251)),0) -> 0 | V251: =IF(AND(Inputs!$B$79=1,B251="OPEN",A251>=Inputs!$B$82,C251>=$E$10,MOD(C251-$E$10,$E$9)=0),MIN(MAX(0,MAX(0,T251-$E$8)*Inputs!$B$81-U251),MAX(0,G251-I251)),0) -> 0 | W251: =MAX(0,G251-I251-V251) -> 240000 | X251: =MAX(0,H251+J251-K251-U251) -> 900000 | Y251: =W251+X251 -> 1140000 | Z251: =T251-U251-V251 -> 126442.85
A252: =A251+1 -> 11 | B252: {=INDEX('Monthly Base'!$B$5:$B$67,A252+1)} -> OPEN | C252: {=INDEX('Monthly Base'!$C$5:$C$67,A252+1)} -> 9 | D252: {=INDEX('Monthly Base'!$O$5:$O$67,A252+1)} -> 14880.203 | E252: {=INDEX('Monthly Base'!$Y$5:$Y$67,A252+1)} -> 0 | F252: =Z251 -> 126442.85 | G252: =W251 -> 240000 | H252: =X251 -> 900000 | I252: =IF(OR(A252<Inputs!$B$15,G252<=0),0,MIN(Financing!$B$10,G252)) -> 0 | J252: =IF(OR(A252<Inputs!$B$15,H252<=0),0,H252*Inputs!$B$13/12) -> 0 | K252: =IF(OR(A252<Inputs!$B$15,H252<=0),0,MIN(Financing!$C$10,H252+J252)) -> 0 | L252: =I252+K252 -> 0 | M252: =S251 -> 148984.88 | N252: =IF(B252="OPEN",IF(Y251=0,$E$7,IF(AND(C252>0,C252>=$E$5,$E$6>0),$E$6,0)),0) -> 5000 | O252: =IF(B252="OPEN",IF(Y251=0,$E$7,IF(AND(C252>0,C252>=$E$5,$E$6>0),$E$6,0)),0) -> 5000 | P252: =(N252+O252)*(1+$E$11) -> 12000 | Q252: =D252-J252-IF(C252=0,0,Inputs!$B$18)-P252 -> -3932.7966 | R252: =MAX(0,Q252-M252)*Inputs!$B$17 -> 0 | S252: =MAX(0,M252-MAX(0,Q252))+MAX(0,-Q252) -> 152917.68 | T252: =F252+D252+E252-L252-P252-R252 -> 129323.05 | U252: =IF(AND(Inputs!$B$79=1,B252="OPEN",A252>=Inputs!$B$82,C252>=$E$10,MOD(C252-$E$10,$E$9)=0),MIN(MAX(0,T252-$E$8)*Inputs!$B$81,MAX(0,H252+J252-K252)),0) -> 0 | V252: =IF(AND(Inputs!$B$79=1,B252="OPEN",A252>=Inputs!$B$82,C252>=$E$10,MOD(C252-$E$10,$E$9)=0),MIN(MAX(0,MAX(0,T252-$E$8)*Inputs!$B$81-U252),MAX(0,G252-I252)),0) -> 0 | W252: =MAX(0,G252-I252-V252) -> 240000 | X252: =MAX(0,H252+J252-K252-U252) -> 900000 | Y252: =W252+X252 -> 1140000 | Z252: =T252-U252-V252 -> 129323.05
A253: =A252+1 -> 12 | B253: {=INDEX('Monthly Base'!$B$5:$B$67,A253+1)} -> OPEN | C253: {=INDEX('Monthly Base'!$C$5:$C$67,A253+1)} -> 10 | D253: {=INDEX('Monthly Base'!$O$5:$O$67,A253+1)} -> 18434.975 | E253: {=INDEX('Monthly Base'!$Y$5:$Y$67,A253+1)} -> 0 | F253: =Z252 -> 129323.05 | G253: =W252 -> 240000 | H253: =X252 -> 900000 | I253: =IF(OR(A253<Inputs!$B$15,G253<=0),0,MIN(Financing!$B$10,G253)) -> 4000 | J253: =IF(OR(A253<Inputs!$B$15,H253<=0),0,H253*Inputs!$B$13/12) -> 3562.5 | K253: =IF(OR(A253<Inputs!$B$15,H253<=0),0,MIN(Financing!$C$10,H253+J253)) -> 16881.221 | L253: =I253+K253 -> 20881.221 | M253: =S252 -> 152917.68 | N253: =IF(B253="OPEN",IF(Y252=0,$E$7,IF(AND(C253>0,C253>=$E$5,$E$6>0),$E$6,0)),0) -> 5000 | O253: =IF(B253="OPEN",IF(Y252=0,$E$7,IF(AND(C253>0,C253>=$E$5,$E$6>0),$E$6,0)),0) -> 5000 | P253: =(N253+O253)*(1+$E$11) -> 12000 | Q253: =D253-J253-IF(C253=0,0,Inputs!$B$18)-P253 -> -3940.5254 | R253: =MAX(0,Q253-M253)*Inputs!$B$17 -> 0 | S253: =MAX(0,M253-MAX(0,Q253))+MAX(0,-Q253) -> 156858.2 | T253: =F253+D253+E253-L253-P253-R253 -> 114876.81 | U253: =IF(AND(Inputs!$B$79=1,B253="OPEN",A253>=Inputs!$B$82,C253>=$E$10,MOD(C253-$E$10,$E$9)=0),MIN(MAX(0,T253-$E$8)*Inputs!$B$81,MAX(0,H253+J253-K253)),0) -> 0 | V253: =IF(AND(Inputs!$B$79=1,B253="OPEN",A253>=Inputs!$B$82,C253>=$E$10,MOD(C253-$E$10,$E$9)=0),MIN(MAX(0,MAX(0,T253-$E$8)*Inputs!$B$81-U253),MAX(0,G253-I253)),0) -> 0 | W253: =MAX(0,G253-I253-V253) -> 236000 | X253: =MAX(0,H253+J253-K253-U253) -> 886681.28 | Y253: =W253+X253 -> 1122681.3 | Z253: =T253-U253-V253 -> 114876.81
... A303: =A302+1 -> 62 | B303: {=INDEX('Monthly Base'!$B$5:$B$67,A303+1)} -> OPEN | C303: {=INDEX('Monthly Base'!$C$5:$C$67,A303+1)} -> 60 | D303: {=INDEX('Monthly Base'!$O$5:$O$67,A303+1)} -> 100568.9 | E303: {=INDEX('Monthly Base'!$Y$5:$Y$67,A303+1)} -> 0 | F303: =Z302 -> 1110435.9 | G303: =W302 -> 0 | H303: =X302 -> 0 | I303: =IF(OR(A303<Inputs!$B$15,G303<=0),0,MIN(Financing!$B$10,G303)) -> 0 | J303: =IF(OR(A303<Inputs!$B$15,H303<=0),0,H303*Inputs!$B$13/12) -> 0 | K303: =IF(OR(A303<Inputs!$B$15,H303<=0),0,MIN(Financing!$C$10,H303+J303)) -> 0 | L303: =I303+K303 -> 0 | M303: =S302 -> 0 | N303: =IF(B303="OPEN",IF(Y302=0,$E$7,IF(AND(C303>0,C303>=$E$5,$E$6>0),$E$6,0)),0) -> 10000 | O303: =IF(B303="OPEN",IF(Y302=0,$E$7,IF(AND(C303>0,C303>=$E$5,$E$6>0),$E$6,0)),0) -> 10000 | P303: =(N303+O303)*(1+$E$11) -> 24000 | Q303: =D303-J303-IF(C303=0,0,Inputs!$B$18)-P303 -> 69755.898 | R303: =MAX(0,Q303-M303)*Inputs!$B$17 -> 16043.857 | S303: =MAX(0,M303-MAX(0,Q303))+MAX(0,-Q303) -> 0 | T303: =F303+D303+E303-L303-P303-R303 -> 1170960.9 | U303: =IF(AND(Inputs!$B$79=1,B303="OPEN",A303>=Inputs!$B$82,C303>=$E$10,MOD(C303-$E$10,$E$9)=0),MIN(MAX(0,T303-$E$8)*Inputs!$B$81,MAX(0,H303+J303-K303)),0) -> 0 | V303: =IF(AND(Inputs!$B$79=1,B303="OPEN",A303>=Inputs!$B$82,C303>=$E$10,MOD(C303-$E$10,$E$9)=0),MIN(MAX(0,MAX(0,T303-$E$8)*Inputs!$B$81-U303),MAX(0,G303-I303)),0) -> 0 | W303: =MAX(0,G303-I303-V303) -> 0 | X303: =MAX(0,H303+J303-K303-U303) -> 0 | Y303: =W303+X303 -> 0 | Z303: =T303-U303-V303 -> 1170960.9

Sheet Monthly Cash Flow
A1: Shaar Binyamin Gym — Monthly Cash In / Cash Out
A2: Pure cash view of the current base case: actual modeled collections in, operating cash out, debt, tax, owner payroll, net monthly change, ending bank cash and debt. EBITDA/depreciation/DSCR are intentionally excluded here.
A4: Current base owner-pay policy | B4: Debt-Max | C4: Cash reserve target | D4: =Inputs!$B$80 -> 150000 | E4: Debt-free op month | F4: ='Owner Pay'!$B$9 -> 42 | G4: Debt sweep rule | H4: Every 6 months from op month 12 | I4: Alternative owner-pay plans | J4: See Salary Scenarios tab
A5: Opening bank cash is carried from the Owner Pay schedule. “Operating cash out” is the day-to-day gym cash burden required to reconcile gross collections to cash generation before debt, tax and owner payroll; it therefore captures the modeled net VAT effect without cluttering this owner view.
A6: Timeline Mo | B6: Phase | C6: Operating Mo | D6: Total Members | E6: Membership Cash In | F6: Other Cash In | G6: Startup VAT Refund | H6: Total Cash In | I6: Operating Cash Out | J6: Regular Debt Payment | K6: Lump-Sum Debt Payment | L6: Corporate Tax | M6: Owner Payroll | N6: Total Cash Out | O6: Net Cash Change | P6: Opening Bank Cash | Q6: Ending Bank Cash | R6: Debt Remaining | S6: Event | T6: Reserve Status
A7: =ROW()-7 -> 0 | B7: {=INDEX('Owner Pay'!$B$21:$B$83,A7+1)} -> BUILD | C7: {=INDEX('Owner Pay'!$C$21:$C$83,A7+1)} -> 0 | D7: {=INDEX('Monthly Base'!$G$5:$G$67,A7+1)} -> 0 | E7: {=INDEX('Monthly Base'!$I$5:$I$67,A7+1)} -> 0 | F7: {=INDEX('Monthly Base'!$J$5:$J$67,A7+1)} -> 0 | G7: {=INDEX('Owner Pay'!$E$21:$E$83,A7+1)} -> 0 | H7: =SUM(E7:G7) -> 0 | I7: {=E7+F7-INDEX('Owner Pay'!$D$21:$D$83,A7+1)} -> 20018 | J7: {=INDEX('Owner Pay'!$L$21:$L$83,A7+1)} -> 0 | K7: {=INDEX('Owner Pay'!$U$21:$U$83,A7+1)+INDEX('Owner Pay'!$V$21:$V$83,A7+1)} -> 0 | L7: {=INDEX('Owner Pay'!$R$21:$R$83,A7+1)} -> 0 | M7: {=INDEX('Owner Pay'!$P$21:$P$83,A7+1)} -> 0 | N7: =SUM(I7:M7) -> 20018 | O7: =H7-N7 -> -20018 | P7: {=INDEX('Owner Pay'!$F$21:$F$83,A7+1)} -> 68990.001 | Q7: {=INDEX('Owner Pay'!$Z$21:$Z$83,A7+1)} -> 48972.001 | R7: {=INDEX('Owner Pay'!$Y$21:$Y$83,A7+1)} -> 1140000 | S7: {=INDEX('Monthly Base'!$AD$5:$AD$67,A7+1)} -> Funding month 0 | T7: =IF(C7=0,"BUILD",IF(Q7<Inputs!$B$80,"BELOW RESERVE","OK")) -> BUILD
A8: =ROW()-7 -> 1 | B8: {=INDEX('Owner Pay'!$B$21:$B$83,A8+1)} -> BUILD | C8: {=INDEX('Owner Pay'!$C$21:$C$83,A8+1)} -> 0 | D8: {=INDEX('Monthly Base'!$G$5:$G$67,A8+1)} -> 0 | E8: {=INDEX('Monthly Base'!$I$5:$I$67,A8+1)} -> 0 | F8: {=INDEX('Monthly Base'!$J$5:$J$67,A8+1)} -> 0 | G8: {=INDEX('Owner Pay'!$E$21:$E$83,A8+1)} -> 0 | H8: =SUM(E8:G8) -> 0 | I8: {=E8+F8-INDEX('Owner Pay'!$D$21:$D$83,A8+1)} -> 20018 | J8: {=INDEX('Owner Pay'!$L$21:$L$83,A8+1)} -> 0 | K8: {=INDEX('Owner Pay'!$U$21:$U$83,A8+1)+INDEX('Owner Pay'!$V$21:$V$83,A8+1)} -> 0 | L8: {=INDEX('Owner Pay'!$R$21:$R$83,A8+1)} -> 0 | M8: {=INDEX('Owner Pay'!$P$21:$P$83,A8+1)} -> 0 | N8: =SUM(I8:M8) -> 20018 | O8: =H8-N8 -> -20018 | P8: {=INDEX('Owner Pay'!$F$21:$F$83,A8+1)} -> 48972.001 | Q8: {=INDEX('Owner Pay'!$Z$21:$Z$83,A8+1)} -> 28954.001 | R8: {=INDEX('Owner Pay'!$Y$21:$Y$83,A8+1)} -> 1140000 | S8: {=INDEX('Monthly Base'!$AD$5:$AD$67,A8+1)} | T8: =IF(C8=0,"BUILD",IF(Q8<Inputs!$B$80,"BELOW RESERVE","OK")) -> BUILD
A9: =ROW()-7 -> 2 | B9: {=INDEX('Owner Pay'!$B$21:$B$83,A9+1)} -> BUILD | C9: {=INDEX('Owner Pay'!$C$21:$C$83,A9+1)} -> 0 | D9: {=INDEX('Monthly Base'!$G$5:$G$67,A9+1)} -> 0 | E9: {=INDEX('Monthly Base'!$I$5:$I$67,A9+1)} -> 0 | F9: {=INDEX('Monthly Base'!$J$5:$J$67,A9+1)} -> 0 | G9: {=INDEX('Owner Pay'!$E$21:$E$83,A9+1)} -> 151933.73 | H9: =SUM(E9:G9) -> 151933.73 | I9: {=E9+F9-INDEX('Owner Pay'!$D$21:$D$83,A9+1)} -> 20018 | J9: {=INDEX('Owner Pay'!$L$21:$L$83,A9+1)} -> 0 | K9: {=INDEX('Owner Pay'!$U$21:$U$83,A9+1)+INDEX('Owner Pay'!$V$21:$V$83,A9+1)} -> 0 | L9: {=INDEX('Owner Pay'!$R$21:$R$83,A9+1)} -> 0 | M9: {=INDEX('Owner Pay'!$P$21:$P$83,A9+1)} -> 0 | N9: =SUM(I9:M9) -> 20018 | O9: =H9-N9 -> 131915.73 | P9: {=INDEX('Owner Pay'!$F$21:$F$83,A9+1)} -> 28954.001 | Q9: {=INDEX('Owner Pay'!$Z$21:$Z$83,A9+1)} -> 160869.73 | R9: {=INDEX('Owner Pay'!$Y$21:$Y$83,A9+1)} -> 1140000 | S9: {=INDEX('Monthly Base'!$AD$5:$AD$67,A9+1)} | T9: =IF(C9=0,"BUILD",IF(Q9<Inputs!$B$80,"BELOW RESERVE","OK")) -> BUILD
A10: =ROW()-7 -> 3 | B10: {=INDEX('Owner Pay'!$B$21:$B$83,A10+1)} -> OPEN | C10: {=INDEX('Owner Pay'!$C$21:$C$83,A10+1)} -> 1 | D10: {=INDEX('Monthly Base'!$G$5:$G$67,A10+1)} -> 238 | E10: {=INDEX('Monthly Base'!$I$5:$I$67,A10+1)} -> 53074 | F10: {=INDEX('Monthly Base'!$J$5:$J$67,A10+1)} -> 6500 | G10: {=INDEX('Owner Pay'!$E$21:$E$83,A10+1)} -> 0 | H10: =SUM(E10:G10) -> 59574 | I10: {=E10+F10-INDEX('Owner Pay'!$D$21:$D$83,A10+1)} -> 73506.153 | J10: {=INDEX('Owner Pay'!$L$21:$L$83,A10+1)} -> 0 | K10: {=INDEX('Owner Pay'!$U$21:$U$83,A10+1)+INDEX('Owner Pay'!$V$21:$V$83,A10+1)} -> 0 | L10: {=INDEX('Owner Pay'!$R$21:$R$83,A10+1)} -> 0 | M10: {=INDEX('Owner Pay'!$P$21:$P$83,A10+1)} -> 0 | N10: =SUM(I10:M10) -> 73506.153 | O10: =H10-N10 -> -13932.153 | P10: {=INDEX('Owner Pay'!$F$21:$F$83,A10+1)} -> 160869.73 | Q10: {=INDEX('Owner Pay'!$Z$21:$Z$83,A10+1)} -> 146937.58 | R10: {=INDEX('Owner Pay'!$Y$21:$Y$83,A10+1)} -> 1140000 | S10: {=INDEX('Monthly Base'!$AD$5:$AD$67,A10+1)} -> REOPEN | T10: =IF(C10=0,"BUILD",IF(Q10<Inputs!$B$80,"BELOW RESERVE","OK")) -> BELOW RESERVE
A11: =ROW()-7 -> 4 | B11: {=INDEX('Owner Pay'!$B$21:$B$83,A11+1)} -> OPEN | C11: {=INDEX('Owner Pay'!$C$21:$C$83,A11+1)} -> 2 | D11: {=INDEX('Monthly Base'!$G$5:$G$67,A11+1)} -> 257 | E11: {=INDEX('Monthly Base'!$I$5:$I$67,A11+1)} -> 57311 | F11: {=INDEX('Monthly Base'!$J$5:$J$67,A11+1)} -> 6500 | G11: {=INDEX('Owner Pay'!$E$21:$E$83,A11+1)} -> 0 | H11: =SUM(E11:G11) -> 63811 | I11: {=E11+F11-INDEX('Owner Pay'!$D$21:$D$83,A11+1)} -> 74188.381 | J11: {=INDEX('Owner Pay'!$L$21:$L$83,A11+1)} -> 0 | K11: {=INDEX('Owner Pay'!$U$21:$U$83,A11+1)+INDEX('Owner Pay'!$V$21:$V$83,A11+1)} -> 0 | L11: {=INDEX('Owner Pay'!$R$21:$R$83,A11+1)} -> 0 | M11: {=INDEX('Owner Pay'!$P$21:$P$83,A11+1)} -> 0 | N11: =SUM(I11:M11) -> 74188.381 | O11: =H11-N11 -> -10377.381 | P11: {=INDEX('Owner Pay'!$F$21:$F$83,A11+1)} -> 146937.58 | Q11: {=INDEX('Owner Pay'!$Z$21:$Z$83,A11+1)} -> 136560.2 | R11: {=INDEX('Owner Pay'!$Y$21:$Y$83,A11+1)} -> 1140000 | S11: {=INDEX('Monthly Base'!$AD$5:$AD$67,A11+1)} | T11: =IF(C11=0,"BUILD",IF(Q11<Inputs!$B$80,"BELOW RESERVE","OK")) -> BELOW RESERVE
A12: =ROW()-7 -> 5 | B12: {=INDEX('Owner Pay'!$B$21:$B$83,A12+1)} -> OPEN | C12: {=INDEX('Owner Pay'!$C$21:$C$83,A12+1)} -> 3 | D12: {=INDEX('Monthly Base'!$G$5:$G$67,A12+1)} -> 277 | E12: {=INDEX('Monthly Base'!$I$5:$I$67,A12+1)} -> 61771 | F12: {=INDEX('Monthly Base'!$J$5:$J$67,A12+1)} -> 6500 | G12: {=INDEX('Owner Pay'!$E$21:$E$83,A12+1)} -> 0 | H12: =SUM(E12:G12) -> 68271 | I12: {=E12+F12-INDEX('Owner Pay'!$D$21:$D$83,A12+1)} -> 74906.517 | J12: {=INDEX('Owner Pay'!$L$21:$L$83,A12+1)} -> 0 | K12: {=INDEX('Owner Pay'!$U$21:$U$83,A12+1)+INDEX('Owner Pay'!$V$21:$V$83,A12+1)} -> 0 | L12: {=INDEX('Owner Pay'!$R$21:$R$83,A12+1)} -> 0 | M12: {=INDEX('Owner Pay'!$P$21:$P$83,A12+1)} -> 0 | N12: =SUM(I12:M12) -> 74906.517 | O12: =H12-N12 -> -6635.5169 | P12: {=INDEX('Owner Pay'!$F$21:$F$83,A12+1)} -> 136560.2 | Q12: {=INDEX('Owner Pay'!$Z$21:$Z$83,A12+1)} -> 129924.68 | R12: {=INDEX('Owner Pay'!$Y$21:$Y$83,A12+1)} -> 1140000 | S12: {=INDEX('Monthly Base'!$AD$5:$AD$67,A12+1)} | T12: =IF(C12=0,"BUILD",IF(Q12<Inputs!$B$80,"BELOW RESERVE","OK")) -> BELOW RESERVE
A13: =ROW()-7 -> 6 | B13: {=INDEX('Owner Pay'!$B$21:$B$83,A13+1)} -> OPEN | C13: {=INDEX('Owner Pay'!$C$21:$C$83,A13+1)} -> 4 | D13: {=INDEX('Monthly Base'!$G$5:$G$67,A13+1)} -> 296 | E13: {=INDEX('Monthly Base'!$I$5:$I$67,A13+1)} -> 66008 | F13: {=INDEX('Monthly Base'!$J$5:$J$67,A13+1)} -> 6500 | G13: {=INDEX('Owner Pay'!$E$21:$E$83,A13+1)} -> 0 | H13: =SUM(E13:G13) -> 72508 | I13: {=E13+F13-INDEX('Owner Pay'!$D$21:$D$83,A13+1)} -> 75588.746 | J13: {=INDEX('Owner Pay'!$L$21:$L$83,A13+1)} -> 0 | K13: {=INDEX('Owner Pay'!$U$21:$U$83,A13+1)+INDEX('Owner Pay'!$V$21:$V$83,A13+1)} -> 0 | L13: {=INDEX('Owner Pay'!$R$21:$R$83,A13+1)} -> 0 | M13: {=INDEX('Owner Pay'!$P$21:$P$83,A13+1)} -> 0 | N13: =SUM(I13:M13) -> 75588.746 | O13: =H13-N13 -> -3080.7458 | P13: {=INDEX('Owner Pay'!$F$21:$F$83,A13+1)} -> 129924.68 | Q13: {=INDEX('Owner Pay'!$Z$21:$Z$83,A13+1)} -> 126843.93 | R13: {=INDEX('Owner Pay'!$Y$21:$Y$83,A13+1)} -> 1140000 | S13: {=INDEX('Monthly Base'!$AD$5:$AD$67,A13+1)} | T13: =IF(C13=0,"BUILD",IF(Q13<Inputs!$B$80,"BELOW RESERVE","OK")) -> BELOW RESERVE
A14: =ROW()-7 -> 7 | B14: {=INDEX('Owner Pay'!$B$21:$B$83,A14+1)} -> OPEN | C14: {=INDEX('Owner Pay'!$C$21:$C$83,A14+1)} -> 5 | D14: {=INDEX('Monthly Base'!$G$5:$G$67,A14+1)} -> 315 | E14: {=INDEX('Monthly Base'!$I$5:$I$67,A14+1)} -> 70245 | F14: {=INDEX('Monthly Base'!$J$5:$J$67,A14+1)} -> 6500 | G14: {=INDEX('Owner Pay'!$E$21:$E$83,A14+1)} -> 0 | H14: =SUM(E14:G14) -> 76745 | I14: {=E14+F14-INDEX('Owner Pay'!$D$21:$D$83,A14+1)} -> 76270.975 | J14: {=INDEX('Owner Pay'!$L$21:$L$83,A14+1)} -> 0 | K14: {=INDEX('Owner Pay'!$U$21:$U$83,A14+1)+INDEX('Owner Pay'!$V$21:$V$83,A14+1)} -> 0 | L14: {=INDEX('Owner Pay'!$R$21:$R$83,A14+1)} -> 0 | M14: {=INDEX('Owner Pay'!$P$21:$P$83,A14+1)} -> 0 | N14: =SUM(I14:M14) -> 76270.975 | O14: =H14-N14 -> 474.02542 | P14: {=INDEX('Owner Pay'!$F$21:$F$83,A14+1)} -> 126843.93 | Q14: {=INDEX('Owner Pay'!$Z$21:$Z$83,A14+1)} -> 127317.96 | R14: {=INDEX('Owner Pay'!$Y$21:$Y$83,A14+1)} -> 1140000 | S14: {=INDEX('Monthly Base'!$AD$5:$AD$67,A14+1)} | T14: =IF(C14=0,"BUILD",IF(Q14<Inputs!$B$80,"BELOW RESERVE","OK")) -> BELOW RESERVE
A15: =ROW()-7 -> 8 | B15: {=INDEX('Owner Pay'!$B$21:$B$83,A15+1)} -> OPEN | C15: {=INDEX('Owner Pay'!$C$21:$C$83,A15+1)} -> 6 | D15: {=INDEX('Monthly Base'!$G$5:$G$67,A15+1)} -> 334 | E15: {=INDEX('Monthly Base'!$I$5:$I$67,A15+1)} -> 74482 | F15: {=INDEX('Monthly Base'!$J$5:$J$67,A15+1)} -> 6500 | G15: {=INDEX('Owner Pay'!$E$21:$E$83,A15+1)} -> 0 | H15: =SUM(E15:G15) -> 80982 | I15: {=E15+F15-INDEX('Owner Pay'!$D$21:$D$83,A15+1)} -> 76953.203 | J15: {=INDEX('Owner Pay'!$L$21:$L$83,A15+1)} -> 0 | K15: {=INDEX('Owner Pay'!$U$21:$U$83,A15+1)+INDEX('Owner Pay'!$V$21:$V$83,A15+1)} -> 0 | L15: {=INDEX('Owner Pay'!$R$21:$R$83,A15+1)} -> 0 | M15: {=INDEX('Owner Pay'!$P$21:$P$83,A15+1)} -> 0 | N15: =SUM(I15:M15) -> 76953.203 | O15: =H15-N15 -> 4028.7966 | P15: {=INDEX('Owner Pay'!$F$21:$F$83,A15+1)} -> 127317.96 | Q15: {=INDEX('Owner Pay'!$Z$21:$Z$83,A15+1)} -> 131346.76 | R15: {=INDEX('Owner Pay'!$Y$21:$Y$83,A15+1)} -> 1140000 | S15: {=INDEX('Monthly Base'!$AD$5:$AD$67,A15+1)} | T15: =IF(C15=0,"BUILD",IF(Q15<Inputs!$B$80,"BELOW RESERVE","OK")) -> BELOW RESERVE
A16: =ROW()-7 -> 9 | B16: {=INDEX('Owner Pay'!$B$21:$B$83,A16+1)} -> OPEN | C16: {=INDEX('Owner Pay'!$C$21:$C$83,A16+1)} -> 7 | D16: {=INDEX('Monthly Base'!$G$5:$G$67,A16+1)} -> 354 | E16: {=INDEX('Monthly Base'!$I$5:$I$67,A16+1)} -> 78942 | F16: {=INDEX('Monthly Base'!$J$5:$J$67,A16+1)} -> 6500 | G16: {=INDEX('Owner Pay'!$E$21:$E$83,A16+1)} -> 0 | H16: =SUM(E16:G16) -> 85442 | I16: {=E16+F16-INDEX('Owner Pay'!$D$21:$D$83,A16+1)} -> 77671.339 | J16: {=INDEX('Owner Pay'!$L$21:$L$83,A16+1)} -> 0 | K16: {=INDEX('Owner Pay'!$U$21:$U$83,A16+1)+INDEX('Owner Pay'!$V$21:$V$83,A16+1)} -> 0 | L16: {=INDEX('Owner Pay'!$R$21:$R$83,A16+1)} -> 0 | M16: {=INDEX('Owner Pay'!$P$21:$P$83,A16+1)} -> 0 | N16: =SUM(I16:M16) -> 77671.339 | O16: =H16-N16 -> 7770.661 | P16: {=INDEX('Owner Pay'!$F$21:$F$83,A16+1)} -> 131346.76 | Q16: {=INDEX('Owner Pay'!$Z$21:$Z$83,A16+1)} -> 139117.42 | R16: {=INDEX('Owner Pay'!$Y$21:$Y$83,A16+1)} -> 1140000 | S16: {=INDEX('Monthly Base'!$AD$5:$AD$67,A16+1)} | T16: =IF(C16=0,"BUILD",IF(Q16<Inputs!$B$80,"BELOW RESERVE","OK")) -> BELOW RESERVE
A17: =ROW()-7 -> 10 | B17: {=INDEX('Owner Pay'!$B$21:$B$83,A17+1)} -> OPEN | C17: {=INDEX('Owner Pay'!$C$21:$C$83,A17+1)} -> 8 | D17: {=INDEX('Monthly Base'!$G$5:$G$67,A17+1)} -> 373 | E17: {=INDEX('Monthly Base'!$I$5:$I$67,A17+1)} -> 83179 | F17: {=INDEX('Monthly Base'!$J$5:$J$67,A17+1)} -> 6500 | G17: {=INDEX('Owner Pay'!$E$21:$E$83,A17+1)} -> 0 | H17: =SUM(E17:G17) -> 89679 | I17: {=E17+F17-INDEX('Owner Pay'!$D$21:$D$83,A17+1)} -> 78353.568 | J17: {=INDEX('Owner Pay'!$L$21:$L$83,A17+1)} -> 0 | K17: {=INDEX('Owner Pay'!$U$21:$U$83,A17+1)+INDEX('Owner Pay'!$V$21:$V$83,A17+1)} -> 0 | L17: {=INDEX('Owner Pay'!$R$21:$R$83,A17+1)} -> 0 | M17: {=INDEX('Owner Pay'!$P$21:$P$83,A17+1)} -> 0 | N17: =SUM(I17:M17) -> 78353.568 | O17: =H17-N17 -> 11325.432 | P17: {=INDEX('Owner Pay'!$F$21:$F$83,A17+1)} -> 139117.42 | Q17: {=INDEX('Owner Pay'!$Z$21:$Z$83,A17+1)} -> 150442.85 | R17: {=INDEX('Owner Pay'!$Y$21:$Y$83,A17+1)} -> 1140000 | S17: {=INDEX('Monthly Base'!$AD$5:$AD$67,A17+1)} | T17: =IF(C17=0,"BUILD",IF(Q17<Inputs!$B$80,"BELOW RESERVE","OK")) -> OK
A18: =ROW()-7 -> 11 | B18: {=INDEX('Owner Pay'!$B$21:$B$83,A18+1)} -> OPEN | C18: {=INDEX('Owner Pay'!$C$21:$C$83,A18+1)} -> 9 | D18: {=INDEX('Monthly Base'!$G$5:$G$67,A18+1)} -> 392 | E18: {=INDEX('Monthly Base'!$I$5:$I$67,A18+1)} -> 87416 | F18: {=INDEX('Monthly Base'!$J$5:$J$67,A18+1)} -> 6500 | G18: {=INDEX('Owner Pay'!$E$21:$E$83,A18+1)} -> 0 | H18: =SUM(E18:G18) -> 93916 | I18: {=E18+F18-INDEX('Owner Pay'!$D$21:$D$83,A18+1)} -> 79035.797 | J18: {=INDEX('Owner Pay'!$L$21:$L$83,A18+1)} -> 0 | K18: {=INDEX('Owner Pay'!$U$21:$U$83,A18+1)+INDEX('Owner Pay'!$V$21:$V$83,A18+1)} -> 0 | L18: {=INDEX('Owner Pay'!$R$21:$R$83,A18+1)} -> 0 | M18: {=INDEX('Owner Pay'!$P$21:$P$83,A18+1)} -> 0 | N18: =SUM(I18:M18) -> 79035.797 | O18: =H18-N18 -> 14880.203 | P18: {=INDEX('Owner Pay'!$F$21:$F$83,A18+1)} -> 150442.85 | Q18: {=INDEX('Owner Pay'!$Z$21:$Z$83,A18+1)} -> 165323.05 | R18: {=INDEX('Owner Pay'!$Y$21:$Y$83,A18+1)} -> 1140000 | S18: {=INDEX('Monthly Base'!$AD$5:$AD$67,A18+1)} | T18: =IF(C18=0,"BUILD",IF(Q18<Inputs!$B$80,"BELOW RESERVE","OK")) -> OK
... A69: =ROW()-7 -> 62 | B69: {=INDEX('Owner Pay'!$B$21:$B$83,A69+1)} -> OPEN | C69: {=INDEX('Owner Pay'!$C$21:$C$83,A69+1)} -> 60 | D69: {=INDEX('Monthly Base'!$G$5:$G$67,A69+1)} -> 850 | E69: {=INDEX('Monthly Base'!$I$5:$I$67,A69+1)} -> 189550 | F69: {=INDEX('Monthly Base'!$J$5:$J$67,A69+1)} -> 6500 | G69: {=INDEX('Owner Pay'!$E$21:$E$83,A69+1)} -> 0 | H69: =SUM(E69:G69) -> 196050 | I69: {=E69+F69-INDEX('Owner Pay'!$D$21:$D$83,A69+1)} -> 95481.102 | J69: {=INDEX('Owner Pay'!$L$21:$L$83,A69+1)} -> 0 | K69: {=INDEX('Owner Pay'!$U$21:$U$83,A69+1)+INDEX('Owner Pay'!$V$21:$V$83,A69+1)} -> 0 | L69: {=INDEX('Owner Pay'!$R$21:$R$83,A69+1)} -> 21563.857 | M69: {=INDEX('Owner Pay'!$P$21:$P$83,A69+1)} -> 0 | N69: =SUM(I69:M69) -> 117044.96 | O69: =H69-N69 -> 79005.042 | P69: {=INDEX('Owner Pay'!$F$21:$F$83,A69+1)} -> 1723385.7 | Q69: {=INDEX('Owner Pay'!$Z$21:$Z$83,A69+1)} -> 1802390.8 | R69: {=INDEX('Owner Pay'!$Y$21:$Y$83,A69+1)} -> 0 | S69: {=INDEX('Monthly Base'!$AD$5:$AD$67,A69+1)} -> YEAR END | T69: =IF(C69=0,"BUILD",IF(Q69<Inputs!$B$80,"BELOW RESERVE","OK")) -> OK

Sheet Sources
A1: Sources
A3: Source | B3: Used for | C3: Reference / URL | D3: Notes
A4: Claude diligence dump | B4: Verified Jump actuals, rebuild model, tax notes, risks, sensitivity inputs | C4: Uploaded gym_dump.md | D4: Primary new source
A5: Consultant business plan | B5: Market, original budget/pricing/startup assumptions | C5: Uploaded PDF: תוכנית עסקית ופרוגרמה -מכון כושר -שער בנימין- גרשון ראפ-9.2026.pdf | D5: Original consultant source
A6: Eurotec quote PQ26001443 | B6: Exact professional equipment cost and VAT | C6: Uploaded PDF: מועצה איזורית מטה בנימין.pdf | D6: 399,076.27 ex VAT / 470,910 incl VAT
A7: Gym_Model_v17.xlsx | B7: Historical Jump member mix, receipts, renewal timing and legacy costs | C7: Uploaded workbook | D7: Reference / diligence
A8: Bank of Israel 01/09/2026 | B8: Policy rate 3.25% | C8: https://www.boi.org.il/en/communication-and-publications/press-releases/01-9-26-en/ | D8: Effective 03/09/2026
A9: Prime convention | B9: Prime = BOI policy rate + 1.5% | C9: https://mortgage.leumi.co.il/Articles/39 | D9: Current modeled Prime 4.75%
A10: User clarification | B10: Grace | C10: This conversation | D10: No payments, no interest, no extra cost during grace
A11: User clarification | B11: Pricing | C11: This conversation | D11: 230 full access / 190 single service / 150 soldiers
A12: User clarification | B12: Owner pay | C12: This conversation | D12: Salaries only when economically logical
A13: Audit treatment | B13: 75k run-in | C13: This workbook | D13: Working-capital reserve in base, not upfront VATable invoice
A14: Audit treatment | B14: VAT cash | C14: This workbook | D14: Avoids subtracting VAT twice after using ex-VAT economics
